Workbook
Name _Ref94102448: IIS_Costs!$B$3
Name _Ref94103649: IIS_Costs!$B$14

Sheet Legend
A1: OMNIA Model
A2: Document type: | B2: BY and NewTech Template
A3: Region: | B3: Global
A4: Sector: | B4: Industry - Detailed sectors | C4: IND
A5: Base-year | B5: 2019
A6: Developer: | B6: UCL
A7: Version: | B7: 0.4
A8: Date: | B8: =TODAY() -> 46163
A9: Document description: | B9: This template holds the structure of the Final Energy Consumption in the Industrial sectors - Industry Sector
A12: Tab colour legend
B13: VEDA-TIMES data input tables
B14: Raw input data
B15: Processed raw input data
B16: EnergyBalance
A18: Table of contents
A19: Sheet | B19: Description
A20: Commodities | B20: Veda inputs: Definition of sector commodities
A21: EnergyBalance | B21: Industry energy balance
A22: Inputs_BY IIS | B22: Processing of energy balance data for input into BY template
A23: IIS_BY Techs | B23: Veda inputs: Characterization of IIS base-year technologies
A24: IIS_New Techs | B24: Veda inputs: Characterization of IIS new technologies
A25: IIS_Prod | B25: Steel production statistics (PIOLab)
A26: IIS_Capacity | B26: Steel plant capacity (Global Energy Monitor)
A27: IIS_Costs | B27: Steel production technology costs
A28: Inputs_BY INM | B28: Processing of energy balance data for input into BY template
A29: Inputs_NT INM | B29: New tech data for non-cement technologies
A30: INM_BY Techs | B30: Veda inputs: Characterization of INM base-year technologies
... A35: Cem_NewTechs | B35: Cement production cost estimates
A36: IAL_INF_Techs
A37: INF_Commodities
A38: INF_BY | B38: Veda inputs: Characterization of INF base-year technologies
A39: INF_NewTech | B39: Veda inputs: Characterization of INF new technologies
A40: INF_Data
A44: Conversion factors
A45: EUR2015 | B45: =1.0778*1.0599 -> 1.1423602 | C45: USD2021
A46: USD2019 | B46: 1.06 | C46: USD2021
A47: EUR2022 | B47: 0.88346756 | C47: EUR2019
A48: EUR2019 | B48: 1.1234 | C48: USD2019
A49: GBP2017 | B49: 1.29 | C49: USD2017
A50: EUR2015 | B50: 1.05 | C50: EUR2019
A51: GW | B51: =60*60*8760*10^-6 -> 31.536 | C51: PJ-y
A52: kg H2G | B52: =120*10^-3 -> 0.12 | C52: GJ
A54: Inflator / Deflator (USA) | B54: https://data.worldbank.org/indicator/FP.CPI.TOTL?locations=US
A55: 2005 | B55: 89.560532
A56: 2006 | B56: 92.449705
A57: 2007 | B57: 95.086992
A58: 2008 | B58: 98.737477
A59: 2009 | B59: 98.38642
A60: 2010 | B60: 100
A61: 2011 | B61: 103.15684
A62: 2012 | B62: 105.2915
A63: 2013 | B63: 106.83385
A64: 2014 | B64: 108.56693
A65: 2015 | B65: 108.69572
A66: 2016 | B66: 110.06701
... A73: 2023 | B73: 139.73579
A76: Emission Factors | B76: Are these needed here?
A77: Natural Gas | B77: 56 | C77: kgCO2/GJ
A78: Coal | B78: 96 | C78: kgCO2/GJ
A80: Codes for processes and commodities names
A81: Dimension | B81: Code | C81: Notes
A82: Sub-sectors
A83: Iron and steel | B83: IS
A84: Non-metallic minerals | B84: NM
A85: Chemicals | B85: CH
A86: Pulp and paper | B86: PP
A87: Wood products | B87: WP
A88: Non-ferrous metals | B88: NF
A89: Other industries | B89: OI
A90: Generic manufacturing processes
A91: High temperature heat | B91: HTH
A92: Low temperature heat | B92: LTH
A93: Machine drive | B93: MDR
A94: Other services | B94: OTS
A95: Generic fuel types
A96: Blast furnace gas | B96: INDBFG
A97: Biogas | B97: INDBGS
A98: Biomass | B98: INDBIO
A99: Bioliquids | B99: INDBLQ
A100: Coal | B100: INDCOA
A101: Coke oven gas | B101: INDCOG
A102: Coke oven coke | B102: INDCOK
A103: Electricity | B103: INDELC
A104: Natural gas | B104: INDGAS
A105: Heat | B105: INDHET
A106: LPG | B106: INDLPG
A107: Oil | B107: INDOIL
... A110: Waste | B110: INDWAS
A111: Hydrogen | B111: INDH2G | C111: Gaseous hydrogen
A112: Natural gas H2 blend | B112: INDH2B
A114: Emissions
A115: CO2eq | B115: INDCO2e | C115: CO2 equivalent: includes all GHG (e.g. CO2, CH4, N2O)
A116: CO2 | B116: INDCO2 | C116: Carbon dioxide
A117: CH4 | B117: INDCH4 | C117: Methane
A118: N2O | B118: INDN2O | C118: Nitrous oxide
A119: CO2 process | B119: INDCO2p | C119: Carbon dioxide
A120: CO2 process | B120: INDCO2c | C120: Carbon dioxide from combustion
A123: Model regions
A124: Model regions | B124: Description | C124: List of countries
A125: AFE | B125: Eastern Africa
...

Sheet LOG
A2: LOG TABLE
A3: Date | B3: TAB | C3: CELL(s) | D3: Description of the change
A4: 45784 | B4: IIS_BY Techs | C4: AF29 | D4: Round very small number for INDELC in MEA to 0
A5: 45785 | B5: Inputs_NT INM | C5: T460-T462 | D5: Change INDELC share to 100% from 0%
A6: 45785 | B6: Inputs_NT INM | C6: T472,T484,T496 | D6: Change INDELC share to 100% from 0%
A7: 45785 | B7: INF_Data | C7: G170-AH170 | D7: Rounded primary IAL demands to minimum 1kt
A8: 45785 | B8: INF_Data | C8: G229-AH229 | D8: Rounded secondary IAL demands to minimum 1kt
A9: 45790 | B9: IIS_BY Techs | C9: J34-AK34 | D9: Corrected formula to point to correct values
A10: 45790 | B10: Inputs_BY INM | C10: E128-AF128, E147-AF147 | D10: Electricity intensity factors corrected to account for assumed split between dry and wet kilns
A11: 45790 | B11: Inputs_BY INM | C11: E121:AF135 & E140:AF154 | D11: Calculations adjusted slightly to ensure full calibration, using the clinker production value in row 35, not row 31
A12: 45814 | B12: Inputs_BY INM | C12: E128-AF128, E147-AF147 | D12: Electricity intensity factors corrected to factor in clinker (not cement) production
A13: 45819 | B13: INF_Data | C13: G232-AH232 | D13: Updated regional secondary aluminium production in base year to align with ENGAGE. Only minor changes
A14: 45831 | B14: INF_Data | C14: Rows 437-449 | D14: Add new/adjust aluminium scrap cost data
A15: 45831 | B15: INF_BY | C15: F147-AI147 | D15: Add ACT_COST for aluminium scrap
... A23: 46007 | B23: IIS_New Techs | C23: G17:G20 | D23: Initial year for steel techs with CCS 2035 instead of 2030
A24: 46013 | B24: EnergyBalance | D24: Nigeria biomass consumption updated
A25: 46106 | B25: Inputs_NT INM | D25: Enabled (0%->100%) OIL techs in Table 16 fuel shares for ASO - previously set to 100%

Sheet Commodities
B1: Commodities definition
B3: ~FI_Comm
B4: Csets | C4: CommName | D4: CommDesc | E4: Unit | F4: LimType | G4: CTSLvl | H4: PeakTS | I4: Ctype
B5: *Commodity set | C5: Commodity name | D5: Description | E5: Unit of measure
B6: NRG | C6: =Legend!B96 -> INDBFG | D6: =Legend!A96&" ("&Legend!$C$4&")" -> Blast furnace gas (IND) | E6: PJ
B7: NRG | C7: =Legend!B97 -> INDBGS | D7: =Legend!A97&" ("&Legend!$C$4&")" -> Biogas (IND) | E7: PJ
B8: NRG | C8: =Legend!B98 -> INDBIO | D8: =Legend!A98&" ("&Legend!$C$4&")" -> Biomass (IND) | E8: PJ
B9: NRG | C9: =Legend!B99 -> INDBLQ | D9: =Legend!A99&" ("&Legend!$C$4&")" -> Bioliquids (IND) | E9: PJ
B10: NRG | C10: =Legend!B100 -> INDCOA | D10: =Legend!A100&" ("&Legend!$C$4&")" -> Coal (IND) | E10: PJ
B11: NRG | C11: =Legend!B101 -> INDCOG | D11: =Legend!A101&" ("&Legend!$C$4&")" -> Coke oven gas (IND) | E11: PJ
B12: NRG | C12: =Legend!B102 -> INDCOK | D12: =Legend!A102&" ("&Legend!$C$4&")" -> Coke oven coke (IND) | E12: PJ
B13: NRG | C13: =Legend!B103 -> INDELC | D13: =Legend!A103&" ("&Legend!$C$4&")" -> Electricity (IND) | E13: PJ | G13: DayNite | I13: ELC
B14: NRG | C14: =Legend!B104 -> INDGAS | D14: =Legend!A104&" ("&Legend!$C$4&")" -> Natural gas (IND) | E14: PJ
B15: NRG | C15: =Legend!B105 -> INDHET | D15: =Legend!A105&" ("&Legend!$C$4&")" -> Heat (IND) | E15: PJ | G15: DayNite | I15: LTHEAT
B16: NRG | C16: =Legend!B106 -> INDLPG | D16: =Legend!A106&" ("&Legend!$C$4&")" -> LPG (IND) | E16: PJ
B17: NRG | C17: =Legend!B107 -> INDOIL | D17: =Legend!A107&" ("&Legend!$C$4&")" -> Oil (IND) | E17: PJ
B18: NRG | C18: =Legend!B108 -> INDGEO | D18: =Legend!A108&" ("&Legend!$C$4&")" -> Geothermal (IND) | E18: PJ
B19: NRG | C19: =Legend!B109 -> INDCSP | D19: =Legend!A109&" ("&Legend!$C$4&")" -> Concentrated solar power (IND) | E19: PJ
B20: NRG | C20: =Legend!B110 -> INDWAS | D20: =Legend!A110&" ("&Legend!$C$4&")" -> Waste (IND) | E20: PJ
B21: NRG | C21: =Legend!B111 -> INDH2G | D21: =Legend!A111&" ("&Legend!$C$4&")" -> Hydrogen (IND) | E21: PJ
B22: NRG | C22: =Legend!B112 -> INDH2B | D22: =Legend!A112&" ("&Legend!$C$4&")" -> Natural gas H2 blend (IND) | E22: PJ
B23: ENV | C23: =Legend!B115 -> INDCO2e | D23: =Legend!A115&" emissions ("&Legend!$C$4&")" -> CO2eq emissions (IND) | E23: kt
B24: ENV | C24: =Legend!B116 -> INDCO2 | D24: =Legend!A116&" emissions ("&Legend!$C$4&")" -> CO2 emissions (IND) | E24: kt
B25: ENV | C25: =Legend!B117 -> INDCH4 | D25: =Legend!A117&" emissions ("&Legend!$C$4&")" -> CH4 emissions (IND) | E25: kt
B26: ENV | C26: =Legend!B118 -> INDN2O | D26: =Legend!A118&" emissions ("&Legend!$C$4&")" -> N2O emissions (IND) | E26: kt
B27: ENV | C27: =Legend!B119 -> INDCO2p | D27: =Legend!A119&" emissions ("&Legend!$C$4&")" -> CO2 process emissions (IND) | E27: kt
B28: ENV | C28: =Legend!B120 -> INDCO2c | D28: =Legend!A120&" emissions ("&Legend!$C$4&")" -> CO2 process emissions (IND) | E28: kt

Sheet EnergyBalance
A2: Industry Sector Final Energy Balances | G2: Source: | H2: Omnia_Energy_Balance_NEW_29_4_2024.xlsx
A4: ** All sectors are included here as this workbook will include multiple sectors**
A7: Subsector | B7: Subsector extended | C7: Primary energy commoditiy | D7: Unit | E7: AFE | F7: AFN | G7: AFW | H7: AFZ | I7: ANZ | J7: ASC | K7: ASE | L7: ASO | M7: BRA | N7: CAN | O7: CHL | P7: CHN | Q7: ENE | R7: ENW | S7: EUE | T7: EUM | U7: EUW | V7: IDN | W7: IND | X7: JPN | Y7: LAM | Z7: MDA | AA7: MEA | AB7: MEX | AC7: NIG | AD7: RUS | AE7: SKT | AF7: USA
A8: ICH | B8: Chemical and petrochemical | C8: INDBFG | D8: TJ | E8: 0 | F8: 0 | G8: 0 | H8: 0 | I8: 0 | J8: 0 | K8: 0 | L8: 0 | M8: 0 | N8: 0 | O8: 0 | P8: 3872 | Q8: 0 | R8: 312 | S8: 0 | T8: 0 | U8: 0 | V8: 0 | W8: 0 | X8: 4355 | Y8: 0 | Z8: 0 | AA8: 0 | AB8: 0 | AC8: 0 | AD8: 0 | AE8: 0 | AF8: 0
A9: ICH | B9: Chemical and petrochemical | C9: INDBGS | D9: TJ | E9: 0 | F9: 0 | G9: 0 | H9: 0 | I9: 0 | J9: 0 | K9: 25868 | L9: 0 | M9: 0 | N9: 0 | O9: 0 | P9: 0 | Q9: 20 | R9: 231 | S9: 110 | T9: 288 | U9: 1049 | V9: 0 | W9: 0 | X9: 0 | Y9: 0 | Z9: 0 | AA9: 0 | AB9: 0 | AC9: 0 | AD9: 0 | AE9: 329 | AF9: 263
A10: ICH | B10: Chemical and petrochemical | C10: INDBIO | D10: TJ | E10: 0 | F10: 209 | G10: 0 | H10: 0 | I10: 805 | J10: 0 | K10: 14207 | L10: 0 | M10: 2409 | N10: 0 | O10: 0 | P10: 33478 | Q10: 1427 | R10: 6599 | S10: 3069 | T10: 5215 | U10: 5060 | V10: 1203 | W10: 0 | X10: 1198 | Y10: 131 | Z10: 0 | AA10: 0 | AB10: 0 | AC10: 0 | AD10: 937 | AE10: 42 | AF10: 2981
A11: ICH | B11: Chemical and petrochemical | C11: INDBLQ | D11: TJ | E11: 0 | F11: 0 | G11: 0 | H11: 0 | I11: 0 | J11: 0 | K11: 0 | L11: 0 | M11: 44 | N11: 0 | O11: 0 | P11: 0 | Q11: 0 | R11: 72 | S11: 0 | T11: 157 | U11: 158 | V11: 19 | W11: 0 | X11: 0 | Y11: 0 | Z11: 0 | AA11: 0 | AB11: 0 | AC11: 0 | AD11: 0 | AE11: 0 | AF11: 1175
A12: ICH | B12: Chemical and petrochemical | C12: INDCOA | D12: TJ | E12: 0 | F12: 0 | G12: 0 | H12: 4796 | I12: 6396 | J12: 533 | K12: 2454 | L12: 0 | M12: 7304 | N12: 0 | O12: 0 | P12: 116413 | Q12: 838 | R12: 9564 | S12: 66719 | T12: 18264 | U12: 11731 | V12: 101851 | W12: 30912 | X12: 111548 | Y12: 3673 | Z12: 24018 | AA12: 0 | AB12: 0 | AC12: 0 | AD12: 7332 | AE12: 3070 | AF12: 66661
A13: ICH | B13: Chemical and petrochemical | C13: INDCOG | D13: TJ | E13: 0 | F13: 0 | G13: 0 | H13: 0 | I13: 0 | J13: 0 | K13: 0 | L13: 0 | M13: 0 | N13: 0 | O13: 0 | P13: 150491 | Q13: 0 | R13: 0 | S13: 671 | T13: 0 | U13: 3394 | V13: 0 | W13: 0 | X13: 27491 | Y13: 0 | Z13: 0 | AA13: 0 | AB13: 0 | AC13: 0 | AD13: 0 | AE13: 0 | AF13: 0
A14: ICH | B14: Chemical and petrochemical | C14: INDCOK | D14: TJ | E14: 0 | F14: 0 | G14: 0 | H14: 0 | I14: 469 | J14: 9110 | K14: 0 | L14: 0 | M14: 0 | N14: 0 | O14: 0 | P14: 699489 | Q14: 0 | R14: 1370 | S14: 2292 | T14: 671 | U14: 790 | V14: 0 | W14: 0 | X14: 1115 | Y14: 14 | Z14: 0 | AA14: 0 | AB14: 0 | AC14: 0 | AD14: 789 | AE14: 0 | AF14: 0
A15: ICH | B15: Chemical and petrochemical | C15: INDELC | D15: TJ | E15: 0 | F15: 12999 | G15: 1909 | H15: 31764 | I15: 15540 | J15: 35450 | K15: 51209 | L15: 0 | M15: 75578 | N15: 75244 | O15: 130 | P15: 1953857 | Q15: 32295 | R15: 91866 | S15: 83617 | T15: 164051 | U15: 349051 | V15: 23501 | W15: 0 | X15: 202335 | Y15: 24125 | Z15: 24849 | AA15: 35292 | AB15: 20678 | AC15: 0 | AD15: 171581 | AE15: 190670 | AF15: 448024
A16: ICH | B16: Chemical and petrochemical | C16: INDGAS | D16: TJ | E16: 0 | F16: 6872 | G16: 0 | H16: 46571 | I16: 84406 | J16: 99351 | K16: 66636 | L16: 0 | M16: 76880 | N16: 146119 | O16: 5934 | P16: 1240400 | Q16: 17746 | R16: 81196 | S16: 84753 | T16: 284828 | U16: 382352 | V16: 39902 | W16: 0 | X16: 82509 | Y16: 72722 | Z16: 61902 | AA16: 706309 | AB16: 108561 | AC16: 17601 | AD16: 352442 | AE16: 37425 | AF16: 2285644
A17: ICH | B17: Chemical and petrochemical | C17: INDHET | D17: TJ | E17: 0 | F17: 0 | G17: 0 | H17: 0 | I17: 0 | J17: 13945 | K17: 0 | L17: 0 | M17: 0 | N17: 10533 | O17: 0 | P17: 1451781 | Q17: 52441 | R17: 12193 | S17: 50107 | T17: 83809 | U17: 191417 | V17: 0 | W17: 0 | X17: 0 | Y17: 0 | Z17: 0 | AA17: 0 | AB17: 0 | AC17: 0 | AD17: 518995 | AE17: 86325 | AF17: 122317
A18: ICH | B18: Chemical and petrochemical | C18: INDLPG | D18: TJ | E18: 0 | F18: 1986 | G18: 0 | H18: 0 | I18: 0 | J18: 477 | K18: 56025 | L18: 0 | M18: 8876 | N18: 0 | O18: 0 | P18: 427300 | Q18: 741 | R18: 3163 | S18: 14021 | T18: 4344 | U18: 49361 | V18: 1215 | W18: 0 | X18: 22356 | Y18: 173 | Z18: 94 | AA18: 7816 | AB18: 473 | AC18: 0 | AD18: 195735 | AE18: 9674 | AF18: 4532
A19: ICH | B19: Chemical and petrochemical | C19: INDOIL | D19: TJ | E19: 0 | F19: 1806 | G19: 979 | H19: 265 | I19: 4471 | J19: 1596 | K19: 103233 | L19: 0 | M19: 99262 | N19: 939 | O19: 0 | P19: 230833 | Q19: 2603 | R19: 16586 | S19: 65936 | T19: 29816 | U19: 163150 | V19: 14807 | W19: 522444 | X19: 339577 | Y19: 9573 | Z19: 415 | AA19: 11112 | AB19: 8703 | AC19: 0 | AD19: 199657 | AE19: 22505 | AF19: 64628
... A100: IOI | B100: Other industries | C100: INDWAS | D100: TJ | E100: 0 | F100: 0 | G100: 28 | H100: 0 | I100: 102 | J100: 0 | K100: 2536 | L100: 0 | M100: 0 | N100: 0 | O100: 0 | P100: 0 | Q100: 0 | R100: 2259 | S100: 1350 | T100: 1863 | U100: 18583 | V100: 0 | W100: 0 | X100: 14610 | Y100: 524 | Z100: 18139 | AA100: 0 | AB100: 0 | AC100: 0 | AD100: 50558 | AE100: 27480 | AF100: 8864
A103: **Other industries is further broken down into further subsectors below [based on file Other_industries_breakdown]
A106: Subsector | B106: Subsector extended | C106: Primary energy commoditiy | D106: Unit | E106: AFE | F106: AFN | G106: AFW | H106: AFZ | I106: ANZ | J106: ASC | K106: ASE | L106: ASO | M106: BRA | N106: CAN | O106: CHL | P106: CHN | Q106: ENE | R106: ENW | S106: EUE | T106: EUM | U106: EUW | V106: IDN | W106: IND | X106: JPN | Y106: LAM | Z106: MDA | AA106: MEA | AB106: MEX | AC106: NIG | AD106: RUS | AE106: SKT | AF106: USA
A107: IPP | B107: Pulp and paper | C107: INDBFG | D107: TJ | E107: 0 | F107: 0 | G107: 0 | H107: 0 | I107: 0 | J107: 0 | K107: 0 | L107: 0 | M107: 0 | N107: 0 | O107: 0 | P107: 0 | Q107: 0 | R107: 0 | S107: 0 | T107: 0 | U107: 0 | V107: 0 | W107: 0 | X107: 0 | Y107: 0 | Z107: 0 | AA107: 0 | AB107: 0 | AC107: 0 | AD107: 0 | AE107: 0 | AF107: 0
A108: IPP | B108: Pulp and paper | C108: INDBGS | D108: TJ | E108: 0 | F108: 0 | G108: 0 | H108: 0 | I108: 24 | J108: 0 | K108: 0 | L108: 0 | M108: 0 | N108: 2384 | O108: 0 | P108: 0 | Q108: 0 | R108: 432 | S108: 214 | T108: 1380 | U108: 6490 | V108: 0 | W108: 0 | X108: 0 | Y108: 0 | Z108: 0 | AA108: 0 | AB108: 0 | AC108: 0 | AD108: 0 | AE108: 71 | AF108: 166
A109: IPP | B109: Pulp and paper | C109: INDBIO | D109: TJ | E109: 0 | F109: 0 | G109: 0 | H109: 0 | I109: 3804 | J109: 0 | K109: 12520 | L109: 0 | M109: 269175 | N109: 0 | O109: 0 | P109: 17361 | Q109: 94 | R109: 19586 | S109: 52923 | T109: 19229 | U109: 47954 | V109: 0 | W109: 0 | X109: 0 | Y109: 4636 | Z109: 0 | AA109: 0 | AB109: 0 | AC109: 363 | AD109: 200 | AE109: 497 | AF109: 1208840
A110: IPP | B110: Pulp and paper | C110: INDBLQ | D110: TJ | E110: 0 | F110: 0 | G110: 0 | H110: 0 | I110: 0 | J110: 0 | K110: 0 | L110: 0 | M110: 644 | N110: 0 | O110: 0 | P110: 0 | Q110: 0 | R110: 0 | S110: 0 | T110: 14 | U110: 510 | V110: 1 | W110: 0 | X110: 0 | Y110: 0 | Z110: 0 | AA110: 0 | AB110: 0 | AC110: 0 | AD110: 0 | AE110: 0 | AF110: 21226
A111: IPP | B111: Pulp and paper | C111: INDCOA | D111: TJ | E111: 0 | F111: 0 | G111: 0 | H111: 3062 | I111: 1779 | J111: 81 | K111: 453 | L111: 0 | M111: 5548 | N111: 0 | O111: 0 | P111: 0 | Q111: 17 | R111: 2742 | S111: 12594 | T111: 221 | U111: 18007 | V111: 0 | W111: 23957 | X111: 67833 | Y111: 15020 | Z111: 8793 | AA111: 0 | AB111: 0 | AC111: 0 | AD111: 1 | AE111: 0 | AF111: 42872
A112: IPP | B112: Pulp and paper | C112: INDCOG | D112: TJ | E112: 0 | F112: 0 | G112: 0 | H112: 0 | I112: 0 | J112: 0 | K112: 0 | L112: 0 | M112: 0 | N112: 0 | O112: 0 | P112: 0 | Q112: 0 | R112: 0 | S112: 0 | T112: 0 | U112: 0 | V112: 0 | W112: 0 | X112: 0 | Y112: 0 | Z112: 0 | AA112: 0 | AB112: 0 | AC112: 0 | AD112: 0 | AE112: 0 | AF112: 0
A113: IPP | B113: Pulp and paper | C113: INDCOK | D113: TJ | E113: 0 | F113: 0 | G113: 0 | H113: 0 | I113: 0 | J113: 0 | K113: 0 | L113: 0 | M113: 0 | N113: 0 | O113: 0 | P113: 0 | Q113: 0 | R113: 0 | S113: 0 | T113: 0 | U113: 0 | V113: 0 | W113: 0 | X113: 692 | Y113: 155 | Z113: 0 | AA113: 0 | AB113: 0 | AC113: 0 | AD113: 2 | AE113: 0 | AF113: 0
A114: IPP | B114: Pulp and paper | C114: INDELC | D114: TJ | E114: 0 | F114: 2010 | G114: 153 | H114: 4189 | I114: 18120 | J114: 1044 | K114: 10983 | L114: 0 | M114: 84362 | N114: 157442 | O114: 20663 | P114: 0 | Q114: 8412 | R114: 58643 | S114: 46620 | T114: 100908 | U114: 264159 | V114: 5684 | W114: 0 | X114: 144400 | Y114: 12931 | Z114: 13741 | AA114: 0 | AB114: 12553 | AC114: 0 | AD114: 74277 | AE114: 45081 | AF114: 289778
A115: IPP | B115: Pulp and paper | C115: INDGAS | D115: TJ | E115: 0 | F115: 2396 | G115: 0 | H115: 605 | I115: 13168 | J115: 2303 | K115: 11368 | L115: 0 | M115: 36524 | N115: 91874 | O115: 5687 | P115: 0 | Q115: 2876 | R115: 19931 | S115: 35007 | T115: 95493 | U115: 148349 | V115: 0 | W115: 0 | X115: 33026 | Y115: 5546 | Z115: 9092 | AA115: 0 | AB115: 34247 | AC115: 0 | AD115: 26042 | AE115: 12681 | AF115: 358012
A116: IPP | B116: Pulp and paper | C116: INDHET | D116: TJ | E116: 0 | F116: 0 | G116: 0 | H116: 0 | I116: 0 | J116: 727 | K116: 0 | L116: 0 | M116: 0 | N116: 4980 | O116: 0 | P116: 0 | Q116: 13044 | R116: 2579 | S116: 7024 | T116: 44303 | U116: 48204 | V116: 0 | W116: 0 | X116: 0 | Y116: 0 | Z116: 0 | AA116: 0 | AB116: 0 | AC116: 0 | AD116: 203739 | AE116: 11389 | AF116: 20016
A117: IPP | B117: Pulp and paper | C117: INDLPG | D117: TJ | E117: 0 | F117: 8 | G117: 0 | H117: 0 | I117: 113 | J117: 14 | K117: 311 | L117: 0 | M117: 2902 | N117: 0 | O117: 546 | P117: 1276 | Q117: 56 | R117: 94 | S117: 405 | T117: 1425 | U117: 4213 | V117: 273 | W117: 0 | X117: 2936 | Y117: 156 | Z117: 0 | AA117: 0 | AB117: 281 | AC117: 0 | AD117: 135 | AE117: 238 | AF117: 1410
A118: IPP | B118: Pulp and paper | C118: INDOIL | D118: TJ | E118: 0 | F118: 816 | G118: 0 | H118: 175 | I118: 2007 | J118: 136 | K118: 6462 | L118: 0 | M118: 17855 | N118: 2166 | O118: 2395 | P118: 16131 | Q118: 828 | R118: 2573 | S118: 1957 | T118: 5412 | U118: 10114 | V118: 188 | W118: 0 | X118: 34659 | Y118: 1341 | Z118: -66 | AA118: 0 | AB118: 9487 | AC118: 0 | AD118: 10059 | AE118: 517 | AF118: 3574
... A215: INS | B215: Not elsewhere specified (industry) | C215: INDWAS | D215: TJ | E215: 0 | F215: 0 | G215: 28 | H215: 0 | I215: 0 | J215: 0 | K215: 2536 | L215: 0 | M215: 0 | N215: 0 | O215: 0 | P215: 0 | Q215: 0 | R215: 506 | S215: 13 | T215: 1198 | U215: 135 | V215: 0 | W215: 0 | X215: 0 | Y215: 241 | Z215: 5662 | AA215: 0 | AB215: 0 | AC215: 0 | AD215: 146 | AE215: 5012 | AF215: 2524
A220: ** Whilst blast furnace is a conversion sector in the energy balance, it has been included in the Iron and steel sector due to being an integral part of the BF-BOF process**
A222: Blast Furnace - Transformation Inputs
AI223: INDCOA | AJ223: =SUMIFS(AF8:AF100,C8:C100,AI223) -> 455517
B225: Subsector | C225: Primary energy commoditiy | D225: Unit | E225: AFE | F225: AFN | G225: AFW | H225: AFZ | I225: ANZ | J225: ASC | K225: ASE | L225: ASO | M225: BRA | N225: CAN | O225: CHL | P225: CHN | Q225: ENE | R225: ENW | S225: EUE | T225: EUM | U225: EUW | V225: IDN | W225: IND | X225: JPN | Y225: LAM | Z225: MDA | AA225: MEA | AB225: MEX | AC225: NIG | AD225: RUS | AE225: SKT | AF225: USA
B226: Blast furnace | C226: UPSBIO | D226: TJ | E226: 0 | F226: 0 | G226: 0 | H226: 0 | I226: 0 | J226: 0 | K226: 0 | L226: 0 | M226: 0 | N226: 0 | O226: 0 | P226: 0 | Q226: 0 | R226: 0 | S226: 0 | T226: 0 | U226: -24 | V226: 0 | W226: 0 | X226: 0 | Y226: 0 | Z226: 0 | AA226: 0 | AB226: 0 | AC226: 0 | AD226: 0 | AE226: 0 | AF226: 0
B227: Blast furnace | C227: UPSCOA | D227: TJ | E227: 0 | F227: -508 | G227: 0 | H227: 0 | I227: -1642 | J227: 0 | K227: 0 | L227: 0 | M227: 0 | N227: 0 | O227: 0 | P227: 0 | Q227: -6389 | R227: -30162 | S227: -30101 | T227: -94630 | U227: -241100 | V227: -7779 | W227: -68539 | X227: -349069 | Y227: 0 | Z227: -27762 | AA227: 0 | AB227: 0 | AC227: 0 | AD227: -67280 | AE227: -202209 | AF227: -26858
B228: Blast furnace | C228: UPSCOK | D228: TJ | E228: 0 | F228: -16215 | G228: 0 | H228: -45329 | I228: -52807 | J228: -56573 | K228: -4858 | L228: 0 | M228: 0 | N228: -52955 | O228: -8024 | P228: -9761909 | Q228: -257714 | R228: -62348 | S228: -192455 | T228: -162461 | U228: -461002 | V228: 0 | W228: -1020695 | X228: -812199 | Y228: -20353 | Z228: -95610 | AA228: -35292 | AB228: -39121 | AC228: 0 | AD228: -478411 | AE228: -413916 | AF228: -239829
B229: Blast furnace | C229: UPSGAS | D229: TJ | E229: 0 | F229: 0 | G229: 0 | H229: 0 | I229: 0 | J229: 0 | K229: 0 | L229: 0 | M229: 0 | N229: 0 | O229: 0 | P229: 0 | Q229: 0 | R229: 0 | S229: -1181 | T229: 0 | U229: 0 | V229: 0 | W229: 0 | X229: 0 | Y229: 0 | Z229: 0 | AA229: 0 | AB229: 0 | AC229: 0 | AD229: 0 | AE229: 0 | AF229: 0
B230: Blast furnace | C230: UPSHFO | D230: TJ | E230: 0 | F230: 0 | G230: 0 | H230: 0 | I230: 0 | J230: -5074 | K230: 0 | L230: 0 | M230: 0 | N230: 0 | O230: 0 | P230: 0 | Q230: 0 | R230: 0 | S230: 0 | T230: 0 | U230: -1414 | V230: 0 | W230: 0 | X230: 0 | Y230: 0 | Z230: 0 | AA230: 0 | AB230: 0 | AC230: 0 | AD230: 0 | AE230: 0 | AF230: 0
B231: Blast furnace | C231: UPSOIL2 | D231: TJ | E231: 0 | F231: 0 | G231: 0 | H231: 0 | I231: 0 | J231: 0 | K231: 0 | L231: 0 | M231: 0 | N231: 0 | O231: 0 | P231: 0 | Q231: 0 | R231: 0 | S231: 0 | T231: 0 | U231: 0 | V231: 0 | W231: 0 | X231: 0 | Y231: -31850 | Z231: 0 | AA231: 0 | AB231: 0 | AC231: 0 | AD231: 0 | AE231: 0 | AF231: 0
A233: Blast Furnace - Transformation Outputs
B236: Subsector | C236: Primary energy commoditiy | D236: Unit | E236: AFE | F236: AFN | G236: AFW | H236: AFZ | I236: ANZ | J236: ASC | K236: ASE | L236: ASO | M236: BRA | N236: CAN | O236: CHL | P236: CHN | Q236: ENE | R236: ENW | S236: EUE | T236: EUM | U236: EUW | V236: IDN | W236: IND | X236: JPN | Y236: LAM | Z236: MDA | AA236: MEA | AB236: MEX | AC236: NIG | AD236: RUS | AE236: SKT | AF236: USA
B237: Blast furnace | C237: UPSBFG | D237: TJ | E237: 0 | F237: 3350 | G237: 0 | H237: 18142 | I237: 23635 | J237: 17821 | K237: 2654 | L237: 0 | M237: 0 | N237: 22913 | O237: 2355 | P237: 4375053 | Q237: 85166 | R237: 36844 | S237: 88202 | T237: 116913 | U237: 265080 | V237: 3260 | W237: 444595 | X237: 410945 | Y237: 10451 | Z237: 49991 | AA237: 14213 | AB237: 16062 | AC237: 0 | AD237: 214602 | AE237: 225861 | AF237: 110352
A241: Energy Industry Own Uses
A244: Subsector | B244: Subsector extended | C244: Primary energy commoditiy | D244: Unit | E244: AFE | F244: AFN | G244: AFW | H244: AFZ | I244: ANZ | J244: ASC | K244: ASE | L244: ASO | M244: BRA | N244: CAN | O244: CHL | P244: CHN | Q244: ENE | R244: ENW | S244: EUE | T244: EUM | U244: EUW | V244: IDN | W244: IND | X244: JPN | Y244: LAM | Z244: MDA | AA244: MEA | AB244: MEX | AC244: NIG | AD244: RUS | AE244: SKT | AF244: USA
A245: OTH OwnUses | B245: Other energy industries own use | C245: UPSBDL | D245: TJ | E245: 0 | F245: 0 | G245: 0 | H245: 0 | I245: 0 | J245: 0 | K245: 0 | L245: 0 | M245: 0 | N245: 0 | O245: 0 | P245: 0 | Q245: 0 | R245: 0 | S245: 0 | T245: 0 | U245: -543 | V245: 0 | W245: 0 | X245: 0 | Y245: -1 | Z245: 0 | AA245: 0 | AB245: 0 | AC245: 0 | AD245: 0 | AE245: 0 | AF245: -4232
A246: OTH OwnUses | B246: Other energy industries own use | C246: UPSBFG | D246: TJ | E246: 0 | F246: 0 | G246: 0 | H246: 0 | I246: -17056 | J246: -7930 | K246: 0 | L246: 0 | M246: 0 | N246: 0 | O246: -2355 | P246: -10093 | Q246: -4662 | R246: -11808 | S246: -18248 | T246: -63424 | U246: -48103 | V246: 0 | W246: 0 | X246: -57681 | Y246: -6969 | Z246: -27198 | AA246: -4105 | AB246: -11648 | AC246: 0 | AD246: -3778 | AE246: -103554 | AF246: -22022
A247: OTH OwnUses | B247: Other energy industries own use | C247: UPSBGS | D247: TJ | E247: 0 | F247: 0 | G247: 0 | H247: 0 | I247: 0 | J247: 0 | K247: 0 | L247: 0 | M247: 0 | N247: 0 | O247: 0 | P247: 0 | Q247: 0 | R247: 0 | S247: -511 | T247: 0 | U247: -20479 | V247: 0 | W247: 0 | X247: 0 | Y247: 0 | Z247: 0 | AA247: 0 | AB247: 0 | AC247: 0 | AD247: 0 | AE247: 0 | AF247: 0
A248: OTH OwnUses | B248: Other energy industries own use | C248: UPSBIO | D248: TJ | E248: -28 | F248: 0 | G248: 0 | H248: -207 | I248: 0 | J248: 0 | K248: 0 | L248: 0 | M248: -548933 | N248: 0 | O248: 0 | P248: -559 | Q248: -20 | R248: 0 | S248: -21 | T248: 0 | U248: -1515 | V248: 0 | W248: 0 | X248: 0 | Y248: -1423 | Z248: 0 | AA248: 0 | AB248: 0 | AC248: 0 | AD248: 0 | AE248: 0 | AF248: 0
A249: OTH OwnUses | B249: Other energy industries own use | C249: UPSCOA | D249: TJ | E249: 0 | F249: 0 | G249: -144 | H249: -671813 | I249: -663 | J249: -8349 | K249: 0 | L249: 0 | M249: 0 | N249: 0 | O249: 0 | P249: -3434146 | Q249: -585 | R249: 0 | S249: -5861 | T249: 0 | U249: -6879 | V249: -61472 | W249: -4367 | X249: -4696 | Y249: 0 | Z249: -466 | AA249: 0 | AB249: 0 | AC249: 0 | AD249: -9538 | AE249: 0 | AF249: -480
A250: OTH OwnUses | B250: Other energy industries own use | C250: UPSCOALIG | D250: TJ | E250: 0 | F250: 0 | G250: 0 | H250: 0 | I250: 0 | J250: -32 | K250: 0 | L250: 0 | M250: 0 | N250: 0 | O250: 0 | P250: 0 | Q250: -1188 | R250: 0 | S250: -10281 | T250: 0 | U250: -6426 | V250: 0 | W250: 0 | X250: 0 | Y250: 0 | Z250: 0 | AA250: 0 | AB250: 0 | AC250: 0 | AD250: -579 | AE250: 0 | AF250: 0
A251: OTH OwnUses | B251: Other energy industries own use | C251: UPSCOG | D251: TJ | E251: 0 | F251: 0 | G251: 0 | H251: 0 | I251: -21373 | J251: -14455 | K251: 0 | L251: 0 | M251: -8330 | N251: 0 | O251: -3550 | P251: -372815 | Q251: -30644 | R251: -6800 | S251: -59201 | T251: -4583 | U251: -32600 | V251: 0 | W251: -81463 | X251: -58700 | Y251: -1746 | Z251: -15277 | AA251: -2632 | AB251: 0 | AC251: 0 | AD251: -42118 | AE251: -38388 | AF251: -28274
A252: OTH OwnUses | B252: Other energy industries own use | C252: UPSCOK | D252: TJ | E252: 0 | F252: 0 | G252: 0 | H252: -770 | I252: 0 | J252: 0 | K252: 0 | L252: 0 | M252: 0 | N252: 0 | O252: 0 | P252: -26683 | Q252: 0 | R252: 0 | S252: 0 | T252: -1645 | U252: 0 | V252: -197 | W252: 0 | X252: 0 | Y252: 0 | Z252: 0 | AA252: 0 | AB252: -1576 | AC252: 0 | AD252: 0 | AE252: 0 | AF252: 0
A253: OTH OwnUses | B253: Other energy industries own use | C253: UPSDSL | D253: TJ | E253: 0 | F253: -33926 | G253: -3968 | H253: -48904 | I253: -159640 | J253: -16706 | K253: -1522 | L253: 0 | M253: -175273 | N253: -342937 | O253: 0 | P253: -138111 | Q253: -8559 | R253: -123339 | S253: -10071 | T253: -7047 | U253: -6439 | V253: -113921 | W253: 0 | X253: -3532 | Y253: -32311 | Z253: -5122 | AA253: -70757 | AB253: 0 | AC253: -207 | AD253: -354574 | AE253: -2099 | AF253: -426368
A254: OTH OwnUses | B254: Other energy industries own use | C254: UPSELC | D254: TJ | E254: -210 | F254: -7152 | G254: -668 | H254: -70609 | I254: -84729 | J254: -51550 | K254: -1379 | L254: 0 | M254: -90504 | N254: -116481 | O254: -2687 | P254: -986324 | Q254: -34281 | R254: -75995 | S254: -94148 | T254: -135774 | U254: -134942 | V254: 0 | W254: -20322 | X254: -79157 | Y254: -27079 | Z254: -18100 | AA254: -81908 | AB254: -13148 | AC254: -871 | AD254: -625035 | AE254: -62755 | AF254: -544338
A255: OTH OwnUses | B255: Other energy industries own use | C255: UPSGAS | D255: TJ | E255: 0 | F255: -406496 | G255: -6102 | H255: -19837 | I255: -382216 | J255: -422657 | K255: -614008 | L255: -17690 | M255: -261424 | N255: -1437495 | O255: -7867 | P255: -859008 | Q255: -46489 | R255: -383907 | S255: -104535 | T255: -221812 | U255: -196778 | V255: -201102 | W255: -311978 | X255: -32802 | Y255: -605638 | Z255: -65247 | AA255: -1822634 | AB255: -630004 | AC255: -220441 | AD255: -687267 | AE255: -4605 | AF255: -2757393
A256: OTH OwnUses | B256: Other energy industries own use | C256: UPSGSL | D256: TJ | E256: 0 | F256: 0 | G256: 0 | H256: 0 | I256: -3 | J256: 0 | K256: 0 | L256: 0 | M256: 0 | N256: -2546 | O256: 0 | P256: -10106 | Q256: 0 | R256: 0 | S256: -19 | T256: -1 | U256: -6 | V256: -2715 | W256: 0 | X256: -22 | Y256: -4668 | Z256: 0 | AA256: 0 | AB256: 0 | AC256: 0 | AD256: 0 | AE256: 0 | AF256: -195536
... A264: OTH OwnUses | B264: Other energy industries own use | C264: UPSWAS | D264: TJ | E264: 0 | F264: 0 | G264: 0 | H264: 0 | I264: 0 | J264: 0 | K264: 0 | L264: 0 | M264: 0 | N264: 0 | O264: 0 | P264: 0 | Q264: 0 | R264: 0 | S264: 0 | T264: 0 | U264: -2159 | V264: 0 | W264: 0 | X264: 0 | Y264: 0 | Z264: 0 | AA264: 0 | AB264: 0 | AC264: 0 | AD264: -5683 | AE264: 0 | AF264: 0
A268: ** It is not clear whether the own use by blast furnaces needs to be accounted for. The exception might be BFG to capture emissions from use; however care is need to avoid emissions double counting**
A270: % of Other energy industries own use computed from UN Energy statistics.
A271: Supplied by M Pied in Own_uses_Blastfurnaces.xlsx
B273: Subsector | C273: Commodity | D273: Unit | E273: AFE | F273: AFN | G273: AFW | H273: AFZ | I273: ANZ | J273: ASC | K273: ASE | L273: ASO | M273: BRA | N273: CAN | O273: CHL | P273: CHN | Q273: ENE | R273: ENW | S273: EUE | T273: EUM | U273: EUW | V273: IDN | W273: IND | X273: JPN | Y273: LAM | Z273: MDA | AA273: MEA | AB273: MEX | AC273: NIG | AD273: RUS | AE273: SKT | AF273: USA
B274: Own use by blast furnaces | C274: UPSBDL | D274: % of Other energy industries own use | E274: 0 | F274: 0 | G274: 0 | H274: 0 | I274: 0 | J274: 0 | K274: 0 | L274: 0 | M274: 0 | N274: 0 | O274: 0 | P274: 0 | Q274: 0 | R274: 0 | S274: 0 | T274: 1 | U274: 0 | V274: 0 | W274: 0 | X274: 0 | Y274: 0 | Z274: 0 | AA274: 0 | AB274: 0 | AC274: 0 | AD274: 0 | AE274: 0 | AF274: 0
B275: Own use by blast furnaces | C275: UPSBFG | D275: % of Other energy industries own use | E275: 0 | F275: 0 | G275: 0 | H275: 0 | I275: 0.97987576 | J275: 1 | K275: 0 | L275: 0 | M275: 0 | N275: 0 | O275: 1 | P275: 0 | Q275: 1 | R275: 0.82906619 | S275: 0.6617061 | T275: 0.58951572 | U275: 0.52865562 | V275: 0 | W275: 0 | X275: 0 | Y275: 1 | Z275: 0.66413642 | AA275: 0 | AB275: 1 | AC275: 0 | AD275: 0 | AE275: 0.52775425 | AF275: 0.98219962
B276: Own use by blast furnaces | C276: UPSBGS | D276: % of Other energy industries own use | E276: 0 | F276: 0 | G276: 0 | H276: 0 | I276: 0 | J276: 0 | K276: 0 | L276: 0 | M276: 0 | N276: 0 | O276: 0 | P276: 0 | Q276: 0 | R276: 0 | S276: 0 | T276: 0 | U276: 0 | V276: 0 | W276: 0 | X276: 0 | Y276: 0 | Z276: 0 | AA276: 0 | AB276: 0 | AC276: 0 | AD276: 0 | AE276: 0 | AF276: 0
B277: Own use by blast furnaces | C277: UPSBIO | D277: % of Other energy industries own use | E277: 0 | F277: 0 | G277: 0 | H277: 0 | I277: 0 | J277: 0 | K277: 0 | L277: 0 | M277: 0 | N277: 0 | O277: 0 | P277: 0 | Q277: 0 | R277: 0 | S277: 0 | T277: 0 | U277: 0 | V277: 0 | W277: 0 | X277: 0 | Y277: 0 | Z277: 0 | AA277: 0 | AB277: 0 | AC277: 0 | AD277: 0 | AE277: 0 | AF277: 0
B278: Own use by blast furnaces | C278: UPSCOA | D278: % of Other energy industries own use | E278: 0 | F278: 0 | G278: 0 | H278: 0 | I278: 0 | J278: 0 | K278: 0 | L278: 0 | M278: 0 | N278: 0 | O278: 0 | P278: 0 | Q278: 0 | R278: 0 | S278: 0 | T278: 0 | U278: 0.044383051 | V278: 0 | W278: 0 | X278: 0 | Y278: 0 | Z278: 0 | AA278: 0 | AB278: 0 | AC278: 0 | AD278: 0 | AE278: 0 | AF278: 0
B279: Own use by blast furnaces | C279: UPSCOALIG | D279: % of Other energy industries own use | E279: 0 | F279: 0 | G279: 0 | H279: 0 | I279: 0 | J279: 0 | K279: 0 | L279: 0 | M279: 0 | N279: 0 | O279: 0 | P279: 0 | Q279: 0 | R279: 0 | S279: 0 | T279: 0 | U279: 0 | V279: 0 | W279: 0 | X279: 0 | Y279: 0 | Z279: 0 | AA279: 0 | AB279: 0 | AC279: 0 | AD279: 0 | AE279: 0 | AF279: 0
B280: Own use by blast furnaces | C280: UPSCOG | D280: % of Other energy industries own use | E280: 0 | F280: 0 | G280: 0 | H280: 0 | I280: 0 | J280: 0 | K280: 0 | L280: 0 | M280: 0 | N280: 0 | O280: 1 | P280: 0 | Q280: 0.31088159 | R280: 0.18078967 | S280: 0.042278759 | T280: 0 | U280: 0.17749207 | V280: 0 | W280: 0.25000307 | X280: 0 | Y280: 0 | Z280: 0.40915643 | AA280: 0 | AB280: 0 | AC280: 0 | AD280: 0 | AE280: 0.62842225 | AF280: 0.24117564
B281: Own use by blast furnaces | C281: UPSCOK | D281: % of Other energy industries own use | E281: 0 | F281: 0 | G281: 0 | H281: 0 | I281: 0 | J281: 0 | K281: 0 | L281: 0 | M281: 0 | N281: 0 | O281: 0 | P281: 0 | Q281: 0 | R281: 0 | S281: 0 | T281: 0 | U281: 0 | V281: 0 | W281: 0 | X281: 0 | Y281: 0 | Z281: 0 | AA281: 0 | AB281: 0 | AC281: 0 | AD281: 0 | AE281: 0 | AF281: 0
B282: Own use by blast furnaces | C282: UPSDSL | D282: % of Other energy industries own use | E282: 0 | F282: 0 | G282: 0 | H282: 0 | I282: 0 | J282: 0 | K282: 0 | L282: 0 | M282: 0 | N282: 0 | O282: 0 | P282: 0 | Q282: 0 | R282: 0 | S282: 0 | T282: 0.0018745494 | U282: 0.0092652645 | V282: 0 | W282: 0 | X282: 0 | Y282: 0 | Z282: 0 | AA282: 0 | AB282: 0 | AC282: 0 | AD282: 0 | AE282: 0 | AF282: 0
B283: Own use by blast furnaces | C283: UPSELC | D283: % of Other energy industries own use | E283: 0 | F283: 0 | G283: 0 | H283: 0 | I283: 0.0056059964 | J283: 0 | K283: 0 | L283: 0 | M283: 0 | N283: 0 | O283: 0 | P283: 0 | Q283: 0 | R283: 0.0074877998 | S283: 0.0078975412 | T283: 0 | U283: 0.032951326 | V283: 0 | W283: 0 | X283: 0 | Y283: 0 | Z283: 0 | AA283: 0.0024869132 | AB283: 0 | AC283: 0 | AD283: 0 | AE283: 0 | AF283: 0.027187181
B284: Own use by blast furnaces | C284: UPSGAS | D284: % of Other energy industries own use | E284: 0 | F284: 0 | G284: 0 | H284: 0 | I284: 0.010741463 | J284: 0 | K284: 0 | L284: 0 | M284: 0 | N284: 0 | O284: 0 | P284: 0 | Q284: 0 | R284: 0 | S284: 0.0020513165 | T284: 0 | U284: 0.013387125 | V284: 0 | W284: 0 | X284: 0 | Y284: 0 | Z284: 0 | AA284: 0.0035719592 | AB284: 0 | AC284: 0 | AD284: 0 | AE284: 0 | AF284: 0.0035513613
B285: Own use by blast furnaces | C285: UPSGSL | D285: % of Other energy industries own use | E285: 0 | F285: 0 | G285: 0 | H285: 0 | I285: 0 | J285: 0 | K285: 0 | L285: 0 | M285: 0 | N285: 0 | O285: 0 | P285: 0 | Q285: 0 | R285: 0 | S285: 0 | T285: 0 | U285: 0 | V285: 0 | W285: 0 | X285: 0 | Y285: 0 | Z285: 0 | AA285: 0 | AB285: 0 | AC285: 0 | AD285: 0 | AE285: 0 | AF285: 0
... B293: Own use by blast furnaces | C293: UPSWAS | D293: % of Other energy industries own use | E293: 0 | F293: 0 | G293: 0 | H293: 0 | I293: 0 | J293: 0 | K293: 0 | L293: 0 | M293: 0 | N293: 0 | O293: 0 | P293: 0 | Q293: 0 | R293: 0 | S293: 0 | T293: 0 | U293: 0 | V293: 0 | W293: 0 | X293: 0 | Y293: 0 | Z293: 0 | AA293: 0 | AB293: 0 | AC293: 0 | AD293: 0 | AE293: 0 | AF293: 0
A296: Subsector | B296: Subsector extended | C296: Primary energy commoditiy | D296: Unit | E296: AFE | F296: AFN | G296: AFW | H296: AFZ | I296: ANZ | J296: ASC | K296: ASE | L296: ASO | M296: BRA | N296: CAN | O296: CHL | P296: CHN | Q296: ENE | R296: ENW | S296: EUE | T296: EUM | U296: EUW | V296: IDN | W296: IND | X296: JPN | Y296: LAM | Z296: MDA | AA296: MEA | AB296: MEX | AC296: NIG | AD296: RUS | AE296: SKT | AF296: USA
A297: OTH OwnUses | B297: Blast furnaces | C297: UPSBDL | D297: TJ | E297: =E245*E274 -> 0 | F297: =F245*F274 -> 0 | G297: =G245*G274 -> 0 | H297: =H245*H274 -> 0 | I297: =I245*I274 -> 0 | J297: =J245*J274 -> 0 | K297: =K245*K274 -> 0 | L297: =L245*L274 -> 0 | ... AF297: =AF245*AF274 -> 0
A298: OTH OwnUses | B298: Blast furnaces | C298: UPSBFG | D298: TJ | E298: =E246*E275 -> 0 | F298: =F246*F275 -> 0 | G298: =G246*G275 -> 0 | H298: =H246*H275 -> 0 | I298: =I246*I275 -> -16712.761 | J298: =J246*J275 -> -7930 | K298: =K246*K275 -> 0 | L298: =L246*L275 -> 0 | ... AF298: =AF246*AF275 -> -21630
A299: OTH OwnUses | B299: Blast furnaces | C299: UPSBGS | D299: TJ | E299: =E247*E276 -> 0 | F299: =F247*F276 -> 0 | G299: =G247*G276 -> 0 | H299: =H247*H276 -> 0 | I299: =I247*I276 -> 0 | J299: =J247*J276 -> 0 | K299: =K247*K276 -> 0 | L299: =L247*L276 -> 0 | ... AF299: =AF247*AF276 -> 0
A300: OTH OwnUses | B300: Blast furnaces | C300: UPSBIO | D300: TJ | E300: =E248*E277 -> 0 | F300: =F248*F277 -> 0 | G300: =G248*G277 -> 0 | H300: =H248*H277 -> 0 | I300: =I248*I277 -> 0 | J300: =J248*J277 -> 0 | K300: =K248*K277 -> 0 | L300: =L248*L277 -> 0 | ... AF300: =AF248*AF277 -> 0
A301: OTH OwnUses | B301: Blast furnaces | C301: UPSCOA | D301: TJ | E301: =E249*E278 -> 0 | F301: =F249*F278 -> 0 | G301: =G249*G278 -> 0 | H301: =H249*H278 -> 0 | I301: =I249*I278 -> 0 | J301: =J249*J278 -> 0 | K301: =K249*K278 -> 0 | L301: =L249*L278 -> 0 | ... AF301: =AF249*AF278 -> 0
A302: OTH OwnUses | B302: Blast furnaces | C302: UPSCOALIG | D302: TJ | E302: =E250*E279 -> 0 | F302: =F250*F279 -> 0 | G302: =G250*G279 -> 0 | H302: =H250*H279 -> 0 | I302: =I250*I279 -> 0 | J302: =J250*J279 -> 0 | K302: =K250*K279 -> 0 | L302: =L250*L279 -> 0 | ... AF302: =AF250*AF279 -> 0
A303: OTH OwnUses | B303: Blast furnaces | C303: UPSCOG | D303: TJ | E303: =E251*E280 -> 0 | F303: =F251*F280 -> 0 | G303: =G251*G280 -> 0 | H303: =H251*H280 -> 0 | I303: =I251*I280 -> 0 | J303: =J251*J280 -> 0 | K303: =K251*K280 -> 0 | L303: =L251*L280 -> 0 | ... AF303: =AF251*AF280 -> -6819
A304: OTH OwnUses | B304: Blast furnaces | C304: UPSCOK | D304: TJ | E304: =E252*E281 -> 0 | F304: =F252*F281 -> 0 | G304: =G252*G281 -> 0 | H304: =H252*H281 -> 0 | I304: =I252*I281 -> 0 | J304: =J252*J281 -> 0 | K304: =K252*K281 -> 0 | L304: =L252*L281 -> 0 | ... AF304: =AF252*AF281 -> 0
A305: OTH OwnUses | B305: Blast furnaces | C305: UPSDSL | D305: TJ | E305: =E253*E282 -> 0 | F305: =F253*F282 -> 0 | G305: =G253*G282 -> 0 | H305: =H253*H282 -> 0 | I305: =I253*I282 -> 0 | J305: =J253*J282 -> 0 | K305: =K253*K282 -> 0 | L305: =L253*L282 -> 0 | ... AF305: =AF253*AF282 -> 0
A306: OTH OwnUses | B306: Blast furnaces | C306: UPSELC | D306: TJ | E306: =E254*E283 -> 0 | F306: =F254*F283 -> 0 | G306: =G254*G283 -> 0 | H306: =H254*H283 -> 0 | I306: =I254*I283 -> -474.99047 | J306: =J254*J283 -> 0 | K306: =K254*K283 -> 0 | L306: =L254*L283 -> 0 | ... AF306: =AF254*AF283 -> -14799.016
A307: OTH OwnUses | B307: Blast furnaces | C307: UPSGAS | D307: TJ | E307: =E255*E284 -> 0 | F307: =F255*F284 -> 0 | G307: =G255*G284 -> 0 | H307: =H255*H284 -> 0 | I307: =I255*I284 -> -4105.5588 | J307: =J255*J284 -> 0 | K307: =K255*K284 -> 0 | L307: =L255*L284 -> 0 | ... AF307: =AF255*AF284 -> -9792.4989
A308: OTH OwnUses | B308: Blast furnaces | C308: UPSGSL | D308: TJ | E308: =E256*E285 -> 0 | F308: =F256*F285 -> 0 | G308: =G256*G285 -> 0 | H308: =H256*H285 -> 0 | I308: =I256*I285 -> 0 | J308: =J256*J285 -> 0 | K308: =K256*K285 -> 0 | L308: =L256*L285 -> 0 | ... AF308: =AF256*AF285 -> 0
... A316: OTH OwnUses | B316: Blast furnaces | C316: UPSWAS | D316: TJ | E316: =E264*E293 -> 0 | F316: =F264*F293 -> 0 | G316: =G264*G293 -> 0 | H316: =H264*H293 -> 0 | I316: =I264*I293 -> 0 | J316: =J264*J293 -> 0 | K316: =K264*K293 -> 0 | L316: =L264*L293 -> 0 | ... AF316: =AF264*AF293 -> 0
A322: Adjustment to other industries
A323: ** In some of the industry sectors, there is insufficient (or too much) energy available for production, based on standardised benchmarks. Consequently, additionally required energy is appropriated from 'Other industries - NES'
A326: Sector requirements (-ve values mean unused / returned)
A328: Subsector | B328: Subsector extended | C328: Primary energy commoditiy | D328: Unit | E328: AFE | F328: AFN | G328: AFW | H328: AFZ | I328: ANZ | J328: ASC | K328: ASE | L328: ASO | M328: BRA | N328: CAN | O328: CHL | P328: CHN | Q328: ENE | R328: ENW | S328: EUE | T328: EUM | U328: EUW | V328: IDN | W328: IND | X328: JPN | Y328: LAM | Z328: MDA | AA328: MEA | AB328: MEX | AC328: NIG | AD328: RUS | AE328: SKT | AF328: USA
A329: IIS - Total | C329: INDBFG | D329: TJ | E329: =IFERROR('Inputs_BY IIS'!E306*1000,0) -> 0 | F329: =IFERROR('Inputs_BY IIS'!F306*1000,0) -> 0 | G329: =IFERROR('Inputs_BY IIS'!G306*1000,0) -> 0 | H329: =IFERROR('Inputs_BY IIS'!H306*1000,0) -> -154.7666 | I329: =IFERROR('Inputs_BY IIS'!I306*1000,0) -> 0 | J329: =IFERROR('Inputs_BY IIS'!J306*1000,0) -> 0 | K329: =IFERROR('Inputs_BY IIS'!K306*1000,0) -> 0 | L329: =IFERROR('Inputs_BY IIS'!L306*1000,0) -> 0 | ... AF329: =IFERROR('Inputs_BY IIS'!AF306*1000,0) -> 0
A330: IIS - Total | C330: INDBGS | D330: TJ | E330: =IFERROR('Inputs_BY IIS'!E307*1000,0) -> 0 | F330: =IFERROR('Inputs_BY IIS'!F307*1000,0) -> 0 | G330: =IFERROR('Inputs_BY IIS'!G307*1000,0) -> 0 | H330: =IFERROR('Inputs_BY IIS'!H307*1000,0) -> 0 | I330: =IFERROR('Inputs_BY IIS'!I307*1000,0) -> 0 | J330: =IFERROR('Inputs_BY IIS'!J307*1000,0) -> 0 | K330: =IFERROR('Inputs_BY IIS'!K307*1000,0) -> 0 | L330: =IFERROR('Inputs_BY IIS'!L307*1000,0) -> 0 | ... AF330: =IFERROR('Inputs_BY IIS'!AF307*1000,0) -> 0
A331: IIS - Total | C331: INDBIO | D331: TJ | E331: =IFERROR('Inputs_BY IIS'!E308*1000,0) -> 0 | F331: =IFERROR('Inputs_BY IIS'!F308*1000,0) -> 0 | G331: =IFERROR('Inputs_BY IIS'!G308*1000,0) -> 0 | H331: =IFERROR('Inputs_BY IIS'!H308*1000,0) -> 0 | I331: =IFERROR('Inputs_BY IIS'!I308*1000,0) -> 0 | J331: =IFERROR('Inputs_BY IIS'!J308*1000,0) -> 0 | K331: =IFERROR('Inputs_BY IIS'!K308*1000,0) -> 0 | L331: =IFERROR('Inputs_BY IIS'!L308*1000,0) -> 0 | ... AF331: =IFERROR('Inputs_BY IIS'!AF308*1000,0) -> 0
A332: IIS - Total | C332: INDBLQ | D332: TJ | E332: =IFERROR('Inputs_BY IIS'!E309*1000,0) -> 0 | F332: =IFERROR('Inputs_BY IIS'!F309*1000,0) -> 0 | G332: =IFERROR('Inputs_BY IIS'!G309*1000,0) -> 0 | H332: =IFERROR('Inputs_BY IIS'!H309*1000,0) -> 0 | I332: =IFERROR('Inputs_BY IIS'!I309*1000,0) -> 0 | J332: =IFERROR('Inputs_BY IIS'!J309*1000,0) -> 0 | K332: =IFERROR('Inputs_BY IIS'!K309*1000,0) -> 0 | L332: =IFERROR('Inputs_BY IIS'!L309*1000,0) -> 0 | ... AF332: =IFERROR('Inputs_BY IIS'!AF309*1000,0) -> 0
A333: IIS - Total | C333: INDCOA | D333: TJ | E333: =IFERROR('Inputs_BY IIS'!E310*1000,0) -> 0 | F333: =IFERROR('Inputs_BY IIS'!F310*1000,0) -> 0 | G333: =IFERROR('Inputs_BY IIS'!G310*1000,0) -> 0 | H333: =IFERROR('Inputs_BY IIS'!H310*1000,0) -> -39294.629 | I333: =IFERROR('Inputs_BY IIS'!I310*1000,0) -> 0 | J333: =IFERROR('Inputs_BY IIS'!J310*1000,0) -> 0 | K333: =IFERROR('Inputs_BY IIS'!K310*1000,0) -> 0 | L333: =IFERROR('Inputs_BY IIS'!L310*1000,0) -> 0 | ... AF333: =IFERROR('Inputs_BY IIS'!AF310*1000,0) -> 0
A334: IIS - Total | C334: INDCOG | D334: TJ | E334: =IFERROR('Inputs_BY IIS'!E311*1000,0) -> 0 | F334: =IFERROR('Inputs_BY IIS'!F311*1000,0) -> 0 | G334: =IFERROR('Inputs_BY IIS'!G311*1000,0) -> 0 | H334: =IFERROR('Inputs_BY IIS'!H311*1000,0) -> -9163.7836 | I334: =IFERROR('Inputs_BY IIS'!I311*1000,0) -> 0 | J334: =IFERROR('Inputs_BY IIS'!J311*1000,0) -> 0 | K334: =IFERROR('Inputs_BY IIS'!K311*1000,0) -> 0 | L334: =IFERROR('Inputs_BY IIS'!L311*1000,0) -> 0 | ... AF334: =IFERROR('Inputs_BY IIS'!AF311*1000,0) -> 0
...

Sheet Inputs_BY IIS
A2: ENERGY BALANCE - COKE OVENS / BF
A3: Source: UN energy balances - Omnia_Energy_Balance_NEW_29_4_2024.xlsx
A5: ** Blast furnace and coke ovens are key sectors associated with steel production. Coke ovens is actually modelled in upstream (as a transformation sector) but captured here to understand flows.
A7: Transformation Energy Use
A8: Subsector | B8: Primary energy commodity | D8: Unit | E8: AFE | F8: AFN | G8: AFW | H8: AFZ | I8: ANZ | J8: ASC | K8: ASE | L8: ASO | M8: BRA | N8: CAN | O8: CHL | P8: CHN | Q8: ENE | R8: ENW | S8: EUE | T8: EUM | U8: EUW | V8: IDN | W8: IND | X8: JPN | Y8: LAM | Z8: MDA | AA8: MEA | AB8: MEX | AC8: NIG | AD8: RUS | AE8: SKT | AF8: USA
A9: Blast furnace | B9: UPSBIO | D9: TJ | E9: =EnergyBalance!E226 -> 0 | F9: =EnergyBalance!F226 -> 0 | G9: =EnergyBalance!G226 -> 0 | H9: =EnergyBalance!H226 -> 0 | I9: =EnergyBalance!I226 -> 0 | J9: =EnergyBalance!J226 -> 0 | K9: =EnergyBalance!K226 -> 0 | L9: =EnergyBalance!L226 -> 0 | ... AF9: =EnergyBalance!AF226 -> 0
A10: Blast furnace | B10: UPSCOA | D10: TJ | E10: =EnergyBalance!E227 -> 0 | F10: =EnergyBalance!F227 -> -508 | G10: =EnergyBalance!G227 -> 0 | H10: =EnergyBalance!H227 -> 0 | I10: =EnergyBalance!I227 -> -1642 | J10: =EnergyBalance!J227 -> 0 | K10: =EnergyBalance!K227 -> 0 | L10: =EnergyBalance!L227 -> 0 | ... AF10: =EnergyBalance!AF227 -> -26858
A11: Blast furnace | B11: UPSCOK | D11: TJ | E11: =EnergyBalance!E228 -> 0 | F11: =EnergyBalance!F228 -> -16215 | G11: =EnergyBalance!G228 -> 0 | H11: =EnergyBalance!H228 -> -45329 | I11: =EnergyBalance!I228 -> -52807 | J11: =EnergyBalance!J228 -> -56573 | K11: =EnergyBalance!K228 -> -4858 | L11: =EnergyBalance!L228 -> 0 | ... AF11: =EnergyBalance!AF228 -> -239829
A12: Blast furnace | B12: UPSGAS | D12: TJ | E12: =EnergyBalance!E229 -> 0 | F12: =EnergyBalance!F229 -> 0 | G12: =EnergyBalance!G229 -> 0 | H12: =EnergyBalance!H229 -> 0 | I12: =EnergyBalance!I229 -> 0 | J12: =EnergyBalance!J229 -> 0 | K12: =EnergyBalance!K229 -> 0 | L12: =EnergyBalance!L229 -> 0 | ... AF12: =EnergyBalance!AF229 -> 0
A13: Blast furnace | B13: UPSHFO | D13: TJ | E13: =EnergyBalance!E230 -> 0 | F13: =EnergyBalance!F230 -> 0 | G13: =EnergyBalance!G230 -> 0 | H13: =EnergyBalance!H230 -> 0 | I13: =EnergyBalance!I230 -> 0 | J13: =EnergyBalance!J230 -> -5074 | K13: =EnergyBalance!K230 -> 0 | L13: =EnergyBalance!L230 -> 0 | ... AF13: =EnergyBalance!AF230 -> 0
A14: Blast furnace | B14: UPSOIL2 | D14: TJ | E14: =EnergyBalance!E231 -> 0 | F14: =EnergyBalance!F231 -> 0 | G14: =EnergyBalance!G231 -> 0 | H14: =EnergyBalance!H231 -> 0 | I14: =EnergyBalance!I231 -> 0 | J14: =EnergyBalance!J231 -> 0 | K14: =EnergyBalance!K231 -> 0 | L14: =EnergyBalance!L231 -> 0 | ... AF14: =EnergyBalance!AF231 -> 0
A16: Coke oven | B16: UPSCOA | D16: TJ | E16: 0 | F16: -14532 | G16: 0 | H16: -82420 | I16: -121746 | J16: -81877 | K16: 0 | L16: 0 | M16: -290360 | N16: -89166 | O16: -16142 | P16: -15039318 | Q16: -379416 | R16: -52836 | S16: -527878 | T16: -205725 | U16: -600926 | V16: -152300 | W16: -1349171 | X16: -1235859 | Y16: -106615 | Z16: -151056 | AA16: -63554 | AB16: -38083 | AC16: 0 | AD16: -1910106 | AE16: -650757 | AF16: -443072
A17: Coke oven | B17: UPSCOALIG | D17: TJ | E17: 0 | F17: 0 | G17: 0 | H17: 0 | I17: 0 | J17: 0 | K17: 0 | L17: 0 | M17: 0 | N17: 0 | O17: 0 | P17: 0 | Q17: 0 | R17: 0 | S17: 0 | T17: 0 | U17: -7860 | V17: 0 | W17: 0 | X17: 0 | Y17: 0 | Z17: 0 | AA17: 0 | AB17: 0 | AC17: 0 | AD17: 0 | AE17: 0 | AF17: 0
A18: Coke oven | B18: UPSGAS | D18: TJ | E18: 0 | F18: 0 | G18: 0 | H18: 0 | I18: 0 | J18: 0 | K18: 0 | L18: 0 | M18: 0 | N18: 0 | O18: 0 | P18: 0 | Q18: 0 | R18: -1002 | S18: 0 | T18: 0 | U18: 0 | V18: 0 | W18: 0 | X18: 0 | Y18: 0 | Z18: 0 | AA18: 0 | AB18: 0 | AC18: 0 | AD18: 0 | AE18: 0 | AF18: 0
A19: Coke oven | B19: UPSLPG | D19: TJ | E19: 0 | F19: 0 | G19: 0 | H19: 0 | I19: 0 | J19: 0 | K19: 0 | L19: 0 | M19: 0 | N19: 0 | O19: 0 | P19: 0 | Q19: 0 | R19: 0 | S19: 0 | T19: -1 | U19: 0 | V19: 0 | W19: 0 | X19: 0 | Y19: 0 | Z19: 0 | AA19: 0 | AB19: 0 | AC19: 0 | AD19: 0 | AE19: 0 | AF19: 0
A20: Coke oven | B20: UPSOIL2 | D20: TJ | E20: 0 | F20: 0 | G20: 0 | H20: 0 | I20: 0 | J20: 0 | K20: 0 | L20: 0 | M20: -49911 | N20: 0 | O20: 0 | P20: 0 | Q20: 0 | R20: 0 | S20: 0 | T20: 0 | U20: -12833 | V20: 0 | W20: 0 | X20: -15839 | Y20: 0 | Z20: 0 | AA20: 0 | AB20: 0 | AC20: 0 | AD20: 0 | AE20: 0 | AF20: 0
A21: Coke oven | B21: UPSWAS | D21: TJ | E21: 0 | F21: 0 | G21: 0 | H21: 0 | I21: 0 | J21: 0 | K21: 0 | L21: 0 | M21: 0 | N21: 0 | O21: 0 | P21: 0 | Q21: 0 | R21: 0 | S21: 0 | T21: 0 | U21: 0 | V21: 0 | W21: 0 | X21: -4872 | Y21: 0 | Z21: 0 | AA21: 0 | AB21: 0 | AC21: 0 | AD21: 0 | AE21: 0 | AF21: 0
A24: Transformation Energy Production
A25: Subsector | B25: Primary energy commoditiy | D25: Unit | E25: AFE | F25: AFN | G25: AFW | H25: AFZ | I25: ANZ | J25: ASC | K25: ASE | L25: ASO | M25: BRA | N25: CAN | O25: CHL | P25: CHN | Q25: ENE | R25: ENW | S25: EUE | T25: EUM | U25: EUW | V25: IDN | W25: IND | X25: JPN | Y25: LAM | Z25: MDA | AA25: MEA | AB25: MEX | AC25: NIG | AD25: RUS | AE25: SKT | AF25: USA
A26: Blast furnace | B26: UPSBFG | D26: TJ | E26: =EnergyBalance!E237 -> 0 | F26: =EnergyBalance!F237 -> 3350 | G26: =EnergyBalance!G237 -> 0 | H26: =EnergyBalance!H237 -> 18142 | I26: =EnergyBalance!I237 -> 23635 | J26: =EnergyBalance!J237 -> 17821 | K26: =EnergyBalance!K237 -> 2654 | L26: =EnergyBalance!L237 -> 0 | ... AF26: =EnergyBalance!AF237 -> 110352
A28: Coke oven | B28: UPSCOG | D28: TJ | E28: 0 | F28: 0 | G28: 0 | H28: 21130 | I28: 24923 | J28: 14455 | K28: 0 | L28: 0 | M28: 77379 | N28: 24338 | O28: 3550 | P28: 1788779 | Q28: 77882 | R28: 13522 | S28: 118747 | T28: 22973 | U28: 125698 | V28: 0 | W28: 205572 | X28: 300259 | Y28: 2526 | Z28: 36032 | AA28: 7973 | AB28: 8592 | AC28: 0 | AD28: 286443 | AE28: 152766 | AF28: 61173
A29: Coke oven | B29: UPSCOK | D29: TJ | E29: 0 | F29: 13122 | G29: 0 | H29: 55223 | I29: 79262 | J29: 67318 | K29: 0 | L29: 0 | M29: 261593 | N29: 64828 | O29: 12370 | P29: 13250539 | Q29: 301533 | R29: 39733 | S29: 408205 | T29: 163220 | U29: 495361 | V29: 125228 | W29: 1143599 | X29: 940192 | Y29: 83873 | Z29: 114729 | AA29: 52545 | AB29: 28614 | AC29: 0 | AD29: 1308694 | AE29: 462698 | AF29: 338265
A31: % use in IIS | B31: UPSBFG | E31: =IFERROR(E54/E26, "") | F31: =IFERROR(F54/F26, "") -> 1 | G31: =IFERROR(G54/G26, "") | H31: =IFERROR(H54/H26, "") -> 1 | I31: =IFERROR(I54/I26, "") -> 0.045991115 | J31: =IFERROR(J54/J26, "") -> 0.55496325 | K31: =IFERROR(K54/K26, "") -> 1 | L31: =IFERROR(L54/L26, "") | ... AF31: =IFERROR(AF54/AF26, "") -> 0.60527222
A32: % use in IIS | B32: UPSCOG | E32: =IFERROR(E59/E28, "") | F32: =IFERROR(F59/F28, "") | G32: =IFERROR(G59/G28, "") | H32: =IFERROR(H59/H28, "") -> 1 | I32: =IFERROR(I59/I28, "") -> 0.037074189 | J32: =IFERROR(J59/J28, "") -> 0 | K32: =IFERROR(K59/K28, "") | L32: =IFERROR(L59/L28, "") | ... AF32: =IFERROR(AF59/AF28, "") -> 0.0035473166
A35: ** Coking coal is a traded commodity; table below highlights net balance (consumption) based on domestic production + imports - exports
A37: Imports / Exports
A38: Subsector | B38: Primary energy commoditiy | D38: Unit | E38: AFE | F38: AFN | G38: AFW | H38: AFZ | I38: ANZ | J38: ASC | K38: ASE | L38: ASO | M38: BRA | N38: CAN | O38: CHL | P38: CHN | Q38: ENE | R38: ENW | S38: EUE | T38: EUM | U38: EUW | V38: IDN | W38: IND | X38: JPN | Y38: LAM | Z38: MDA | AA38: MEA | AB38: MEX | AC38: NIG | AD38: RUS | AE38: SKT | AF38: USA
A39: Import | B39: UPSCOK | D39: TJ | E39: 533 | F39: 11985 | G39: 0 | H39: 1925 | I39: 12117 | J39: 36538 | K39: 3653 | L39: 0 | M39: 37758 | N39: 18072 | O39: 29 | P39: 14803 | Q39: 48311 | R39: 36890 | S39: 57068 | T39: 58550 | U39: 133223 | V39: 48026 | W39: 81075 | X39: 20631 | Y39: 3585 | Z39: 19378 | AA39: 12319 | AB39: 33220 | AC39: 0 | AD39: 1913 | AE39: 8807 | AF39: 3031
A40: Export | B40: UPSCOK | D40: TJ | E40: 0 | F40: -4565 | G40: 0 | H40: -3022 | I40: -17739 | J40: -2818 | K40: 0 | L40: 0 | M40: 0 | N40: -3328 | O40: -1563 | P40: -185204 | Q40: -12439 | R40: -118 | S40: -216091 | T40: -12369 | U40: -58387 | V40: 0 | W40: -620 | X40: -46554 | Y40: -63257 | Z40: -3947 | AA40: -10180 | AB40: 0 | AC40: 0 | AD40: -81184 | AE40: 0 | AF40: -25343
A42: Regional use | B42: UPSCOK | D42: TJ | E42: =E29+E39+E40 -> 533 | F42: =F29+F39+F40 -> 20542 | G42: =G29+G39+G40 -> 0 | H42: =H29+H39+H40 -> 54126 | I42: =I29+I39+I40 -> 73640 | J42: =J29+J39+J40 -> 101038 | K42: =K29+K39+K40 -> 3653 | L42: =L29+L39+L40 -> 0 | ... AF42: =AF29+AF39+AF40 -> 315953
A43: % use in IIS | B43: UPSCOK | E43: =IFERROR(E60/E42, "") -> 0 | F43: =IFERROR(F60/F42, "") -> 0.21477948 | G43: =IFERROR(G60/G42, "") | H43: =IFERROR(H60/H42, "") -> 0.10748993 | I43: =IFERROR(I60/I42, "") -> 0.1661597 | J43: =IFERROR(J60/J42, "") -> 0.26640472 | K43: =IFERROR(K60/K42, "") -> 0.056118259 | L43: =IFERROR(L60/L42, "") | ... AF43: =IFERROR(AF60/AF42, "") -> 0.23380376
A47: ** The next section considers combining steel sector energy balances with production levels (see 'SteelProduction'), to estimate intensity of production values for each of the three production pathways
A49: ENERGY BALANCE - IIS
A50: Source: UN energy balances - Omnia_Energy_Balance_NEW_29_4_2024.xlsx
A52: Final Energy Use
A53: Subsector | B53: Subsector extended | C53: Primary energy commoditiy | D53: Unit | E53: AFE | F53: AFN | G53: AFW | H53: AFZ | I53: ANZ | J53: ASC | K53: ASE | L53: ASO | M53: BRA | N53: CAN | O53: CHL | P53: CHN | Q53: ENE | R53: ENW | S53: EUE | T53: EUM | U53: EUW | V53: IDN | W53: IND | X53: JPN | Y53: LAM | Z53: MDA | AA53: MEA | AB53: MEX | AC53: NIG | AD53: RUS | AE53: SKT | AF53: USA
A54: IIS | B54: Iron and steel | C54: INDBFG | D54: TJ | E54: =EnergyBalance!E38 -> 0 | F54: =EnergyBalance!F38 -> 3350 | G54: =EnergyBalance!G38 -> 0 | H54: =EnergyBalance!H38 -> 18142 | I54: =EnergyBalance!I38 -> 1087 | J54: =EnergyBalance!J38 -> 9890 | K54: =EnergyBalance!K38 -> 2654 | L54: =EnergyBalance!L38 -> 0 | ... AF54: =EnergyBalance!AF38 -> 66793
A55: IIS | B55: Iron and steel | C55: INDBGS | D55: TJ | E55: =EnergyBalance!E39 -> 0 | F55: =EnergyBalance!F39 -> 0 | G55: =EnergyBalance!G39 -> 0 | H55: =EnergyBalance!H39 -> 0 | I55: =EnergyBalance!I39 -> 0 | J55: =EnergyBalance!J39 -> 0 | K55: =EnergyBalance!K39 -> 0 | L55: =EnergyBalance!L39 -> 0 | ... AF55: =EnergyBalance!AF39 -> 0
A56: IIS | B56: Iron and steel | C56: INDBIO | D56: TJ | E56: =EnergyBalance!E40 -> 0 | F56: =EnergyBalance!F40 -> 0 | G56: =EnergyBalance!G40 -> 0 | H56: =EnergyBalance!H40 -> 0 | I56: =EnergyBalance!I40 -> 0 | J56: =EnergyBalance!J40 -> 0 | K56: =EnergyBalance!K40 -> 0 | L56: =EnergyBalance!L40 -> 0 | ... AF56: =EnergyBalance!AF40 -> 0
A57: IIS | B57: Iron and steel | C57: INDBLQ | D57: TJ | E57: =EnergyBalance!E41 -> 0 | F57: =EnergyBalance!F41 -> 0 | G57: =EnergyBalance!G41 -> 0 | H57: =EnergyBalance!H41 -> 0 | I57: =EnergyBalance!I41 -> 0 | J57: =EnergyBalance!J41 -> 0 | K57: =EnergyBalance!K41 -> 0 | L57: =EnergyBalance!L41 -> 0 | ... AF57: =EnergyBalance!AF41 -> 74
A58: IIS | B58: Iron and steel | C58: INDCOA | D58: TJ | E58: =EnergyBalance!E42 -> 0 | F58: =EnergyBalance!F42 -> 12 | G58: =EnergyBalance!G42 -> 0 | H58: =EnergyBalance!H42 -> 71951 | I58: =EnergyBalance!I42 -> 619 | J58: =EnergyBalance!J42 -> 23523 | K58: =EnergyBalance!K42 -> 2814 | L58: =EnergyBalance!L42 -> 0 | ... AF58: =EnergyBalance!AF42 -> 8862
A59: IIS | B59: Iron and steel | C59: INDCOG | D59: TJ | E59: =EnergyBalance!E43 -> 0 | F59: =EnergyBalance!F43 -> 0 | G59: =EnergyBalance!G43 -> 0 | H59: =EnergyBalance!H43 -> 21130 | I59: =EnergyBalance!I43 -> 924 | J59: =EnergyBalance!J43 -> 0 | K59: =EnergyBalance!K43 -> 0 | L59: =EnergyBalance!L43 -> 0 | ... AF59: =EnergyBalance!AF43 -> 217
A60: IIS | B60: Iron and steel | C60: INDCOK | D60: TJ | E60: =EnergyBalance!E44 -> 0 | F60: =EnergyBalance!F44 -> 4412 | G60: =EnergyBalance!G44 -> 0 | H60: =EnergyBalance!H44 -> 5818 | I60: =EnergyBalance!I44 -> 12236 | J60: =EnergyBalance!J44 -> 26917 | K60: =EnergyBalance!K44 -> 205 | L60: =EnergyBalance!L44 -> 0 | ... AF60: =EnergyBalance!AF44 -> 73871
A61: IIS | B61: Iron and steel | C61: INDELC | D61: TJ | E61: =EnergyBalance!E45 -> 5910 | F61: =EnergyBalance!F45 -> 3073 | G61: =EnergyBalance!G45 -> 996 | H61: =EnergyBalance!H45 -> 68980 | I61: =EnergyBalance!I45 -> 17187 | J61: =EnergyBalance!J45 -> 87381 | K61: =EnergyBalance!K45 -> 31525 | L61: =EnergyBalance!L45 -> 0 | ... AF61: =EnergyBalance!AF45 -> 204414
A62: IIS | B62: Iron and steel | C62: INDGAS | D62: TJ | E62: =EnergyBalance!E46 -> 0 | F62: =EnergyBalance!F46 -> 104833 | G62: =EnergyBalance!G46 -> 0 | H62: =EnergyBalance!H46 -> 9200 | I62: =EnergyBalance!I46 -> 8424 | J62: =EnergyBalance!J46 -> 25226 | K62: =EnergyBalance!K46 -> 14925 | L62: =EnergyBalance!L46 -> 703 | ... AF62: =EnergyBalance!AF46 -> 393069
A63: IIS | B63: Iron and steel | C63: INDHET | D63: TJ | E63: =EnergyBalance!E47 -> 0 | F63: =EnergyBalance!F47 -> 0 | G63: =EnergyBalance!G47 -> 0 | H63: =EnergyBalance!H47 -> 0 | I63: =EnergyBalance!I47 -> 0 | J63: =EnergyBalance!J47 -> 35700 | K63: =EnergyBalance!K47 -> 0 | L63: =EnergyBalance!L47 -> 0 | ... AF63: =EnergyBalance!AF47 -> 7327
A64: IIS | B64: Iron and steel | C64: INDLPG | D64: TJ | E64: =EnergyBalance!E48 -> 0 | F64: =EnergyBalance!F48 -> 0 | G64: =EnergyBalance!G48 -> 0 | H64: =EnergyBalance!H48 -> 0 | I64: =EnergyBalance!I48 -> 30 | J64: =EnergyBalance!J48 -> 4113 | K64: =EnergyBalance!K48 -> 4750 | L64: =EnergyBalance!L48 -> 0 | ... AF64: =EnergyBalance!AF48 -> 91
A65: IIS | B65: Iron and steel | C65: INDOIL | D65: TJ | E65: =EnergyBalance!E49 -> 0 | F65: =EnergyBalance!F49 -> 2322 | G65: =EnergyBalance!G49 -> 307 | H65: =EnergyBalance!H49 -> 506 | I65: =EnergyBalance!I49 -> 841 | J65: =EnergyBalance!J49 -> 17078 | K65: =EnergyBalance!K49 -> 11368 | L65: =EnergyBalance!L49 -> 0 | ... AF65: =EnergyBalance!AF49 -> 3635
... A68: IIS | B68: Iron and steel | C68: INDWAS | D68: TJ | E68: =EnergyBalance!E52 -> 0 | F68: =EnergyBalance!F52 -> 0 | G68: =EnergyBalance!G52 -> 0 | H68: =EnergyBalance!H52 -> 0 | I68: =EnergyBalance!I52 -> 0 | J68: =EnergyBalance!J52 -> 0 | K68: =EnergyBalance!K52 -> 0 | L68: =EnergyBalance!L52 -> 0 | ... AF68: =EnergyBalance!AF52 -> 0
B70: Thermal est. in EnBal | D70: TJ | E70: =SUM(E68,E62:E65,E54:E60) -> 0 | F70: =SUM(F68,F62:F65,F54:F60) -> 114929 | G70: =SUM(G68,G62:G65,G54:G60) -> 307 | H70: =SUM(H68,H62:H65,H54:H60) -> 126747 | I70: =SUM(I68,I62:I65,I54:I60) -> 24161 | J70: =SUM(J68,J62:J65,J54:J60) -> 142447 | K70: =SUM(K68,K62:K65,K54:K60) -> 36716 | L70: =SUM(L68,L62:L65,L54:L60) -> 703 | ... AF70: =SUM(AF68,AF62:AF65,AF54:AF60) -> 553939
B72: BFG use per Mt Steel | C72: INDBFG | D72: PJ/Mt | E72: =IFERROR(E54/1000/(E81*E85),"") | F72: =IFERROR(F54/1000/(F81*F85),"") -> 3.4287552 | G72: =IFERROR(G54/1000/(G81*G85),"") | H72: =IFERROR(H54/1000/(H81*H85),"") -> 3.7485371 | I72: =IFERROR(I54/1000/(I81*I85),"") -> 0.25147316 | J72: =IFERROR(J54/1000/(J81*J85),"") -> 2.836927 | K72: =IFERROR(K54/1000/(K81*K85),"") -> 3.2712572 | L72: =IFERROR(L54/1000/(L81*L85),"") | ... AF72: =IFERROR(AF54/1000/(AF81*AF85),"") -> 2.3353828
D73: ktCO2/Mt
A75: METALS PRODUCTION DATA
A76: Source: PIOT database (OMNIA_steel_production_2017_and_2019.xlsx)
E77: =INDEX(IIS_Prod!$B$7:$K$35,MATCH('Inputs_BY IIS'!E$78,IIS_Prod!$C$7:$C$35,0),1) -> Eastern Africa | F77: =INDEX(IIS_Prod!$B$7:$K$35,MATCH('Inputs_BY IIS'!F$78,IIS_Prod!$C$7:$C$35,0),1) -> Northern Africa | G77: =INDEX(IIS_Prod!$B$7:$K$35,MATCH('Inputs_BY IIS'!G$78,IIS_Prod!$C$7:$C$35,0),1) -> Western Africa | H77: =INDEX(IIS_Prod!$B$7:$K$35,MATCH('Inputs_BY IIS'!H$78,IIS_Prod!$C$7:$C$35,0),1) -> Southern Africa | I77: =INDEX(IIS_Prod!$B$7:$K$35,MATCH('Inputs_BY IIS'!I$78,IIS_Prod!$C$7:$C$35,0),1) -> Australia and New Zealand | J77: =INDEX(IIS_Prod!$B$7:$K$35,MATCH('Inputs_BY IIS'!J$78,IIS_Prod!$C$7:$C$35,0),1) -> Central Asia | K77: =INDEX(IIS_Prod!$B$7:$K$35,MATCH('Inputs_BY IIS'!K$78,IIS_Prod!$C$7:$C$35,0),1) -> Southeast Asia | L77: =INDEX(IIS_Prod!$B$7:$K$35,MATCH('Inputs_BY IIS'!L$78,IIS_Prod!$C$7:$C$35,0),1) -> South Asia | ... AF77: =INDEX(IIS_Prod!$B$7:$K$35,MATCH('Inputs_BY IIS'!AF$78,IIS_Prod!$C$7:$C$35,0),1) -> United States
E78: AFE | F78: AFN | G78: AFW | H78: AFZ | I78: ANZ | J78: ASC | K78: ASE | L78: ASO | M78: BRA | N78: CAN | O78: CHL | P78: CHN | Q78: ENE | R78: ENW | S78: EUE | T78: EUM | U78: EUW | V78: IDN | W78: IND | X78: JPN | Y78: LAM | Z78: MDA | AA78: MEA | AB78: MEX | AC78: NIG | AD78: RUS | AE78: SKT | AF78: USA | AH78: Check
B79: =IIS_Prod!E4 -> 3 | C79: Pig iron production | D79: Mt | E79: =INDEX(IIS_Prod!$C$7:$K$35,MATCH('Inputs_BY IIS'!E$78,IIS_Prod!$C$7:$C$35,0),$B79) -> 0 | F79: =INDEX(IIS_Prod!$C$7:$K$35,MATCH('Inputs_BY IIS'!F$78,IIS_Prod!$C$7:$C$35,0),$B79) -> 0.70378422 | G79: =INDEX(IIS_Prod!$C$7:$K$35,MATCH('Inputs_BY IIS'!G$78,IIS_Prod!$C$7:$C$35,0),$B79) -> 0 | H79: =INDEX(IIS_Prod!$C$7:$K$35,MATCH('Inputs_BY IIS'!H$78,IIS_Prod!$C$7:$C$35,0),$B79) -> 7.0188134 | I79: =INDEX(IIS_Prod!$C$7:$K$35,MATCH('Inputs_BY IIS'!I$78,IIS_Prod!$C$7:$C$35,0),$B79) -> 3.9611571 | J79: =INDEX(IIS_Prod!$C$7:$K$35,MATCH('Inputs_BY IIS'!J$78,IIS_Prod!$C$7:$C$35,0),$B79) -> 2.330698 | K79: =INDEX(IIS_Prod!$C$7:$K$35,MATCH('Inputs_BY IIS'!K$78,IIS_Prod!$C$7:$C$35,0),$B79) -> 2.3086387 | L79: =INDEX(IIS_Prod!$C$7:$K$35,MATCH('Inputs_BY IIS'!L$78,IIS_Prod!$C$7:$C$35,0),$B79) -> 0 | ... AF79: =INDEX(IIS_Prod!$C$7:$K$35,MATCH('Inputs_BY IIS'!AF$78,IIS_Prod!$C$7:$C$35,0),$B79) -> 24.108387 | AH79: =SUM(E79:AF79)/IIS_Prod!E36 -> 1.0021714
B80: =IIS_Prod!F4 -> 4 | C80: Sponge iron production | D80: Mt | E80: =INDEX(IIS_Prod!$C$7:$K$35,MATCH('Inputs_BY IIS'!E$78,IIS_Prod!$C$7:$C$35,0),$B80) -> 0 | F80: =INDEX(IIS_Prod!$C$7:$K$35,MATCH('Inputs_BY IIS'!F$78,IIS_Prod!$C$7:$C$35,0),$B80) -> 3.1311631 | G80: =INDEX(IIS_Prod!$C$7:$K$35,MATCH('Inputs_BY IIS'!G$78,IIS_Prod!$C$7:$C$35,0),$B80) -> 0 | H80: =INDEX(IIS_Prod!$C$7:$K$35,MATCH('Inputs_BY IIS'!H$78,IIS_Prod!$C$7:$C$35,0),$B80) -> 0.65135187 | I80: =INDEX(IIS_Prod!$C$7:$K$35,MATCH('Inputs_BY IIS'!I$78,IIS_Prod!$C$7:$C$35,0),$B80) -> 0 | J80: =INDEX(IIS_Prod!$C$7:$K$35,MATCH('Inputs_BY IIS'!J$78,IIS_Prod!$C$7:$C$35,0),$B80) -> 0 | K80: =INDEX(IIS_Prod!$C$7:$K$35,MATCH('Inputs_BY IIS'!K$78,IIS_Prod!$C$7:$C$35,0),$B80) -> 5.8270193 | L80: =INDEX(IIS_Prod!$C$7:$K$35,MATCH('Inputs_BY IIS'!L$78,IIS_Prod!$C$7:$C$35,0),$B80) -> 0 | ... AF80: =INDEX(IIS_Prod!$C$7:$K$35,MATCH('Inputs_BY IIS'!AF$78,IIS_Prod!$C$7:$C$35,0),$B80) -> 0.74777109 | AH80: =SUM(E80:AF80)/IIS_Prod!F36 -> 2.2503498
B81: =IIS_Prod!K4 -> 9 | C81: Crude Steel production | D81: Mt | E81: =INDEX(IIS_Prod!$C$7:$K$35,MATCH('Inputs_BY IIS'!E$78,IIS_Prod!$C$7:$C$35,0),$B$81) -> 0.055066776 | F81: =INDEX(IIS_Prod!$C$7:$K$35,MATCH('Inputs_BY IIS'!F$78,IIS_Prod!$C$7:$C$35,0),$B$81) -> 4.7763804 | G81: =INDEX(IIS_Prod!$C$7:$K$35,MATCH('Inputs_BY IIS'!G$78,IIS_Prod!$C$7:$C$35,0),$B$81) -> 0.060573454 | H81: =INDEX(IIS_Prod!$C$7:$K$35,MATCH('Inputs_BY IIS'!H$78,IIS_Prod!$C$7:$C$35,0),$B$81) -> 7.9477235 | I81: =INDEX(IIS_Prod!$C$7:$K$35,MATCH('Inputs_BY IIS'!I$78,IIS_Prod!$C$7:$C$35,0),$B$81) -> 5.7290694 | J81: =INDEX(IIS_Prod!$C$7:$K$35,MATCH('Inputs_BY IIS'!J$78,IIS_Prod!$C$7:$C$35,0),$B$81) -> 3.9504671 | K81: =INDEX(IIS_Prod!$C$7:$K$35,MATCH('Inputs_BY IIS'!K$78,IIS_Prod!$C$7:$C$35,0),$B$81) -> 5.4087258 | L81: =INDEX(IIS_Prod!$C$7:$K$35,MATCH('Inputs_BY IIS'!L$78,IIS_Prod!$C$7:$C$35,0),$B$81) -> 3.4063714 | ... AF81: =INDEX(IIS_Prod!$C$7:$K$35,MATCH('Inputs_BY IIS'!AF$78,IIS_Prod!$C$7:$C$35,0),$B$81) -> 86.712626 | AH81: =SUM(E81:AF81)/IIS_Prod!K36 -> 1
E82: =1/$AM$82 -> 1.25 | F82: =1/$AM$82 -> 1.25 | G82: =1/$AM$82 -> 1.25 | H82: =1/$AM$82 -> 1.25 | I82: =1/$AM$82 -> 1.25 | J82: =1/$AM$82 -> 1.25 | K82: =1/$AM$82 -> 1.25 | L82: =1/$AM$82 -> 1.25 | ... AF82: =1/$AM$82 -> 1.25 | AH82: Capacity adjustment factor, based on OECD | AM82: 0.8
P83: =1150/P81 -> 1.2127346 | W83: =128/W81 -> 1.2219455
C84: Shares by steel production pathway
B85: =IIS_Prod!W4 -> 21 | C85: BF-BOF | D85: % | E85: =INDEX(IIS_Prod!$C$7:$Y$35,MATCH('Inputs_BY IIS'!E$78,IIS_Prod!$C$7:$C$35,0),$B85) -> 0 | F85: =INDEX(IIS_Prod!$C$7:$Y$35,MATCH('Inputs_BY IIS'!F$78,IIS_Prod!$C$7:$C$35,0),$B85) -> 0.20455468 | G85: =INDEX(IIS_Prod!$C$7:$Y$35,MATCH('Inputs_BY IIS'!G$78,IIS_Prod!$C$7:$C$35,0),$B85) -> 0 | H85: =INDEX(IIS_Prod!$C$7:$Y$35,MATCH('Inputs_BY IIS'!H$78,IIS_Prod!$C$7:$C$35,0),$B85) -> 0.60894854 | I85: =INDEX(IIS_Prod!$C$7:$Y$35,MATCH('Inputs_BY IIS'!I$78,IIS_Prod!$C$7:$C$35,0),$B85) -> 0.75449058 | J85: =INDEX(IIS_Prod!$C$7:$Y$35,MATCH('Inputs_BY IIS'!J$78,IIS_Prod!$C$7:$C$35,0),$B85) -> 0.88246945 | K85: 0.15 | L85: =INDEX(IIS_Prod!$C$7:$Y$35,MATCH('Inputs_BY IIS'!L$78,IIS_Prod!$C$7:$C$35,0),$B85) -> 0 | M85: =INDEX(IIS_Prod!$C$7:$Y$35,MATCH('Inputs_BY IIS'!M$78,IIS_Prod!$C$7:$C$35,0),$B85) -> 0.77509534 | N85: =INDEX(IIS_Prod!$C$7:$Y$35,MATCH('Inputs_BY IIS'!N$78,IIS_Prod!$C$7:$C$35,0),$B85) -> 0.68327753 | O85: =INDEX(IIS_Prod!$C$7:$Y$35,MATCH('Inputs_BY IIS'!O$78,IIS_Prod!$C$7:$C$35,0),$B85) -> 0.80639402 | P85: =INDEX(IIS_Prod!$C$7:$Y$35,MATCH('Inputs_BY IIS'!P$78,IIS_Prod!$C$7:$C$35,0),$B85) -> 0.90200686 | Q85: =INDEX(IIS_Prod!$C$7:$Y$35,MATCH('Inputs_BY IIS'!Q$78,IIS_Prod!$C$7:$C$35,0),$B85) -> 0.94744692 | R85: =INDEX(IIS_Prod!$C$7:$Y$35,MATCH('Inputs_BY IIS'!R$78,IIS_Prod!$C$7:$C$35,0),$B85) -> 0.69418554 | S85: =INDEX(IIS_Prod!$C$7:$Y$35,MATCH('Inputs_BY IIS'!S$78,IIS_Prod!$C$7:$C$35,0),$B85) -> 0.78651198 | ... AF85: =INDEX(IIS_Prod!$C$7:$Y$35,MATCH('Inputs_BY IIS'!AF$78,IIS_Prod!$C$7:$C$35,0),$B85) -> 0.32983029
B86: =IIS_Prod!X4 -> 22 | C86: DRI-EAF | D86: % | E86: =INDEX(IIS_Prod!$C$7:$Y$35,MATCH('Inputs_BY IIS'!E$78,IIS_Prod!$C$7:$C$35,0),$B86) -> 0.10019141 | F86: =INDEX(IIS_Prod!$C$7:$Y$35,MATCH('Inputs_BY IIS'!F$78,IIS_Prod!$C$7:$C$35,0),$B86) -> 0.42146474 | G86: =INDEX(IIS_Prod!$C$7:$Y$35,MATCH('Inputs_BY IIS'!G$78,IIS_Prod!$C$7:$C$35,0),$B86) -> 0.10019141 | H86: =INDEX(IIS_Prod!$C$7:$Y$35,MATCH('Inputs_BY IIS'!H$78,IIS_Prod!$C$7:$C$35,0),$B86) -> 0.039179996 | I86: =INDEX(IIS_Prod!$C$7:$Y$35,MATCH('Inputs_BY IIS'!I$78,IIS_Prod!$C$7:$C$35,0),$B86) -> 0.024316282 | J86: =INDEX(IIS_Prod!$C$7:$Y$35,MATCH('Inputs_BY IIS'!J$78,IIS_Prod!$C$7:$C$35,0),$B86) -> 0.011717176 | K86: 0.1 | L86: =INDEX(IIS_Prod!$C$7:$Y$35,MATCH('Inputs_BY IIS'!L$78,IIS_Prod!$C$7:$C$35,0),$B86) -> 0.099694732 | M86: =INDEX(IIS_Prod!$C$7:$Y$35,MATCH('Inputs_BY IIS'!M$78,IIS_Prod!$C$7:$C$35,0),$B86) -> 0.022499526 | N86: =INDEX(IIS_Prod!$C$7:$Y$35,MATCH('Inputs_BY IIS'!N$78,IIS_Prod!$C$7:$C$35,0),$B86) -> 0.031657426 | O86: =INDEX(IIS_Prod!$C$7:$Y$35,MATCH('Inputs_BY IIS'!O$78,IIS_Prod!$C$7:$C$35,0),$B86) -> 0.019339669 | P86: =INDEX(IIS_Prod!$C$7:$Y$35,MATCH('Inputs_BY IIS'!P$78,IIS_Prod!$C$7:$C$35,0),$B86) -> 0.009894687 | Q86: =INDEX(IIS_Prod!$C$7:$Y$35,MATCH('Inputs_BY IIS'!Q$78,IIS_Prod!$C$7:$C$35,0),$B86) -> 0.0052471121 | R86: =INDEX(IIS_Prod!$C$7:$Y$35,MATCH('Inputs_BY IIS'!R$78,IIS_Prod!$C$7:$C$35,0),$B86) -> 0.030481579 | S86: =INDEX(IIS_Prod!$C$7:$Y$35,MATCH('Inputs_BY IIS'!S$78,IIS_Prod!$C$7:$C$35,0),$B86) -> 0.023692725 | ... AF86: =INDEX(IIS_Prod!$C$7:$Y$35,MATCH('Inputs_BY IIS'!AF$78,IIS_Prod!$C$7:$C$35,0),$B86) -> 0.066977557
B87: =IIS_Prod!Y4 -> 23 | C87: SCRP-EAF | D87: % | E87: =INDEX(IIS_Prod!$C$7:$Y$35,MATCH('Inputs_BY IIS'!E$78,IIS_Prod!$C$7:$C$35,0),$B87) -> 0.89980859 | F87: =INDEX(IIS_Prod!$C$7:$Y$35,MATCH('Inputs_BY IIS'!F$78,IIS_Prod!$C$7:$C$35,0),$B87) -> 0.37398058 | G87: =INDEX(IIS_Prod!$C$7:$Y$35,MATCH('Inputs_BY IIS'!G$78,IIS_Prod!$C$7:$C$35,0),$B87) -> 0.89980859 | H87: =INDEX(IIS_Prod!$C$7:$Y$35,MATCH('Inputs_BY IIS'!H$78,IIS_Prod!$C$7:$C$35,0),$B87) -> 0.35187146 | I87: =INDEX(IIS_Prod!$C$7:$Y$35,MATCH('Inputs_BY IIS'!I$78,IIS_Prod!$C$7:$C$35,0),$B87) -> 0.22119314 | J87: =INDEX(IIS_Prod!$C$7:$Y$35,MATCH('Inputs_BY IIS'!J$78,IIS_Prod!$C$7:$C$35,0),$B87) -> 0.10581337 | K87: 0.75 | L87: =INDEX(IIS_Prod!$C$7:$Y$35,MATCH('Inputs_BY IIS'!L$78,IIS_Prod!$C$7:$C$35,0),$B87) -> 0.90030527 | M87: =INDEX(IIS_Prod!$C$7:$Y$35,MATCH('Inputs_BY IIS'!M$78,IIS_Prod!$C$7:$C$35,0),$B87) -> 0.20240513 | N87: =INDEX(IIS_Prod!$C$7:$Y$35,MATCH('Inputs_BY IIS'!N$78,IIS_Prod!$C$7:$C$35,0),$B87) -> 0.28506504 | O87: =INDEX(IIS_Prod!$C$7:$Y$35,MATCH('Inputs_BY IIS'!O$78,IIS_Prod!$C$7:$C$35,0),$B87) -> 0.17426631 | P87: =INDEX(IIS_Prod!$C$7:$Y$35,MATCH('Inputs_BY IIS'!P$78,IIS_Prod!$C$7:$C$35,0),$B87) -> 0.088098454 | Q87: =INDEX(IIS_Prod!$C$7:$Y$35,MATCH('Inputs_BY IIS'!Q$78,IIS_Prod!$C$7:$C$35,0),$B87) -> 0.047305965 | R87: =INDEX(IIS_Prod!$C$7:$Y$35,MATCH('Inputs_BY IIS'!R$78,IIS_Prod!$C$7:$C$35,0),$B87) -> 0.27533288 | S87: =INDEX(IIS_Prod!$C$7:$Y$35,MATCH('Inputs_BY IIS'!S$78,IIS_Prod!$C$7:$C$35,0),$B87) -> 0.18979529 | ... AF87: =INDEX(IIS_Prod!$C$7:$Y$35,MATCH('Inputs_BY IIS'!AF$78,IIS_Prod!$C$7:$C$35,0),$B87) -> 0.60319216
B89: Scrap input | C89: BF-BOF | D89: t/t | E89: 0.125 | F89: 0.125 | G89: 0.125 | H89: 0.125 | I89: 0.125 | J89: 0.125 | K89: 0.125 | L89: 0.125 | M89: 0.125 | N89: 0.125 | O89: 0.125 | P89: 0.125 | Q89: 0.125 | R89: 0.125 | S89: 0.125 | T89: 0.125 | U89: 0.125 | V89: 0.125 | W89: 0.125 | X89: 0.125 | Y89: 0.125 | Z89: 0.125 | AA89: 0.125 | AB89: 0.125 | AC89: 0.125 | AD89: 0.125 | AE89: 0.125 | AF89: 0.125 | AH89: https://www.worldsteel.org/about-steel/steel-facts.html
C90: DRI-EAF | D90: t/t | E90: 0.125 | F90: 0.125 | G90: 0.125 | H90: 0.125 | I90: 0.125 | J90: 0.125 | K90: 0.125 | L90: 0.125 | M90: 0.125 | N90: 0.125 | O90: 0.125 | P90: 0.125 | Q90: 0.125 | R90: 0.125 | S90: 0.125 | T90: 0.125 | U90: 0.125 | V90: 0.125 | W90: 0.125 | X90: 0.125 | Y90: 0.125 | Z90: 0.125 | AA90: 0.125 | AB90: 0.125 | AC90: 0.125 | AD90: 0.125 | AE90: 0.125 | AF90: 0.125 | AH90: https://www.worldsteel.org/about-steel/steel-facts.html
C91: SCRP-EAF | D91: t/t | E91: 1.05 | F91: 1.05 | G91: 1.05 | H91: 1.05 | I91: 1.05 | J91: 1.05 | K91: 1.05 | L91: 1.05 | M91: 1.05 | N91: 1.05 | O91: 1.05 | P91: 1.05 | Q91: 1.05 | R91: 1.05 | S91: 1.05 | T91: 1.05 | U91: 1.05 | V91: 1.05 | W91: 1.05 | X91: 1.05 | Y91: 1.05 | Z91: 1.05 | AA91: 1.05 | AB91: 1.05 | AC91: 1.05 | AD91: 1.05 | AE91: 1.05 | AF91: 1.05
B93: Scrap level | C93: BF-BOF | D93: Mt | E93: =E85*E$81*E89 -> 0 | F93: =F85*F$81*F89 -> 0.12212887 | G93: =G85*G$81*G89 -> 0 | H93: =H85*H$81*H89 -> 0.60496933 | I93: =I85*I$81*I89 -> 0.54031611 | J93: =J85*J$81*J89 -> 0.43577082 | K93: =K85*K$81*K89 -> 0.10141361 | L93: =L85*L$81*L89 -> 0 | ... AF93: =AF85*AF$81*AF89 -> 3.5750563
C94: DRI-EAF | D94: Mt | E94: =E86*E$81*E90 -> 0.00068965223 | F94: =F86*F$81*F90 -> 0.25163449 | G94: =G86*G$81*G90 -> 0.00075861746 | H94: =H86*H$81*H90 -> 0.038923972 | I94: =I86*I$81*I90 -> 0.017413708 | J94: =J86*J$81*J90 -> 0.00578604 | K94: =K86*K$81*K90 -> 0.067609072 | L94: =L86*L$81*L90 -> 0.042449661 | ... AF94: =AF86*AF$81*AF90 -> 0.72597497
C95: SCRP-EAF | D95: Mt | E95: =E87*E$81*E91 -> 0.052027036 | F95: =F87*F$81*F91 -> 1.8755872 | G95: =G87*G$81*G91 -> 0.05722974 | H95: =H87*H$81*H91 -> 2.9364059 | I95: =I87*I$81*I91 -> 1.3305924 | J95: =J87*J$81*J91 -> 0.43891285 | K95: =K87*K$81*K91 -> 4.2593715 | L95: =L87*L$81*L91 -> 3.2201128 | ... AF95: =AF87*AF$81*AF91 -> 54.919595
C96: Total | D96: Mt | E96: =SUM(E93:E95) -> 0.052716689 | F96: =SUM(F93:F95) -> 2.2493506 | G96: =SUM(G93:G95) -> 0.057988358 | H96: =SUM(H93:H95) -> 3.5802992 | I96: =SUM(I93:I95) -> 1.8883222 | J96: =SUM(J93:J95) -> 0.88046971 | K96: =SUM(K93:K95) -> 4.4283942 | L96: =SUM(L93:L95) -> 3.2625625 | ... AF96: =SUM(AF93:AF95) -> 59.220626
C98: BF-BOF output | D98: Mt | E98: =E85*E81 -> 0 | F98: =F85*F81 -> 0.97703096 | G98: =G85*G81 -> 0 | H98: =H85*H81 -> 4.8397546 | I98: =I85*I81 -> 4.3225289 | J98: =J85*J81 -> 3.4861665 | K98: =K85*K81 -> 0.81130887 | L98: =L85*L81 -> 0 | ... AF98: =AF85*AF81 -> 28.60045
E99: =E98/(SUM($E$98:$AF$98)) -> 0 | F99: =F98/(SUM($E$98:$AF$98)) -> 0.00073301332 | G99: =G98/(SUM($E$98:$AF$98)) -> 0 | H99: =H98/(SUM($E$98:$AF$98)) -> 0.0036310053 | I99: =I98/(SUM($E$98:$AF$98)) -> 0.0032429589 | J99: =J98/(SUM($E$98:$AF$98)) -> 0.0026154816 | K99: =K98/(SUM($E$98:$AF$98)) -> 0.00060868102 | L99: =L98/(SUM($E$98:$AF$98)) -> 0 | ... AF99: =AF98/(SUM($E$98:$AF$98)) -> 0.021457366
A100: ** This subsector will be located in upstream (as agreed with Marie)
A102: COKE PRODUCTION | E102: =INDEX(IIS_Prod!$B$7:$K$35,MATCH('Inputs_BY IIS'!E$78,IIS_Prod!$C$7:$C$35,0),1) -> Eastern Africa | F102: =INDEX(IIS_Prod!$B$7:$K$35,MATCH('Inputs_BY IIS'!F$78,IIS_Prod!$C$7:$C$35,0),1) -> Northern Africa | G102: =INDEX(IIS_Prod!$B$7:$K$35,MATCH('Inputs_BY IIS'!G$78,IIS_Prod!$C$7:$C$35,0),1) -> Western Africa | H102: =INDEX(IIS_Prod!$B$7:$K$35,MATCH('Inputs_BY IIS'!H$78,IIS_Prod!$C$7:$C$35,0),1) -> Southern Africa | I102: =INDEX(IIS_Prod!$B$7:$K$35,MATCH('Inputs_BY IIS'!I$78,IIS_Prod!$C$7:$C$35,0),1) -> Australia and New Zealand | J102: =INDEX(IIS_Prod!$B$7:$K$35,MATCH('Inputs_BY IIS'!J$78,IIS_Prod!$C$7:$C$35,0),1) -> Central Asia | K102: =INDEX(IIS_Prod!$B$7:$K$35,MATCH('Inputs_BY IIS'!K$78,IIS_Prod!$C$7:$C$35,0),1) -> Southeast Asia | L102: =INDEX(IIS_Prod!$B$7:$K$35,MATCH('Inputs_BY IIS'!L$78,IIS_Prod!$C$7:$C$35,0),1) -> South Asia | ... AF102: =INDEX(IIS_Prod!$B$7:$K$35,MATCH('Inputs_BY IIS'!AF$78,IIS_Prod!$C$7:$C$35,0),1) -> United States
E103: AFE | F103: AFN | G103: AFW | H103: AFZ | I103: ANZ | J103: ASC | K103: ASE | L103: ASO | M103: BRA | N103: CAN | O103: CHL | P103: CHN | Q103: ENE | R103: ENW | S103: EUE | T103: EUM | U103: EUW | V103: IDN | W103: IND | X103: JPN | Y103: LAM | Z103: MDA | AA103: MEA | AB103: MEX | AC103: NIG | AD103: RUS | AE103: SKT | AF103: USA
A104: Coke oven | B104: UPSCOA | C104: INPUT | D104: TJ / TJ COK | E104: =IF(E16=0,"",-E16/E$29) | F104: =IF(F16=0,"",-F16/F$29) -> 1.1074531 | G104: =IF(G16=0,"",-G16/G$29) | H104: =IF(H16=0,"",-H16/H$29) -> 1.4924941 | I104: =IF(I16=0,"",-I16/I$29) -> 1.5359945 | J104: =IF(J16=0,"",-J16/J$29) -> 1.216272 | K104: =IF(K16=0,"",-K16/K$29) | L104: =IF(L16=0,"",-L16/L$29) | ... AF104: =IF(AF16=0,"",-AF16/AF$29) -> 1.309837
A105: Coke oven | B105: UPSCOALIG | C105: INPUT | D105: TJ / TJ COK | E105: =IF(E17=0,"",-E17/E$29) | F105: =IF(F17=0,"",-F17/F$29) | G105: =IF(G17=0,"",-G17/G$29) | H105: =IF(H17=0,"",-H17/H$29) | I105: =IF(I17=0,"",-I17/I$29) | J105: =IF(J17=0,"",-J17/J$29) | K105: =IF(K17=0,"",-K17/K$29) | L105: =IF(L17=0,"",-L17/L$29) | ... AF105: =IF(AF17=0,"",-AF17/AF$29)
A106: Coke oven | B106: UPSGAS | C106: INPUT | D106: TJ / TJ COK | E106: =IF(E18=0,"",-E18/E$29) | F106: =IF(F18=0,"",-F18/F$29) | G106: =IF(G18=0,"",-G18/G$29) | H106: =IF(H18=0,"",-H18/H$29) | I106: =IF(I18=0,"",-I18/I$29) | J106: =IF(J18=0,"",-J18/J$29) | K106: =IF(K18=0,"",-K18/K$29) | L106: =IF(L18=0,"",-L18/L$29) | ... AF106: =IF(AF18=0,"",-AF18/AF$29)
A107: Coke oven | B107: UPSLPG | C107: INPUT | D107: TJ / TJ COK | E107: =IF(E19=0,"",-E19/E$29) | F107: =IF(F19=0,"",-F19/F$29) | G107: =IF(G19=0,"",-G19/G$29) | H107: =IF(H19=0,"",-H19/H$29) | I107: =IF(I19=0,"",-I19/I$29) | J107: =IF(J19=0,"",-J19/J$29) | K107: =IF(K19=0,"",-K19/K$29) | L107: =IF(L19=0,"",-L19/L$29) | ... AF107: =IF(AF19=0,"",-AF19/AF$29)
A108: Coke oven | B108: UPSOIL2 | C108: INPUT | D108: TJ / TJ COK | E108: =IF(E20=0,"",-E20/E$29) | F108: =IF(F20=0,"",-F20/F$29) | G108: =IF(G20=0,"",-G20/G$29) | H108: =IF(H20=0,"",-H20/H$29) | I108: =IF(I20=0,"",-I20/I$29) | J108: =IF(J20=0,"",-J20/J$29) | K108: =IF(K20=0,"",-K20/K$29) | L108: =IF(L20=0,"",-L20/L$29) | ... AF108: =IF(AF20=0,"",-AF20/AF$29)
A109: Coke oven | B109: UPSWAS | C109: INPUT | D109: TJ / TJ COK | E109: =IF(E21=0,"",-E21/E$29) | F109: =IF(F21=0,"",-F21/F$29) | G109: =IF(G21=0,"",-G21/G$29) | H109: =IF(H21=0,"",-H21/H$29) | I109: =IF(I21=0,"",-I21/I$29) | J109: =IF(J21=0,"",-J21/J$29) | K109: =IF(K21=0,"",-K21/K$29) | L109: =IF(L21=0,"",-L21/L$29) | ... AF109: =IF(AF21=0,"",-AF21/AF$29)
A111: Coke oven | B111: UPSCOG | C111: OUTPUT | D111: TJ / COK | E111: =IF(E112=1,E28/E29,"") | F111: =IF(F112=1,F28/F29,"") -> 0 | G111: =IF(G112=1,G28/G29,"") | H111: =IF(H112=1,H28/H29,"") -> 0.38263043 | I111: =IF(I112=1,I28/I29,"") -> 0.31443819 | J111: =IF(J112=1,J28/J29,"") -> 0.21472712 | K111: =IF(K112=1,K28/K29,"") | L111: =IF(L112=1,L28/L29,"") | ... AF111: =IF(AF112=1,AF28/AF29,"") -> 0.18084342
A112: Coke oven | B112: UPSCOK | C112: OUTPUT | D112: TJ | E112: =IF(E29>0,1,"") | F112: =IF(F29>0,1,"") -> 1 | G112: =IF(G29>0,1,"") | H112: =IF(H29>0,1,"") -> 1 | I112: =IF(I29>0,1,"") -> 1 | J112: =IF(J29>0,1,"") -> 1 | K112: =IF(K29>0,1,"") | L112: =IF(L29>0,1,"") | ... AF112: =IF(AF29>0,1,"") -> 1
A116: ** Approach to disaggregating EnBal across production pathways is to start off with determining DRI / EAF consumption via benchmarks
A117: ** Note that we do not differentiate between energy intensity of production between regions which is a limitation of this approach
A119: ELECTRIC ARC FURNACE (SCRAP)
E120: AFE | F120: AFN | G120: AFW | H120: AFZ | I120: ANZ | J120: ASC | K120: ASE | L120: ASO | M120: BRA | N120: CAN | O120: CHL | P120: CHN | Q120: ENE | R120: ENW | S120: EUE | T120: EUM | U120: EUW | V120: IDN | W120: IND | X120: JPN | Y120: LAM | Z120: MDA | AA120: MEA | AB120: MEX | AC120: NIG | AD120: RUS | AE120: SKT | AF120: USA
A121: EAF | B121: INDELC | C121: Benchmark | D121: GJ/t | E121: =$AI$131 -> 2.1 | F121: =$AI$131 -> 2.1 | G121: =$AI$131 -> 2.1 | H121: =$AI$131 -> 2.1 | I121: =$AI$131 -> 2.1 | J121: =$AI$131 -> 2.1 | K121: =$AI$131 -> 2.1 | L121: =$AI$131 -> 2.1 | ... X121: =$AI$131 -> 2.1 | Y121: 2.1 | Z121: =$AI$131 -> 2.1 | AA121: 2.1 | AB121: 2.1 | AC121: =$AI$131 -> 2.1 | AD121: =$AI$131 -> 2.1 | AE121: =$AI$131 -> 2.1 | AF121: =$AI$131 -> 2.1
A122: EAF | B122: INDELC | C122: Benchmark estimate | D122: TJ | E122: =E87*E81*E121*1000 -> 104.05407 | F122: =F87*F81*F121*1000 -> 3751.1744 | G122: =G87*G81*G121*1000 -> 114.45948 | H122: =H87*H81*H121*1000 -> 5872.8119 | I122: =I87*I81*I121*1000 -> 2661.1848 | J122: =J87*J81*J121*1000 -> 877.82571 | K122: =K87*K81*K121*1000 -> 8518.7431 | L122: =L87*L81*L121*1000 -> 6440.2257 | ... AF122: =AF87*AF81*AF121*1000 -> 109839.19
A123: EAF | C123: Share of IIS energy balance | D123: % | E123: =IFERROR(IF(E122=0,"",E122/E61),1) -> 0.017606442 | F123: =IFERROR(IF(F122=0,"",F122/F61),1) -> 1.220688 | G123: =IFERROR(IF(G122=0,"",G122/G61),1) -> 0.11491916 | H123: =IFERROR(IF(H122=0,"",H122/H61),1) -> 0.085137893 | I123: =IFERROR(IF(I122=0,"",I122/I61),1) -> 0.15483708 | J123: =IFERROR(IF(J122=0,"",J122/J61),1) -> 0.010045956 | K123: =IFERROR(IF(K122=0,"",K122/K61),1) -> 0.27022183 | L123: =IFERROR(IF(L122=0,"",L122/L61),1) -> 1 | ... AF123: =IFERROR(IF(AF122=0,"",AF122/AF61),1) -> 0.53733692 | AH123: 100% denotes EAF production but no or insufficient electricity input to achieve benchmark
A125: **This is the additional electricity requirement not provided in the energy balance to meet the benchmark
B126: INDELC | C126: Additional requirement | D126: TJ | E126: =_xlfn.IFS(E123<100%,0,E123>100%,(E123-1)*E122,E123=100%,E122) -> 0 | F126: =_xlfn.IFS(F123<100%,0,F123>100%,(F123-1)*F122,F123=100%,F122) -> 827.83936 | G126: =_xlfn.IFS(G123<100%,0,G123>100%,(G123-1)*G122,G123=100%,G122) -> 0 | H126: =_xlfn.IFS(H123<100%,0,H123>100%,(H123-1)*H122,H123=100%,H122) -> 0 | I126: =_xlfn.IFS(I123<100%,0,I123>100%,(I123-1)*I122,I123=100%,I122) -> 0 | J126: =_xlfn.IFS(J123<100%,0,J123>100%,(J123-1)*J122,J123=100%,J122) -> 0 | K126: =_xlfn.IFS(K123<100%,0,K123>100%,(K123-1)*K122,K123=100%,K122) -> 0 | L126: =_xlfn.IFS(L123<100%,0,L123>100%,(L123-1)*L122,L123=100%,L122) -> 6440.2257 | ... AF126: =_xlfn.IFS(AF123<100%,0,AF123>100%,(AF123-1)*AF122,AF123=100%,AF122) -> 0 | AH126: Additional energy provided from other industry (NES)
A128: DRI + ELECTRIC ARC FURNACE
E129: AFE | F129: AFN | G129: AFW | H129: AFZ | I129: ANZ | J129: ASC | K129: ASE | L129: ASO | M129: BRA | N129: CAN | O129: CHL | P129: CHN | Q129: ENE | R129: ENW | S129: EUE | T129: EUM | U129: EUW | V129: IDN | W129: IND | X129: JPN | Y129: LAM | Z129: MDA | AA129: MEA | AB129: MEX | AC129: NIG | AD129: RUS | AE129: SKT | AF129: USA
A130: DRI | B130: INDGAS | C130: % DRI using gas | D130: % | E130: 1 | F130: 1 | G130: 1 | H130: 1 | I130: 1 | J130: 1 | K130: 1 | L130: 1 | M130: 1 | N130: 1 | O130: 1 | P130: 1 | Q130: 1 | R130: 1 | S130: 1 | T130: 1 | U130: 1 | V130: 1 | W130: 0.05 | X130: 1 | Y130: 1 | Z130: 1 | AA130: 1 | AB130: 1 | AC130: 1 | AD130: 1 | AE130: 1 | AF130: 1 | AH130: Benchmark energy use (GJ/t)
A131: DRI | B131: INDGAS | C131: Benchmark | D131: GJ/t | E131: =$AI$132-E121 -> 15 | F131: =$AI$132-F121 -> 15 | G131: =$AI$132-G121 -> 15 | H131: =$AI$132-H121 -> 15 | I131: =$AI$132-I121 -> 15 | J131: =$AI$132-J121 -> 15 | K131: =$AI$132-K121 -> 15 | L131: =$AI$132-L121 -> 15 | ... AF131: =$AI$132-AF121 -> 15 | AH131: EAF | AI131: 2.1
A132: DRI | B132: INDGAS | C132: Benchmark estimate | D132: TJ | E132: =E86*E81*E131*1000*E130 -> 82.758268 | F132: =F86*F81*F131*1000*F130 -> 30196.139 | G132: =G86*G81*G131*1000*G130 -> 91.034095 | H132: =H86*H81*H131*1000*H130 -> 4670.8766 | I132: =I86*I81*I131*1000*I130 -> 2089.645 | J132: =J86*J81*J131*1000*J130 -> 694.3248 | K132: =K86*K81*K131*1000*K130 -> 8113.0887 | L132: =L86*L81*L131*1000*L130 -> 5093.9593 | ... AF132: =AF86*AF81*AF131*1000*AF130 -> 87116.997 | AH132: DRI-EAF | AI132: 17.1 | AJ132: (Gas-based) | AK132: 20 | AL132: (coal-based)
A133: DRI | C133: Share of IIS energy balance | D133: % | E133: =IFERROR(IF(E132<=0,"",E132/E62),"FLAG") -> FLAG | F133: =IFERROR(IF(F132<=0,"",F132/F62),"FLAG") -> 0.2880404 | G133: =IFERROR(IF(G132<=0,"",G132/G62),"FLAG") -> FLAG | H133: =IFERROR(IF(H132<=0,"",H132/H62),"FLAG") -> 0.50770398 | I133: =IFERROR(IF(I132<=0,"",I132/I62),"FLAG") -> 0.24805853 | J133: =IFERROR(IF(J132<=0,"",J132/J62),"FLAG") -> 0.027524173 | K133: =IFERROR(IF(K132<=0,"",K132/K62),"FLAG") -> 0.54359053 | L133: =IFERROR(IF(L132<=0,"",L132/L62),"FLAG") -> 7.2460303 | ... AF133: =IFERROR(IF(AF132<=0,"",AF132/AF62),"FLAG") -> 0.22163284 | AH133: BF-BOF | AI133: 21.4
...

Sheet IIS_BY Techs
A1: Characterization of sectoral technologies
A2: Sector: | B2: Iron and Steel
A3: Code: | B3: IS
A5: Production pathways | H5: https://www.ipcc-nggip.iges.or.jp/public/2019rf/pdf/3_Volume3/19R_V3_Ch04_Metal_Industry.pdf | AM5: Process definition
A6: ~FI_T | AM6: ~FI_Process
A7: TechName | B7: *Technology Description | C7: Comm-OUT | D7: PRC_CAPACT | E7: NCAP_AFA | F7: FIXOM | G7: *NCAP_TLIFE | H7: Attribute | I7: *Unit | J7: AFE | K7: AFN | L7: AFW | M7: AFZ | N7: ANZ | O7: ASC | P7: ASE | Q7: ASO | R7: BRA | S7: CAN | T7: CHL | U7: CHN | V7: ENE | W7: ENW | X7: EUE | Y7: EUM | Z7: EUW | AA7: IDN | AB7: IND | AC7: JPN | AD7: LAM | AE7: MDA | AF7: MEA | AG7: MEX | AH7: NIG | AI7: RUS | AJ7: SKT | AK7: USA | AM7: Sets | AN7: TechName | AO7: TechDesc | AP7: Tact | AQ7: Tcap | AR7: *Comm-IN | AS7: Tslvl | AT7: PrimaryCG | AU7: Vintage
A8: *Technology Name | B8: Description | C8: Output Commodity | D8: Capacity to Activity Factor | E8: Availability factor | F8: Fixed costs ($M/Mt) | G8: Technical life | H8: TIMES attribute for regionalized variables -> | I8: unit | AM8: \I: Process Set Membership | AN8: Technology name | AO8: Description | AP8: Activity unit | AQ8: Capacity unit | AR8: Input Commodity | AS8: TimeSlice level of Process Activity | AT8: Primary Commodity Group | AU8: Vintage Tracking
A9: =AN9 -> I-IS-BF_BOF | B9: =AO9 -> IND Iron and Steel technology: BF-BOF | C9: IIS | D9: 1 | E9: ='Inputs_BY IIS'!AM$82 -> 0.8 | H9: PRC_RESID | I9: Mt | J9: ='Inputs_BY IIS'!E85*'Inputs_BY IIS'!E$81*'Inputs_BY IIS'!E$82 -> 0 | K9: ='Inputs_BY IIS'!F85*'Inputs_BY IIS'!F$81*'Inputs_BY IIS'!F$82 -> 1.2212887 | L9: ='Inputs_BY IIS'!G85*'Inputs_BY IIS'!G$81*'Inputs_BY IIS'!G$82 -> 0 | M9: ='Inputs_BY IIS'!H85*'Inputs_BY IIS'!H$81*'Inputs_BY IIS'!H$82 -> 6.0496933 | N9: ='Inputs_BY IIS'!I85*'Inputs_BY IIS'!I$81*'Inputs_BY IIS'!I$82 -> 5.4031611 | O9: ='Inputs_BY IIS'!J85*'Inputs_BY IIS'!J$81*'Inputs_BY IIS'!J$82 -> 4.3577082 | P9: ='Inputs_BY IIS'!K85*'Inputs_BY IIS'!K$81*'Inputs_BY IIS'!K$82 -> 1.0141361 | Q9: ='Inputs_BY IIS'!L85*'Inputs_BY IIS'!L$81*'Inputs_BY IIS'!L$82 -> 0 | ... AK9: ='Inputs_BY IIS'!AF85*'Inputs_BY IIS'!AF$81*'Inputs_BY IIS'!AF$82 -> 35.750563 | AM9: DMD | AN9: I-IS-BF_BOF | AO9: IND Iron and Steel technology: BF-BOF | AP9: PJ | AQ9: Mt
A10: =AN10 -> I-IS-DRI_EAF_COA | B10: =AO10 -> IND Iron and Steel technology: DRI using coal plus EAF | C10: IIS | D10: 1 | E10: ='Inputs_BY IIS'!AM$82 -> 0.8 | H10: PRC_RESID | I10: Mt | J10: ='Inputs_BY IIS'!E86*'Inputs_BY IIS'!E$81*(1-'Inputs_BY IIS'!E$130)/$E10 -> 0 | K10: ='Inputs_BY IIS'!F86*'Inputs_BY IIS'!F$81*(1-'Inputs_BY IIS'!F$130)/$E10 -> 0 | L10: ='Inputs_BY IIS'!G86*'Inputs_BY IIS'!G$81*(1-'Inputs_BY IIS'!G$130)/$E10 -> 0 | M10: ='Inputs_BY IIS'!H86*'Inputs_BY IIS'!H$81*(1-'Inputs_BY IIS'!H$130)/$E10 -> 0 | N10: ='Inputs_BY IIS'!I86*'Inputs_BY IIS'!I$81*(1-'Inputs_BY IIS'!I$130)/$E10 -> 0 | O10: ='Inputs_BY IIS'!J86*'Inputs_BY IIS'!J$81*(1-'Inputs_BY IIS'!J$130)/$E10 -> 0 | P10: ='Inputs_BY IIS'!K86*'Inputs_BY IIS'!K$81*(1-'Inputs_BY IIS'!K$130)/$E10 -> 0 | Q10: ='Inputs_BY IIS'!L86*'Inputs_BY IIS'!L$81*(1-'Inputs_BY IIS'!L$130)/$E10 -> 0 | ... AK10: ='Inputs_BY IIS'!AF86*'Inputs_BY IIS'!AF$81*(1-'Inputs_BY IIS'!AF$130)/$E10 -> 0 | AM10: DMD | AN10: I-IS-DRI_EAF_COA | AO10: IND Iron and Steel technology: DRI using coal plus EAF | AP10: PJ | AQ10: Mt
A11: =AN11 -> I-IS-DRI_EAF_NGA | B11: =AO11 -> IND Iron and Steel technology: DRI using gas plus EAF | C11: IIS | D11: 1 | E11: ='Inputs_BY IIS'!AM$82 -> 0.8 | H11: PRC_RESID | I11: Mt | J11: ='Inputs_BY IIS'!E86*'Inputs_BY IIS'!E$81*'Inputs_BY IIS'!E$130/$E11 -> 0.0068965223 | K11: ='Inputs_BY IIS'!F86*'Inputs_BY IIS'!F$81*'Inputs_BY IIS'!F$130/$E11 -> 2.5163449 | L11: ='Inputs_BY IIS'!G86*'Inputs_BY IIS'!G$81*'Inputs_BY IIS'!G$130/$E11 -> 0.0075861746 | M11: ='Inputs_BY IIS'!H86*'Inputs_BY IIS'!H$81*'Inputs_BY IIS'!H$130/$E11 -> 0.38923972 | N11: ='Inputs_BY IIS'!I86*'Inputs_BY IIS'!I$81*'Inputs_BY IIS'!I$130/$E11 -> 0.17413708 | O11: ='Inputs_BY IIS'!J86*'Inputs_BY IIS'!J$81*'Inputs_BY IIS'!J$130/$E11 -> 0.0578604 | P11: ='Inputs_BY IIS'!K86*'Inputs_BY IIS'!K$81*'Inputs_BY IIS'!K$130/$E11 -> 0.67609072 | Q11: ='Inputs_BY IIS'!L86*'Inputs_BY IIS'!L$81*'Inputs_BY IIS'!L$130/$E11 -> 0.42449661 | ... AK11: ='Inputs_BY IIS'!AF86*'Inputs_BY IIS'!AF$81*'Inputs_BY IIS'!AF$130/$E11 -> 7.2597497 | AM11: DMD | AN11: I-IS-DRI_EAF_NGA | AO11: IND Iron and Steel technology: DRI using gas plus EAF | AP11: PJ | AQ11: Mt
A12: =AN12 -> I-IS-SCP_EAF | B12: =AO12 -> IND Iron and Steel technology: EAF using scrap (secondary) | C12: IIS | D12: 1 | E12: ='Inputs_BY IIS'!AM$82 -> 0.8 | H12: PRC_RESID | I12: Mt | J12: ='Inputs_BY IIS'!E87*'Inputs_BY IIS'!E$81/$E12 -> 0.061936948 | K12: ='Inputs_BY IIS'!F87*'Inputs_BY IIS'!F$81/$E12 -> 2.2328419 | L12: ='Inputs_BY IIS'!G87*'Inputs_BY IIS'!G$81/$E12 -> 0.068130643 | M12: ='Inputs_BY IIS'!H87*'Inputs_BY IIS'!H$81/$E12 -> 3.4957214 | N12: ='Inputs_BY IIS'!I87*'Inputs_BY IIS'!I$81/$E12 -> 1.5840386 | O12: ='Inputs_BY IIS'!J87*'Inputs_BY IIS'!J$81/$E12 -> 0.5225153 | P12: ='Inputs_BY IIS'!K87*'Inputs_BY IIS'!K$81/$E12 -> 5.0706804 | Q12: ='Inputs_BY IIS'!L87*'Inputs_BY IIS'!L$81/$E12 -> 3.8334677 | ... AK12: ='Inputs_BY IIS'!AF87*'Inputs_BY IIS'!AF$81/$E12 -> 65.38047 | AM12: DMD | AN12: I-IS-SCP_EAF | AO12: IND Iron and Steel technology: EAF using scrap (secondary) | AP12: PJ | AQ12: Mt
A13: =AN9 -> I-IS-BF_BOF | B13: =AO9 -> IND Iron and Steel technology: BF-BOF | H13: NCAP_TLIFE | I13: Years | J13: 25 | K13: 25 | L13: 25 | M13: 25 | N13: 25 | O13: 25 | P13: 25 | Q13: 25 | R13: 25 | S13: 25 | T13: 25 | U13: 25 | V13: 25 | W13: 25 | X13: 25 | Y13: 25 | Z13: 25 | AA13: 25 | AB13: 25 | AC13: 25 | AD13: 25 | AE13: 25 | AF13: 25 | AG13: 25 | AH13: 25 | AI13: 25 | AJ13: 25 | AK13: 25 | AM13: MAT | AN13: I-IS-SCP_PRD | AO13: IND Scrap IS Dummy | AP13: Mt | AQ13: Mta
A14: =AN10 -> I-IS-DRI_EAF_COA | B14: =AO10 -> IND Iron and Steel technology: DRI using coal plus EAF | H14: NCAP_TLIFE | I14: Years | J14: 25 | K14: 25 | L14: 25 | M14: 25 | N14: 25 | O14: 25 | P14: 25 | Q14: 25 | R14: 25 | S14: 25 | T14: 25 | U14: 25 | V14: 25 | W14: 25 | X14: 25 | Y14: 25 | Z14: 25 | AA14: 25 | AB14: 25 | AC14: 25 | AD14: 25 | AE14: 25 | AF14: 25 | AG14: 25 | AH14: 25 | AI14: 25 | AJ14: 25 | AK14: 25
A15: =AN11 -> I-IS-DRI_EAF_NGA | B15: =AO11 -> IND Iron and Steel technology: DRI using gas plus EAF | H15: NCAP_TLIFE | I15: Years | J15: 25 | K15: 25 | L15: 25 | M15: 25 | N15: 25 | O15: 25 | P15: 25 | Q15: 25 | R15: 25 | S15: 25 | T15: 25 | U15: 25 | V15: 25 | W15: 25 | X15: 25 | Y15: 25 | Z15: 25 | AA15: 25 | AB15: 25 | AC15: 25 | AD15: 25 | AE15: 25 | AF15: 25 | AG15: 25 | AH15: 25 | AI15: 25 | AJ15: 25 | AK15: 25
A16: =AN12 -> I-IS-SCP_EAF | B16: =AO12 -> IND Iron and Steel technology: EAF using scrap (secondary) | H16: NCAP_TLIFE | I16: Years | J16: 25 | K16: 25 | L16: 25 | M16: 25 | N16: 25 | O16: 25 | P16: 25 | Q16: 25 | R16: 25 | S16: 25 | T16: 25 | U16: 25 | V16: 25 | W16: 25 | X16: 25 | Y16: 25 | Z16: 25 | AA16: 25 | AB16: 25 | AC16: 25 | AD16: 25 | AE16: 25 | AF16: 25 | AG16: 25 | AH16: 25 | AI16: 25 | AJ16: 25 | AK16: 25
A20: ~FI_T
A21: TechName | B21: *Technology Description | C21: Comm-IN | D21: Comm-OUT | E21: * | F21: * | G21: LimType | H21: Attribute | I21: *Unit | J21: AFE | K21: AFN | L21: AFW | M21: AFZ | N21: ANZ | O21: ASC | P21: ASE | Q21: ASO | R21: BRA | S21: CAN | T21: CHL | U21: CHN | V21: ENE | W21: ENW | X21: EUE | Y21: EUM | Z21: EUW | AA21: IDN | AB21: IND | AC21: JPN | AD21: LAM | AE21: MDA | AF21: MEA | AG21: MEX | AH21: NIG | AI21: RUS | AJ21: SKT | AK21: USA
A22: *Technology Name | B22: Description | C22: Input Commodity | D22: Output commodity | G22: Sign of the equation | H22: TIMES attribute for regionalized variables -> | I22: unit
A23: =AN9 -> I-IS-BF_BOF | B23: =AO9 -> IND Iron and Steel technology: BF-BOF | C23: INDBGS | H23: INPUT | I23: PJ / Mt | J23: ='Inputs_BY IIS'!E258 | K23: ='Inputs_BY IIS'!F258 | L23: ='Inputs_BY IIS'!G258 | M23: ='Inputs_BY IIS'!H258 | N23: ='Inputs_BY IIS'!I258 | O23: ='Inputs_BY IIS'!J258 | P23: ='Inputs_BY IIS'!K258 | Q23: ='Inputs_BY IIS'!L258 | ... AK23: ='Inputs_BY IIS'!AF258
C24: INDBIO | H24: INPUT | I24: PJ / Mt | J24: ='Inputs_BY IIS'!E259 | K24: ='Inputs_BY IIS'!F259 | L24: ='Inputs_BY IIS'!G259 | M24: ='Inputs_BY IIS'!H259 | N24: ='Inputs_BY IIS'!I259 | O24: ='Inputs_BY IIS'!J259 | P24: ='Inputs_BY IIS'!K259 | Q24: ='Inputs_BY IIS'!L259 | ... AK24: ='Inputs_BY IIS'!AF259
C25: INDBLQ | H25: INPUT | I25: PJ / Mt | J25: ='Inputs_BY IIS'!E260 | K25: ='Inputs_BY IIS'!F260 | L25: ='Inputs_BY IIS'!G260 | M25: ='Inputs_BY IIS'!H260 | N25: ='Inputs_BY IIS'!I260 | O25: ='Inputs_BY IIS'!J260 | P25: ='Inputs_BY IIS'!K260 | Q25: ='Inputs_BY IIS'!L260 | ... AK25: ='Inputs_BY IIS'!AF260 -> 0.0025873719
C26: INDCOA | H26: INPUT | I26: PJ / Mt | J26: ='Inputs_BY IIS'!E261 | K26: ='Inputs_BY IIS'!F261 -> 0.012282108 | L26: ='Inputs_BY IIS'!G261 | M26: ='Inputs_BY IIS'!H261 -> 6.7475262 | N26: ='Inputs_BY IIS'!I261 -> 0.14320321 | O26: ='Inputs_BY IIS'!J261 -> 6.7475262 | P26: ='Inputs_BY IIS'!K261 -> 3.4684694 | Q26: ='Inputs_BY IIS'!L261 | ... AK26: ='Inputs_BY IIS'!AF261 -> 0.30985526
C27: INDCOG | H27: INPUT | I27: PJ / Mt | J27: ='Inputs_BY IIS'!E262 | K27: ='Inputs_BY IIS'!F262 | L27: ='Inputs_BY IIS'!G262 | M27: ='Inputs_BY IIS'!H262 -> 2.4724841 | N27: ='Inputs_BY IIS'!I262 -> 0.21376375 | O27: ='Inputs_BY IIS'!J262 | P27: ='Inputs_BY IIS'!K262 | Q27: ='Inputs_BY IIS'!L262 | ... AK27: ='Inputs_BY IIS'!AF262 -> 0.0075872932
C28: INDCOK | H28: INPUT | I28: PJ / Mt | J28: ='Inputs_BY IIS'!E263 | K28: ='Inputs_BY IIS'!F263 -> 4.5157218 | L28: ='Inputs_BY IIS'!G263 | M28: ='Inputs_BY IIS'!H263 -> 1.2021271 | N28: ='Inputs_BY IIS'!I263 -> 2.8307503 | O28: ='Inputs_BY IIS'!J263 -> 7.7210884 | P28: ='Inputs_BY IIS'!K263 -> 0.25267812 | Q28: ='Inputs_BY IIS'!L263 | ... AK28: ='Inputs_BY IIS'!AF263 -> 2.5828614
C29: INDELC | H29: INPUT | I29: PJ / Mt | J29: ='Inputs_BY IIS'!E264 | K29: ='Inputs_BY IIS'!F264 | L29: ='Inputs_BY IIS'!G264 | M29: ='Inputs_BY IIS'!H264 -> 12.904221 | N29: ='Inputs_BY IIS'!I264 -> 3.2928096 | O29: ='Inputs_BY IIS'!J264 -> 15.280454 | P29: ='Inputs_BY IIS'!K264 -> 15.280454 | Q29: ='Inputs_BY IIS'!L264 | ... AK29: ='Inputs_BY IIS'!AF264 -> 2.8803194
C30: INDGAS | H30: INPUT | I30: PJ / Mt | J30: ='Inputs_BY IIS'!E265 | K30: ='Inputs_BY IIS'!F265 -> 10.492673 | L30: ='Inputs_BY IIS'!G265 | M30: ='Inputs_BY IIS'!H265 -> 0.93581673 | N30: ='Inputs_BY IIS'!I265 -> 1.465428 | O30: ='Inputs_BY IIS'!J265 -> 7.0368627 | P30: ='Inputs_BY IIS'!K265 -> 8.3961998 | Q30: ='Inputs_BY IIS'!L265 | ... AK30: ='Inputs_BY IIS'!AF265 -> 10.492673
C31: INDHET | H31: INPUT | I31: PJ / Mt | J31: ='Inputs_BY IIS'!E266 | K31: ='Inputs_BY IIS'!F266 | L31: ='Inputs_BY IIS'!G266 | M31: ='Inputs_BY IIS'!H266 | N31: ='Inputs_BY IIS'!I266 | O31: ='Inputs_BY IIS'!J266 -> 4.8418281 | P31: ='Inputs_BY IIS'!K266 | Q31: ='Inputs_BY IIS'!L266 | ... AK31: ='Inputs_BY IIS'!AF266 -> 0.25618478
C32: INDLPG | H32: INPUT | I32: PJ / Mt | J32: ='Inputs_BY IIS'!E267 | K32: ='Inputs_BY IIS'!F267 | L32: ='Inputs_BY IIS'!G267 | M32: ='Inputs_BY IIS'!H267 | N32: ='Inputs_BY IIS'!I267 -> 0.0069403816 | O32: ='Inputs_BY IIS'!J267 -> 0.44454892 | P32: ='Inputs_BY IIS'!K267 -> 0.44454892 | Q32: ='Inputs_BY IIS'!L267 | ... AK32: ='Inputs_BY IIS'!AF267 -> 0.0031817681
C33: INDOIL | H33: INPUT | I33: PJ / Mt | J33: ='Inputs_BY IIS'!E268 | K33: ='Inputs_BY IIS'!F268 -> 2.1005555 | L33: ='Inputs_BY IIS'!G268 | M33: ='Inputs_BY IIS'!H268 -> 0.10455075 | N33: ='Inputs_BY IIS'!I268 -> 0.19456203 | O33: ='Inputs_BY IIS'!J268 -> 2.1005555 | P33: ='Inputs_BY IIS'!K268 -> 2.1005555 | Q33: ='Inputs_BY IIS'!L268 | ... AK33: ='Inputs_BY IIS'!AF268 -> 0.1270959
C34: INDWAS | H34: INPUT | I34: PJ / Mt | J34: ='Inputs_BY IIS'!E271 | K34: ='Inputs_BY IIS'!F271 | L34: ='Inputs_BY IIS'!G271 | M34: ='Inputs_BY IIS'!H271 | N34: ='Inputs_BY IIS'!I271 | O34: ='Inputs_BY IIS'!J271 | P34: ='Inputs_BY IIS'!K271 | Q34: ='Inputs_BY IIS'!L271 | ... AK34: ='Inputs_BY IIS'!AF271
C35: BIOMASS | H35: INPUT | I35: PJ / Mt | J35: ='Inputs_BY IIS'!E193 | K35: ='Inputs_BY IIS'!F193 | L35: ='Inputs_BY IIS'!G193 | M35: ='Inputs_BY IIS'!H193 | N35: ='Inputs_BY IIS'!I193 | O35: ='Inputs_BY IIS'!J193 | P35: ='Inputs_BY IIS'!K193 | Q35: ='Inputs_BY IIS'!L193 | ... AK35: ='Inputs_BY IIS'!AF193 | AN35: [UPS denotes input into BF; however technology combines both BF and BOF]
C36: COA | H36: INPUT | I36: PJ / Mt | J36: ='Inputs_BY IIS'!E194 | K36: =IF('Inputs_BY IIS'!F194=0,"",'Inputs_BY IIS'!F194) -> 0.51994258 | L36: =IF('Inputs_BY IIS'!G194=0,"",'Inputs_BY IIS'!G194) | M36: =IF('Inputs_BY IIS'!H194=0,"",'Inputs_BY IIS'!H194) | N36: =IF('Inputs_BY IIS'!I194=0,"",'Inputs_BY IIS'!I194) -> 0.37987022 | O36: =IF('Inputs_BY IIS'!J194=0,"",'Inputs_BY IIS'!J194) | P36: =IF('Inputs_BY IIS'!K194=0,"",'Inputs_BY IIS'!K194) | Q36: =IF('Inputs_BY IIS'!L194=0,"",'Inputs_BY IIS'!L194) | R36: =IF('Inputs_BY IIS'!M194=0,"",'Inputs_BY IIS'!M194) | ... AK36: =IF('Inputs_BY IIS'!AF194=0,"",'Inputs_BY IIS'!AF194) -> 0.93907613
C37: COACOK | H37: INPUT | I37: PJ / Mt | J37: ='Inputs_BY IIS'!E195 | K37: =IF('Inputs_BY IIS'!F195=0,"",'Inputs_BY IIS'!F195) -> 15.425621 | L37: =IF('Inputs_BY IIS'!G195=0,"",'Inputs_BY IIS'!G195) | M37: =IF('Inputs_BY IIS'!H195=0,"",'Inputs_BY IIS'!H195) -> 9.3659707 | N37: =IF('Inputs_BY IIS'!I195=0,"",'Inputs_BY IIS'!I195) -> 12.216691 | O37: =IF('Inputs_BY IIS'!J195=0,"",'Inputs_BY IIS'!J195) -> 15.425621 | P37: =IF('Inputs_BY IIS'!K195=0,"",'Inputs_BY IIS'!K195) -> 5.9878552 | Q37: =IF('Inputs_BY IIS'!L195=0,"",'Inputs_BY IIS'!L195) | R37: =IF('Inputs_BY IIS'!M195=0,"",'Inputs_BY IIS'!M195) | ... AK37: =IF('Inputs_BY IIS'!AF195=0,"",'Inputs_BY IIS'!AF195) -> 8.3854974
C38: GASNAT | H38: INPUT | I38: PJ / Mt | J38: ='Inputs_BY IIS'!E196 | K38: ='Inputs_BY IIS'!F196 | L38: ='Inputs_BY IIS'!G196 | M38: ='Inputs_BY IIS'!H196 | N38: ='Inputs_BY IIS'!I196 | O38: ='Inputs_BY IIS'!J196 | P38: ='Inputs_BY IIS'!K196 | Q38: ='Inputs_BY IIS'!L196 | ... AK38: ='Inputs_BY IIS'!AF196
C39: OILHFO | H39: INPUT | I39: PJ / Mt | J39: ='Inputs_BY IIS'!E197 | K39: ='Inputs_BY IIS'!F197 | L39: ='Inputs_BY IIS'!G197 | M39: ='Inputs_BY IIS'!H197 | N39: ='Inputs_BY IIS'!I197 | O39: ='Inputs_BY IIS'!J197 -> 1.3127 | P39: ='Inputs_BY IIS'!K197 | Q39: ='Inputs_BY IIS'!L197 | ... AK39: ='Inputs_BY IIS'!AF197
C40: OILOPP | H40: INPUT | I40: PJ / Mt | J40: ='Inputs_BY IIS'!E198 | K40: ='Inputs_BY IIS'!F198 | L40: ='Inputs_BY IIS'!G198 | M40: ='Inputs_BY IIS'!H198 | N40: ='Inputs_BY IIS'!I198 | O40: ='Inputs_BY IIS'!J198 | P40: ='Inputs_BY IIS'!K198 | Q40: ='Inputs_BY IIS'!L198 | ... AK40: ='Inputs_BY IIS'!AF198
C41: IISSCP | H41: INPUT | I41: Mt / Mt | K41: ='Inputs_BY IIS'!F89 -> 0.125 | M41: ='Inputs_BY IIS'!H89 -> 0.125 | N41: ='Inputs_BY IIS'!I89 -> 0.125 | O41: ='Inputs_BY IIS'!J89 -> 0.125 | P41: ='Inputs_BY IIS'!K89 -> 0.125 | R41: ='Inputs_BY IIS'!M89 -> 0.125 | S41: ='Inputs_BY IIS'!N89 -> 0.125 | T41: ='Inputs_BY IIS'!O89 -> 0.125 | U41: ='Inputs_BY IIS'!P89 -> 0.125 | V41: ='Inputs_BY IIS'!Q89 -> 0.125 | W41: ='Inputs_BY IIS'!R89 -> 0.125 | X41: ='Inputs_BY IIS'!S89 -> 0.125 | Y41: ='Inputs_BY IIS'!T89 -> 0.125 | ... AG41: ='Inputs_BY IIS'!AB89 -> 0.125 | AI41: ='Inputs_BY IIS'!AD89 -> 0.125 | AJ41: ='Inputs_BY IIS'!AE89 -> 0.125 | AK41: ='Inputs_BY IIS'!AF89 -> 0.125
D42: GASBFG | H42: OUTPUT | I42: PJ / Mt | J42: =IF('Inputs_BY IIS'!E176=0,"",'Inputs_BY IIS'!E176) | K42: =IF('Inputs_BY IIS'!F176=0,"",'Inputs_BY IIS'!F176) | L42: =IF('Inputs_BY IIS'!G176=0,"",'Inputs_BY IIS'!G176) | M42: =IF('Inputs_BY IIS'!H176=0,"",'Inputs_BY IIS'!H176) | N42: =IF('Inputs_BY IIS'!I176=0,"",'Inputs_BY IIS'!I176) -> 5.2163908 | O42: =IF('Inputs_BY IIS'!J176=0,"",'Inputs_BY IIS'!J176) -> 2.2749917 | P42: =IF('Inputs_BY IIS'!K176=0,"",'Inputs_BY IIS'!K176) | Q42: =IF('Inputs_BY IIS'!L176=0,"",'Inputs_BY IIS'!L176) | ... AK42: =IF('Inputs_BY IIS'!AF176=0,"",'Inputs_BY IIS'!AF176) -> 1.523018 | AN42: ='Inputs_BY IIS'!AH176 -> BFG production net of use in I&S sector
D43: INDCO2c | H43: OUTPUT | I43: kt/Mt | J43: =IF(IFERROR($AM43*('Inputs_BY IIS'!E186+'Inputs_BY IIS'!E189),"")=0,"",IFERROR($AM43*('Inputs_BY IIS'!E186+'Inputs_BY IIS'!E189),"")) | K43: =IF(IFERROR($AM43*('Inputs_BY IIS'!F186+'Inputs_BY IIS'!F189),"")=0,"",IFERROR($AM43*('Inputs_BY IIS'!F186+'Inputs_BY IIS'!F189),"")) -> 891.47636 | L43: =IF(IFERROR($AM43*('Inputs_BY IIS'!G186+'Inputs_BY IIS'!G189),"")=0,"",IFERROR($AM43*('Inputs_BY IIS'!G186+'Inputs_BY IIS'!G189),"")) | M43: =IF(IFERROR($AM43*('Inputs_BY IIS'!H186+'Inputs_BY IIS'!H189),"")=0,"",IFERROR($AM43*('Inputs_BY IIS'!H186+'Inputs_BY IIS'!H189),"")) -> 974.61966 | N43: =IF(IFERROR($AM43*('Inputs_BY IIS'!I186+'Inputs_BY IIS'!I189),"")=0,"",IFERROR($AM43*('Inputs_BY IIS'!I186+'Inputs_BY IIS'!I189),"")) -> 1091.301 | O43: =IF(IFERROR($AM43*('Inputs_BY IIS'!J186+'Inputs_BY IIS'!J189),"")=0,"",IFERROR($AM43*('Inputs_BY IIS'!J186+'Inputs_BY IIS'!J189),"")) -> 1329.0243 | P43: =IF(IFERROR($AM43*('Inputs_BY IIS'!K186+'Inputs_BY IIS'!K189),"")=0,"",IFERROR($AM43*('Inputs_BY IIS'!K186+'Inputs_BY IIS'!K189),"")) -> 850.52688 | Q43: =IF(IFERROR($AM43*('Inputs_BY IIS'!L186+'Inputs_BY IIS'!L189),"")=0,"",IFERROR($AM43*('Inputs_BY IIS'!L186+'Inputs_BY IIS'!L189),"")) | ... AK43: =IF(IFERROR($AM43*('Inputs_BY IIS'!AF186+'Inputs_BY IIS'!AF189),"")=0,"",IFERROR($AM43*('Inputs_BY IIS'!AF186+'Inputs_BY IIS'!AF189),"")) -> 807.39638 | AM43: 260 | AN43: KtCO2/PJ for combustion of BFG (as a final energy commodity in the process)
D44: INDCO2p | H44: OUTPUT | I44: kt/Mt | J44: =IF('Inputs_BY IIS'!E81*'Inputs_BY IIS'!E85=0,"",$AM$44) | K44: =IF('Inputs_BY IIS'!F81*'Inputs_BY IIS'!F85=0,"",$AM$44) -> 392.37852 | L44: =IF('Inputs_BY IIS'!G81*'Inputs_BY IIS'!G85=0,"",$AM$44) | M44: =IF('Inputs_BY IIS'!H81*'Inputs_BY IIS'!H85=0,"",$AM$44) -> 392.37852 | N44: =IF('Inputs_BY IIS'!I81*'Inputs_BY IIS'!I85=0,"",$AM$44) -> 392.37852 | O44: =IF('Inputs_BY IIS'!J81*'Inputs_BY IIS'!J85=0,"",$AM$44) -> 392.37852 | P44: =IF('Inputs_BY IIS'!K81*'Inputs_BY IIS'!K85=0,"",$AM$44) -> 392.37852 | Q44: =IF('Inputs_BY IIS'!L81*'Inputs_BY IIS'!L85=0,"",$AM$44) | ... AK44: =IF('Inputs_BY IIS'!AF81*'Inputs_BY IIS'!AF85=0,"",$AM$44) -> 392.37852 | AM44: =523000/(SUM(J9:AK9)/1.25) -> 392.37852 | AN44: KtCO2/Mt of steel (calibration factor for iron and steel process emissions)
D45: IIS | H45: OUTPUT | I45: Mt | K45: 1 | M45: 1 | N45: 1 | O45: 1 | P45: 1 | R45: 1 | S45: 1 | T45: 1 | U45: 1 | V45: 1 | W45: 1 | X45: 1 | Y45: 1 | Z45: 1 | AA45: 1 | AB45: 1 | AC45: 1 | AD45: 1 | AE45: 1 | AF45: 1 | AG45: 1 | AI45: 1 | AJ45: 1 | AK45: 1
A46: =AN10 -> I-IS-DRI_EAF_COA | B46: =AO10 -> IND Iron and Steel technology: DRI using coal plus EAF | C46: INDCOA | H46: INPUT | I46: PJ / Mt | J46: ='Inputs_BY IIS'!E138 -> 17.9 | K46: ='Inputs_BY IIS'!F138 -> 17.9 | L46: ='Inputs_BY IIS'!G138 -> 17.9 | M46: ='Inputs_BY IIS'!H138 -> 17.9 | N46: ='Inputs_BY IIS'!I138 -> 17.9 | O46: ='Inputs_BY IIS'!J138 -> 17.9 | P46: ='Inputs_BY IIS'!K138 -> 17.9 | Q46: ='Inputs_BY IIS'!L138 -> 17.9 | ... AK46: ='Inputs_BY IIS'!AF138 -> 17.9
C47: INDELC | H47: INPUT | I47: PJ / Mt | J47: ='Inputs_BY IIS'!E143 -> 2.1 | K47: ='Inputs_BY IIS'!F143 -> 2.1 | L47: ='Inputs_BY IIS'!G143 -> 2.1 | M47: ='Inputs_BY IIS'!H143 -> 2.1 | N47: ='Inputs_BY IIS'!I143 -> 2.1 | O47: ='Inputs_BY IIS'!J143 -> 2.1 | P47: ='Inputs_BY IIS'!K143 -> 2.1 | Q47: ='Inputs_BY IIS'!L143 -> 2.1 | ... AK47: ='Inputs_BY IIS'!AF143 -> 2.1
C48: IISSCP | H48: INPUT | I48: Mt / Mt | J48: ='Inputs_BY IIS'!E90 -> 0.125 | K48: ='Inputs_BY IIS'!F90 -> 0.125 | L48: ='Inputs_BY IIS'!G90 -> 0.125 | M48: ='Inputs_BY IIS'!H90 -> 0.125 | N48: ='Inputs_BY IIS'!I90 -> 0.125 | O48: ='Inputs_BY IIS'!J90 -> 0.125 | P48: ='Inputs_BY IIS'!K90 -> 0.125 | Q48: ='Inputs_BY IIS'!L90 -> 0.125 | ... AK48: ='Inputs_BY IIS'!AF90 -> 0.125
D49: INDCO2p | H49: OUTPUT | I49: kt/Mt | J49: =$AM49*1000 -> 880 | K49: =$AM49*1000 -> 880 | L49: =$AM49*1000 -> 880 | M49: =$AM49*1000 -> 880 | N49: =$AM49*1000 -> 880 | O49: =$AM49*1000 -> 880 | P49: =$AM49*1000 -> 880 | Q49: =$AM49*1000 -> 880 | ... AK49: =$AM49*1000 -> 880 | AM49: =0.7+0.18 -> 0.88 | AN49: From IPCC, https://www.ipcc-nggip.iges.or.jp/public/2019rf/pdf/3_Volume3/19R_V3_Ch04_Metal_Industry.pdf
D50: IIS | H50: OUTPUT | I50: Mt | J50: 1 | K50: 1 | L50: 1 | M50: 1 | N50: 1 | O50: 1 | P50: 1 | Q50: 1 | R50: 1 | S50: 1 | T50: 1 | U50: 1 | V50: 1 | W50: 1 | X50: 1 | Y50: 1 | Z50: 1 | AA50: 1 | AB50: 1 | AC50: 1 | AD50: 1 | AE50: 1 | AF50: 1 | AG50: 1 | AH50: 1 | AI50: 1 | AJ50: 1 | AK50: 1
A51: =AN11 -> I-IS-DRI_EAF_NGA | B51: =AO11 -> IND Iron and Steel technology: DRI using gas plus EAF | C51: INDGAS | H51: INPUT | I51: PJ / Mt | J51: ='Inputs_BY IIS'!E131 -> 15 | K51: ='Inputs_BY IIS'!F131 -> 15 | L51: ='Inputs_BY IIS'!G131 -> 15 | M51: ='Inputs_BY IIS'!H131 -> 15 | N51: ='Inputs_BY IIS'!I131 -> 15 | O51: ='Inputs_BY IIS'!J131 -> 15 | P51: ='Inputs_BY IIS'!K131 -> 15 | Q51: ='Inputs_BY IIS'!L131 -> 15 | ... AK51: ='Inputs_BY IIS'!AF131 -> 15
C52: INDELC | H52: INPUT | I52: PJ / Mt | J52: ='Inputs_BY IIS'!E143 -> 2.1 | K52: ='Inputs_BY IIS'!F143 -> 2.1 | L52: ='Inputs_BY IIS'!G143 -> 2.1 | M52: ='Inputs_BY IIS'!H143 -> 2.1 | N52: ='Inputs_BY IIS'!I143 -> 2.1 | O52: ='Inputs_BY IIS'!J143 -> 2.1 | P52: ='Inputs_BY IIS'!K143 -> 2.1 | Q52: ='Inputs_BY IIS'!L143 -> 2.1 | ... AK52: ='Inputs_BY IIS'!AF143 -> 2.1
C53: IISSCP | H53: INPUT | I53: Mt / Mt | J53: ='Inputs_BY IIS'!E90 -> 0.125 | K53: ='Inputs_BY IIS'!F90 -> 0.125 | L53: ='Inputs_BY IIS'!G90 -> 0.125 | M53: ='Inputs_BY IIS'!H90 -> 0.125 | N53: ='Inputs_BY IIS'!I90 -> 0.125 | O53: ='Inputs_BY IIS'!J90 -> 0.125 | P53: ='Inputs_BY IIS'!K90 -> 0.125 | Q53: ='Inputs_BY IIS'!L90 -> 0.125 | ... AK53: ='Inputs_BY IIS'!AF90 -> 0.125
D54: INDCO2p | H54: OUTPUT | I54: kt/Mt | J54: =$AM54*1000 -> 880 | K54: =$AM54*1000 -> 880 | L54: =$AM54*1000 -> 880 | M54: =$AM54*1000 -> 880 | N54: =$AM54*1000 -> 880 | O54: =$AM54*1000 -> 880 | P54: =$AM54*1000 -> 880 | Q54: =$AM54*1000 -> 880 | ... AK54: =$AM54*1000 -> 880 | AM54: =0.7+0.18 -> 0.88 | AN54: From IPCC, https://www.ipcc-nggip.iges.or.jp/public/2019rf/pdf/3_Volume3/19R_V3_Ch04_Metal_Industry.pdf
D55: IIS | H55: OUTPUT | I55: Mt | J55: 1 | K55: 1 | L55: 1 | M55: 1 | N55: 1 | O55: 1 | P55: 1 | Q55: 1 | R55: 1 | S55: 1 | T55: 1 | U55: 1 | V55: 1 | W55: 1 | X55: 1 | Y55: 1 | Z55: 1 | AA55: 1 | AB55: 1 | AC55: 1 | AD55: 1 | AE55: 1 | AF55: 1 | AG55: 1 | AH55: 1 | AI55: 1 | AJ55: 1 | AK55: 1
A56: =AN12 -> I-IS-SCP_EAF | B56: =AO12 -> IND Iron and Steel technology: EAF using scrap (secondary) | C56: INDELC | H56: INPUT | I56: PJ / Mt | J56: ='Inputs_BY IIS'!E121 -> 2.1 | K56: ='Inputs_BY IIS'!F121 -> 2.1 | L56: ='Inputs_BY IIS'!G121 -> 2.1 | M56: ='Inputs_BY IIS'!H121 -> 2.1 | N56: ='Inputs_BY IIS'!I121 -> 2.1 | O56: ='Inputs_BY IIS'!J121 -> 2.1 | P56: ='Inputs_BY IIS'!K121 -> 2.1 | Q56: ='Inputs_BY IIS'!L121 -> 2.1 | ... AK56: ='Inputs_BY IIS'!AF121 -> 2.1
C57: IISSCP | H57: INPUT | I57: Mt / Mt | J57: ='Inputs_BY IIS'!E91 -> 1.05 | K57: ='Inputs_BY IIS'!F91 -> 1.05 | L57: ='Inputs_BY IIS'!G91 -> 1.05 | M57: ='Inputs_BY IIS'!H91 -> 1.05 | N57: ='Inputs_BY IIS'!I91 -> 1.05 | O57: ='Inputs_BY IIS'!J91 -> 1.05 | P57: ='Inputs_BY IIS'!K91 -> 1.05 | Q57: ='Inputs_BY IIS'!L91 -> 1.05 | ... AK57: ='Inputs_BY IIS'!AF91 -> 1.05
D58: INDCO2p | H58: OUTPUT | I58: kt/Mt | J58: =$AM58*1000 -> 180 | K58: =$AM58*1000 -> 180 | L58: =$AM58*1000 -> 180 | M58: =$AM58*1000 -> 180 | N58: =$AM58*1000 -> 180 | O58: =$AM58*1000 -> 180 | P58: =$AM58*1000 -> 180 | Q58: =$AM58*1000 -> 180 | ... AK58: =$AM58*1000 -> 180 | AM58: =0.18 -> 0.18 | AN58: From IPCC, https://www.ipcc-nggip.iges.or.jp/public/2019rf/pdf/3_Volume3/19R_V3_Ch04_Metal_Industry.pdf
D59: IIS | H59: OUTPUT | I59: Mt | J59: 1 | K59: 1 | L59: 1 | M59: 1 | N59: 1 | O59: 1 | P59: 1 | Q59: 1 | R59: 1 | S59: 1 | T59: 1 | U59: 1 | V59: 1 | W59: 1 | X59: 1 | Y59: 1 | Z59: 1 | AA59: 1 | AB59: 1 | AC59: 1 | AD59: 1 | AE59: 1 | AF59: 1 | AG59: 1 | AH59: 1 | AI59: 1 | AJ59: 1 | AK59: 1
A60: =AN13 -> I-IS-SCP_PRD | B60: =AO13 -> IND Scrap IS Dummy | D60: IISSCP | H60: OUTPUT | I60: Mt | J60: 1 | K60: 1 | L60: 1 | M60: 1 | N60: 1 | O60: 1 | P60: 1 | Q60: 1 | R60: 1 | S60: 1 | T60: 1 | U60: 1 | V60: 1 | W60: 1 | X60: 1 | Y60: 1 | Z60: 1 | AA60: 1 | AB60: 1 | AC60: 1 | AD60: 1 | AE60: 1 | AF60: 1 | AG60: 1 | AH60: 1 | AI60: 1 | AJ60: 1 | AK60: 1
A65: ~FI_T
A66: TechName | B66: *Technology Description | C66: Year | D66: * | E66: * | F66: * | G66: LimType | H66: Attribute | I66: *Unit | J66: AFE | K66: AFN | L66: AFW | M66: AFZ | N66: ANZ | O66: ASC | P66: ASE | Q66: ASO | R66: BRA | S66: CAN | T66: CHL | U66: CHN | V66: ENE | W66: ENW | X66: EUE | Y66: EUM | Z66: EUW | AA66: IDN | AB66: IND | AC66: JPN | AD66: LAM | AE66: MDA | AF66: MEA | AG66: MEX | AH66: NIG | AI66: RUS | AJ66: SKT | AK66: USA | AN66: IEA (2020) I&S roadmap
A67: *Technology Name | B67: Description | C67: Year | G67: Sign of the equation | H67: TIMES attribute for regionalized variables -> | I67: unit | AM67: Range | AN67: 200 | AO67: $/t
A68: =AN13 -> I-IS-SCP_PRD | B68: =AO13 -> IND Scrap IS Dummy | C68: 2019 | H68: COST | I68: M$/Mt | J68: 0 | K68: 0 | L68: 0 | M68: 0 | N68: 0 | O68: 0 | P68: 0 | Q68: 0 | R68: 0 | S68: 0 | T68: 0 | U68: 0 | V68: 0 | W68: 0 | X68: 0 | Y68: 0 | Z68: 0 | AA68: 0 | AB68: 0 | AC68: 0 | AD68: 0 | AE68: 0 | AF68: 0 | AG68: 0 | AH68: 0 | AI68: 0 | AJ68: 0 | AK68: 0 | AN68: 300 | AO68: $/t
C69: 2050 | H69: COST | I69: M$/Mt | J69: 0 | K69: 0 | L69: 0 | M69: 0 | N69: 0 | O69: 0 | P69: 0 | Q69: 0 | R69: 0 | S69: 0 | T69: 0 | U69: 0 | V69: 0 | W69: 0 | X69: 0 | Y69: 0 | Z69: 0 | AA69: 0 | AB69: 0 | AC69: 0 | AD69: 0 | AE69: 0 | AF69: 0 | AG69: 0 | AH69: 0 | AI69: 0 | AJ69: 0 | AK69: 0 | AN69: =AVERAGE(AN67:AN68)*(Legend!B71/Legend!B69) -> 264.97349 | AO69: Assumed to be 2019 basis so inflated to 2021
A72: Demands | AM72: Sector commodity definition
A73: ~FI_T | AM73: ~FI_Comm
A74: CommName | B74: *CommDesc | C74: Year | D74: * | E74: * | F74: * | G74: * | H74: Attribute | I74: *Unit | J74: AFE | K74: AFN | L74: AFW | M74: AFZ | N74: ANZ | O74: ASC | P74: ASE | Q74: ASO | R74: BRA | S74: CAN | T74: CHL | U74: CHN | V74: ENE | W74: ENW | X74: EUE | Y74: EUM | Z74: EUW | AA74: IDN | AB74: IND | AC74: JPN | AD74: LAM | AE74: MDA | AF74: MEA | AG74: MEX | AH74: NIG | AI74: RUS | AJ74: SKT | AK74: USA | AM74: Csets | AN74: CommName | AO74: CommDesc | AP74: Unit | AQ74: LimType | AR74: CTSLvl | AS74: PeakTS | AT74: Ctype
A75: *Commodity | B75: Description | C75: Year | H75: TIMES attribute | I75: Unit | AM75: *Commodity set | AN75: Commodity name | AO75: Description | AP75: Unit of measure
A76: IIS | B76: Demand for industry (IND): Iron and Steel | C76: 2019 | H76: COM_PROJ | I76: Mt | J76: ='Inputs_BY IIS'!E81 -> 0.055066776 | K76: ='Inputs_BY IIS'!F81 -> 4.7763804 | L76: ='Inputs_BY IIS'!G81 -> 0.060573454 | M76: ='Inputs_BY IIS'!H81 -> 7.9477235 | N76: ='Inputs_BY IIS'!I81 -> 5.7290694 | O76: ='Inputs_BY IIS'!J81 -> 3.9504671 | P76: ='Inputs_BY IIS'!K81 -> 5.4087258 | Q76: ='Inputs_BY IIS'!L81 -> 3.4063714 | ... AK76: ='Inputs_BY IIS'!AF81 -> 86.712626 | AM76: DEM | AN76: IIS | AO76: Demand for industry (IND): Iron and Steel | AP76: Mt
AM77: MAT | AN77: IISSCP | AO77: Scrap steel | AP77: Mt

Sheet IIS_New Techs
A1: Characterization of new sectoral technology options
A2: Sector: | B2: Iron and steel
A3: Code: | B3: IS
A7: New Steel Production Processes | AK7: Process definition
A8: ~FI_T | AK8: ~FI_Process
A9: TechName | B9: *Technology Description | C9: *Comm-IN | D9: Comm-OUT | E9: PRC_CAPACT | F9: NCAP_AFA | G9: START | H9: NCAP_TLIFE | AK9: Sets | AL9: TechName | AM9: TechDesc | AN9: Tact | AO9: Tcap | AP9: *Comm-IN | AQ9: Tslvl | AR9: PrimaryCG | AS9: Vintage
A10: *Technology Name | B10: Description | C10: Input Commodity | D10: Output Commodity | E10: Capacity to Activity Factor | F10: Availability factor | G10: Start year | H10: Technical life | AK10: \I: Process Set Membership | AL10: Technology name | AM10: Description | AN10: Activity unit | AO10: Capacity unit | AP10: Input Commodity | AQ10: TimeSlice level of Process Activity | AR10: Primary Commodity Group | AS10: Vintage Tracking
A11: =AL11 -> I-IS-BF_BOF01 | B11: =AM11 -> IND Iron and Steel technology: BF-BOF | D11: IIS | E11: 1 | F11: 0.95 | G11: 2020 | H11: 30 | AK11: DMD | AL11: I-IS-BF_BOF01 | AM11: IND Iron and Steel technology: BF-BOF | AN11: Mt | AO11: Mt_a
A12: =AL12 -> I-IS-BF_BOF02 | B12: =AM12 -> IND Iron and Steel technology: BF-BOF - High bio | D12: IIS | E12: 1 | F12: 0.95 | G12: 2020 | H12: 30 | AK12: DMD | AL12: I-IS-BF_BOF02 | AM12: IND Iron and Steel technology: BF-BOF - High bio | AN12: Mt | AO12: Mt_a
A13: =AL13 -> I-IS-DRI_EAF_COA01 | B13: =AM13 -> IND Iron and Steel technology: DRI using coal plus EAF | D13: IIS | E13: 1 | F13: 0.95 | G13: 2020 | H13: 30 | AK13: DMD | AL13: I-IS-DRI_EAF_COA01 | AM13: IND Iron and Steel technology: DRI using coal plus EAF | AN13: Mt | AO13: Mt_a
A14: =AL14 -> I-IS-DRI_EAF_NGA01 | B14: =AM14 -> IND Iron and Steel technology: DRI using gas plus EAF | D14: IIS | E14: 1 | F14: 0.95 | G14: 2020 | H14: 30 | AK14: DMD | AL14: I-IS-DRI_EAF_NGA01 | AM14: IND Iron and Steel technology: DRI using gas plus EAF | AN14: Mt | AO14: Mt_a
A15: =AL15 -> I-IS-DRI_EAF_H201 | B15: =AM15 -> IND Iron and Steel technology: DRI using H2 plus EAF | D15: IIS | E15: 1 | F15: 0.95 | G15: 2020 | H15: 30 | AK15: DMD | AL15: I-IS-DRI_EAF_H201 | AM15: IND Iron and Steel technology: DRI using H2 plus EAF | AN15: Mt | AO15: Mt_a
A16: =AL16 -> I-IS-SCP_EAF01 | B16: =AM16 -> IND Iron and Steel technology: EAF using scrap (secondary) | D16: IIS | E16: 1 | F16: 0.95 | G16: 2020 | H16: 30 | AK16: DMD | AL16: I-IS-SCP_EAF01 | AM16: IND Iron and Steel technology: EAF using scrap (secondary) | AN16: Mt | AO16: Mt_a
A17: =AL17 -> I-IS-BF_BOF01_CCS | B17: =AM17 -> IND Iron and Steel technology: BF-BOF w/CCS | D17: IIS | E17: 1 | F17: 0.95 | G17: 2035 | H17: 30 | AK17: DMD | AL17: I-IS-BF_BOF01_CCS | AM17: IND Iron and Steel technology: BF-BOF w/CCS | AN17: Mt | AO17: Mt_a
A18: =AL18 -> I-IS-BF_BOF02_CCS | B18: =AM18 -> IND Iron and Steel technology: BF-BOF - High bio w/CCS | D18: IIS | E18: 1 | F18: 0.95 | G18: 2035 | H18: 30 | AK18: DMD | AL18: I-IS-BF_BOF02_CCS | AM18: IND Iron and Steel technology: BF-BOF - High bio w/CCS | AN18: Mt | AO18: Mt_a
A19: =AL19 -> I-IS-DRI_EAF_COA01_CCS | B19: =AM19 -> IND Iron and Steel technology: DRI using coal plus EAF w/CCS | D19: IIS | E19: 1 | F19: 0.95 | G19: 2035 | H19: 30 | AK19: DMD | AL19: I-IS-DRI_EAF_COA01_CCS | AM19: IND Iron and Steel technology: DRI using coal plus EAF w/CCS | AN19: Mt | AO19: Mt_a
A20: =AL20 -> I-IS-DRI_EAF_NGA01_CCS | B20: =AM20 -> IND Iron and Steel technology: DRI using gas plus EAF w/CCS | D20: IIS | E20: 1 | F20: 0.95 | G20: 2035 | H20: 30 | AK20: DMD | AL20: I-IS-DRI_EAF_NGA01_CCS | AM20: IND Iron and Steel technology: DRI using gas plus EAF w/CCS | AN20: Mt | AO20: Mt_a
A21: =AL21 -> I-IS-MOE01 | B21: =AM21 -> IND Iron and Steel technology: Molten Oxide Electrolysis | D21: IIS | E21: 1 | F21: 0.95 | G21: 2035 | H21: 30 | AK21: DMD | AL21: I-IS-MOE01 | AM21: IND Iron and Steel technology: Molten Oxide Electrolysis | AN21: Mt | AO21: Mt_a
A24: ~FI_T
A25: TechName | B25: *Technology Description | C25: Comm-IN | D25: Comm-OUT | E25: LimType | F25: Attribute | G25: *Unit | H25: AFE | I25: AFN | J25: AFW | K25: AFZ | L25: ANZ | M25: ASC | N25: ASE | O25: ASO | P25: BRA | Q25: CAN | R25: CHL | S25: CHN | T25: ENE | U25: ENW | V25: EUE | W25: EUM | X25: EUW | Y25: IDN | Z25: IND | AA25: JPN | AB25: LAM | AC25: MDA | AD25: MEA | AE25: MEX | AF25: NIG | AG25: RUS | AH25: SKT | AI25: USA
A26: *Technology Name | B26: Description | C26: Input Commodity | D26: Output commodity | E26: Sign of the equation | F26: TIMES attribute for regionalized variables -> | G26: unit
A27: =AL11 -> I-IS-BF_BOF01 | B27: =AM11 -> IND Iron and Steel technology: BF-BOF | C27: INDCOA | F27: INPUT | G27: PJ/Mt | H27: =$AK27 -> 1.5 | I27: =$AK27 -> 1.5 | J27: =$AK27 -> 1.5 | K27: =$AK27 -> 1.5 | L27: =$AK27 -> 1.5 | M27: =$AK27 -> 1.5 | N27: =$AK27 -> 1.5 | O27: =$AK27 -> 1.5 | ... AI27: =$AK27 -> 1.5 | AK27: 1.5
C28: INDCOG | F28: INPUT | G28: PJ/Mt | H28: =$AK28 -> 1 | I28: =$AK28 -> 1 | J28: =$AK28 -> 1 | K28: =$AK28 -> 1 | L28: =$AK28 -> 1 | M28: =$AK28 -> 1 | N28: =$AK28 -> 1 | O28: =$AK28 -> 1 | ... AI28: =$AK28 -> 1 | AK28: 1
C29: INDCOK | F29: INPUT | G29: PJ/Mt | H29: =$AK29 -> 1.5 | I29: =$AK29 -> 1.5 | J29: =$AK29 -> 1.5 | K29: =$AK29 -> 1.5 | L29: =$AK29 -> 1.5 | M29: =$AK29 -> 1.5 | N29: =$AK29 -> 1.5 | O29: =$AK29 -> 1.5 | ... AI29: =$AK29 -> 1.5 | AK29: 1.5
C30: INDELC | F30: INPUT | G30: PJ/Mt | H30: =$AK30 -> 1.5 | I30: =$AK30 -> 1.5 | J30: =$AK30 -> 1.5 | K30: =$AK30 -> 1.5 | L30: =$AK30 -> 1.5 | M30: =$AK30 -> 1.5 | N30: =$AK30 -> 1.5 | O30: =$AK30 -> 1.5 | ... AI30: =$AK30 -> 1.5 | AK30: 1.5
C31: INDGAS | F31: INPUT | G31: PJ/Mt | H31: =$AK31 -> 2 | I31: =$AK31 -> 2 | J31: =$AK31 -> 2 | K31: =$AK31 -> 2 | L31: =$AK31 -> 2 | M31: =$AK31 -> 2 | N31: =$AK31 -> 2 | O31: =$AK31 -> 2 | ... AI31: =$AK31 -> 2 | AK31: 2
C32: UPSCOA | F32: INPUT | G32: PJ/Mt | H32: =$AK32 -> 2 | I32: =$AK32 -> 2 | J32: =$AK32 -> 2 | K32: =$AK32 -> 2 | L32: =$AK32 -> 2 | M32: =$AK32 -> 2 | N32: =$AK32 -> 2 | O32: =$AK32 -> 2 | ... AI32: =$AK32 -> 2 | AK32: 2
C33: UPSCOK | F33: INPUT | G33: PJ/Mt | H33: =$AK33 -> 8 | I33: =$AK33 -> 8 | J33: =$AK33 -> 8 | K33: =$AK33 -> 8 | L33: =$AK33 -> 8 | M33: =$AK33 -> 8 | N33: =$AK33 -> 8 | O33: =$AK33 -> 8 | ... AI33: =$AK33 -> 8 | AK33: 8
D34: INDCO2p | F34: OUTPUT | G34: kt/Mt | H34: =$AL34*1000 -> 1580 | I34: =$AL34*1000 -> 1580 | J34: =$AL34*1000 -> 1580 | K34: =$AL34*1000 -> 1580 | L34: =$AL34*1000 -> 1580 | M34: =$AL34*1000 -> 1580 | N34: =$AL34*1000 -> 1580 | O34: =$AL34*1000 -> 1580 | ... AI34: =$AL34*1000 -> 1580 | AL34: =1.58 -> 1.58 | AM34: From IPCC, https://www.ipcc-nggip.iges.or.jp/public/2019rf/pdf/3_Volume3/19R_V3_Ch04_Metal_Industry.pdf
D35: GASBFG | F35: OUTPUT | G35: PJ / Mt | H35: =$AL$35 -> 1.2624923 | I35: =$AL$35 -> 1.2624923 | J35: =$AL$35 -> 1.2624923 | K35: =$AL$35 -> 1.2624923 | L35: =$AL$35 -> 1.2624923 | M35: =$AL$35 -> 1.2624923 | N35: =$AL$35 -> 1.2624923 | O35: =$AL$35 -> 1.2624923 | ... AI35: =$AL$35 -> 1.2624923 | AL35: ='IIS_BY Techs'!U42 -> 1.2624923 | AM35: Uses the value from CHN as the basis for BFG generation (note the wide variation in regional base year values)
C36: IISSCP | F36: INPUT | G36: Mt/Mt | H36: =$AK36 -> 0.125 | I36: =$AK36 -> 0.125 | J36: =$AK36 -> 0.125 | K36: =$AK36 -> 0.125 | L36: =$AK36 -> 0.125 | M36: =$AK36 -> 0.125 | N36: =$AK36 -> 0.125 | O36: =$AK36 -> 0.125 | ... AI36: =$AK36 -> 0.125 | AK36: 0.125
A37: =AL12 -> I-IS-BF_BOF02 | B37: =AM12 -> IND Iron and Steel technology: BF-BOF - High bio | C37: INDCOA | F37: INPUT | G37: PJ/Mt | H37: =$AK37 -> 1.1571429 | I37: =$AK37 -> 1.1571429 | J37: =$AK37 -> 1.1571429 | K37: =$AK37 -> 1.1571429 | L37: =$AK37 -> 1.1571429 | M37: =$AK37 -> 1.1571429 | N37: =$AK37 -> 1.1571429 | O37: =$AK37 -> 1.1571429 | ... AI37: =$AK37 -> 1.1571429 | AK37: =((SUM($AK$27:$AK$33)-$AK$42)/SUM($AK$27:$AK$33))*AK27 -> 1.1571429
C38: INDCOG | F38: INPUT | G38: PJ/Mt | H38: =$AK38 -> 0.77142857 | I38: =$AK38 -> 0.77142857 | J38: =$AK38 -> 0.77142857 | K38: =$AK38 -> 0.77142857 | L38: =$AK38 -> 0.77142857 | M38: =$AK38 -> 0.77142857 | N38: =$AK38 -> 0.77142857 | O38: =$AK38 -> 0.77142857 | ... AI38: =$AK38 -> 0.77142857 | AK38: =((SUM($AK$27:$AK$33)-$AK$42)/SUM($AK$27:$AK$33))*AK28 -> 0.77142857
C39: INDCOK | F39: INPUT | G39: PJ/Mt | H39: =$AK39 -> 1.1571429 | I39: =$AK39 -> 1.1571429 | J39: =$AK39 -> 1.1571429 | K39: =$AK39 -> 1.1571429 | L39: =$AK39 -> 1.1571429 | M39: =$AK39 -> 1.1571429 | N39: =$AK39 -> 1.1571429 | O39: =$AK39 -> 1.1571429 | ... AI39: =$AK39 -> 1.1571429 | AK39: =((SUM($AK$27:$AK$33)-$AK$42)/SUM($AK$27:$AK$33))*AK29 -> 1.1571429
C40: INDELC | F40: INPUT | G40: PJ/Mt | H40: =$AK40 -> 1.1571429 | I40: =$AK40 -> 1.1571429 | J40: =$AK40 -> 1.1571429 | K40: =$AK40 -> 1.1571429 | L40: =$AK40 -> 1.1571429 | M40: =$AK40 -> 1.1571429 | N40: =$AK40 -> 1.1571429 | O40: =$AK40 -> 1.1571429 | ... AI40: =$AK40 -> 1.1571429 | AK40: =((SUM($AK$27:$AK$33)-$AK$42)/SUM($AK$27:$AK$33))*AK30 -> 1.1571429
C41: INDGAS | F41: INPUT | G41: PJ/Mt | H41: =$AK41 -> 1.5428571 | I41: =$AK41 -> 1.5428571 | J41: =$AK41 -> 1.5428571 | K41: =$AK41 -> 1.5428571 | L41: =$AK41 -> 1.5428571 | M41: =$AK41 -> 1.5428571 | N41: =$AK41 -> 1.5428571 | O41: =$AK41 -> 1.5428571 | ... AI41: =$AK41 -> 1.5428571 | AK41: =((SUM($AK$27:$AK$33)-$AK$42)/SUM($AK$27:$AK$33))*AK31 -> 1.5428571
C42: INDBIO | F42: INPUT | G42: PJ/Mt | H42: =$AK42 -> 4 | I42: =$AK42 -> 4 | J42: =$AK42 -> 4 | K42: =$AK42 -> 4 | L42: =$AK42 -> 4 | M42: =$AK42 -> 4 | N42: =$AK42 -> 4 | O42: =$AK42 -> 4 | ... AI42: =$AK42 -> 4 | AK42: 4
C43: UPSCOA | F43: INPUT | G43: PJ/Mt | H43: =$AK43 -> 1.5428571 | I43: =$AK43 -> 1.5428571 | J43: =$AK43 -> 1.5428571 | K43: =$AK43 -> 1.5428571 | L43: =$AK43 -> 1.5428571 | M43: =$AK43 -> 1.5428571 | N43: =$AK43 -> 1.5428571 | O43: =$AK43 -> 1.5428571 | ... AI43: =$AK43 -> 1.5428571 | AK43: =((SUM($AK$27:$AK$33)-$AK$42)/SUM($AK$27:$AK$33))*AK32 -> 1.5428571
C44: UPSCOK | F44: INPUT | G44: PJ/Mt | H44: =$AK44 -> 6.1714286 | I44: =$AK44 -> 6.1714286 | J44: =$AK44 -> 6.1714286 | K44: =$AK44 -> 6.1714286 | L44: =$AK44 -> 6.1714286 | M44: =$AK44 -> 6.1714286 | N44: =$AK44 -> 6.1714286 | O44: =$AK44 -> 6.1714286 | ... AI44: =$AK44 -> 6.1714286 | AK44: =((SUM($AK$27:$AK$33)-$AK$42)/SUM($AK$27:$AK$33))*AK33 -> 6.1714286
D45: INDCO2p | F45: OUTPUT | G45: kt/Mt | H45: =$AL45*1000 -> 1580 | I45: =$AL45*1000 -> 1580 | J45: =$AL45*1000 -> 1580 | K45: =$AL45*1000 -> 1580 | L45: =$AL45*1000 -> 1580 | M45: =$AL45*1000 -> 1580 | N45: =$AL45*1000 -> 1580 | O45: =$AL45*1000 -> 1580 | ... AI45: =$AL45*1000 -> 1580 | AL45: =1.58 -> 1.58 | AM45: From IPCC, https://www.ipcc-nggip.iges.or.jp/public/2019rf/pdf/3_Volume3/19R_V3_Ch04_Metal_Industry.pdf
D46: GASBFG | F46: OUTPUT | G46: PJ / Mt | H46: =$AL$46 -> 1.2624923 | I46: =$AL$46 -> 1.2624923 | J46: =$AL$46 -> 1.2624923 | K46: =$AL$46 -> 1.2624923 | L46: =$AL$46 -> 1.2624923 | M46: =$AL$46 -> 1.2624923 | N46: =$AL$46 -> 1.2624923 | O46: =$AL$46 -> 1.2624923 | ... AI46: =$AL$46 -> 1.2624923 | AL46: =AL35 -> 1.2624923 | AM46: Uses the value from CHN as the basis for BFG generation (note the wide variation in regional base year values)
C47: IISSCP | F47: INPUT | G47: Mt/Mt | H47: =$AK47 -> 0.125 | I47: =$AK47 -> 0.125 | J47: =$AK47 -> 0.125 | K47: =$AK47 -> 0.125 | L47: =$AK47 -> 0.125 | M47: =$AK47 -> 0.125 | N47: =$AK47 -> 0.125 | O47: =$AK47 -> 0.125 | ... AI47: =$AK47 -> 0.125 | AK47: 0.125
A48: =AL13 -> I-IS-DRI_EAF_COA01 | B48: =AM13 -> IND Iron and Steel technology: DRI using coal plus EAF | C48: INDCOA | F48: INPUT | G48: PJ/Mt | H48: =$AK48 -> 15.215 | I48: =$AK48 -> 15.215 | J48: =$AK48 -> 15.215 | K48: =$AK48 -> 15.215 | L48: =$AK48 -> 15.215 | M48: =$AK48 -> 15.215 | N48: =$AK48 -> 15.215 | O48: =$AK48 -> 15.215 | ... AI48: =$AK48 -> 15.215 | AK48: =('Inputs_BY IIS'!AK132-'Inputs_BY IIS'!AI131)*85% -> 15.215
C49: INDELC | F49: INPUT | G49: PJ/Mt | H49: =$AK49 -> 2.1 | I49: =$AK49 -> 2.1 | J49: =$AK49 -> 2.1 | K49: =$AK49 -> 2.1 | L49: =$AK49 -> 2.1 | M49: =$AK49 -> 2.1 | N49: =$AK49 -> 2.1 | O49: =$AK49 -> 2.1 | ... AI49: =$AK49 -> 2.1 | AK49: 2.1
D50: INDCO2p | F50: OUTPUT | G50: kt/Mt | H50: =$AL50*1000 -> 880 | I50: =$AL50*1000 -> 880 | J50: =$AL50*1000 -> 880 | K50: =$AL50*1000 -> 880 | L50: =$AL50*1000 -> 880 | M50: =$AL50*1000 -> 880 | N50: =$AL50*1000 -> 880 | O50: =$AL50*1000 -> 880 | ... AI50: =$AL50*1000 -> 880 | AL50: =0.7+0.18 -> 0.88 | AM50: From IPCC, https://www.ipcc-nggip.iges.or.jp/public/2019rf/pdf/3_Volume3/19R_V3_Ch04_Metal_Industry.pdf
C51: IISSCP | F51: INPUT | G51: Mt/Mt | H51: =$AK51 -> 0.125 | I51: =$AK51 -> 0.125 | J51: =$AK51 -> 0.125 | K51: =$AK51 -> 0.125 | L51: =$AK51 -> 0.125 | M51: =$AK51 -> 0.125 | N51: =$AK51 -> 0.125 | O51: =$AK51 -> 0.125 | ... AI51: =$AK51 -> 0.125 | AK51: 0.125
A52: =AL14 -> I-IS-DRI_EAF_NGA01 | B52: =AM14 -> IND Iron and Steel technology: DRI using gas plus EAF | C52: INDGAS | F52: INPUT | G52: PJ/Mt | H52: =$AK52 -> 12 | I52: =$AK52 -> 12 | J52: =$AK52 -> 12 | K52: =$AK52 -> 12 | L52: =$AK52 -> 12 | M52: =$AK52 -> 12 | N52: =$AK52 -> 12 | O52: =$AK52 -> 12 | ... AI52: =$AK52 -> 12 | AK52: =('Inputs_BY IIS'!AI132-'Inputs_BY IIS'!AI131)*80% -> 12
C53: INDELC | F53: INPUT | G53: PJ/Mt | H53: =$AK53 -> 2.1 | I53: =$AK53 -> 2.1 | J53: =$AK53 -> 2.1 | K53: =$AK53 -> 2.1 | L53: =$AK53 -> 2.1 | M53: =$AK53 -> 2.1 | N53: =$AK53 -> 2.1 | O53: =$AK53 -> 2.1 | ... AI53: =$AK53 -> 2.1 | AK53: 2.1
D54: INDCO2p | F54: OUTPUT | G54: kt/Mt | H54: =$AL54*1000 -> 880 | I54: =$AL54*1000 -> 880 | J54: =$AL54*1000 -> 880 | K54: =$AL54*1000 -> 880 | L54: =$AL54*1000 -> 880 | M54: =$AL54*1000 -> 880 | N54: =$AL54*1000 -> 880 | O54: =$AL54*1000 -> 880 | ... AI54: =$AL54*1000 -> 880 | AL54: =0.7+0.18 -> 0.88 | AM54: From IPCC, https://www.ipcc-nggip.iges.or.jp/public/2019rf/pdf/3_Volume3/19R_V3_Ch04_Metal_Industry.pdf
C55: IISSCP | F55: INPUT | G55: Mt/Mt | H55: =$AK55 -> 0.125 | I55: =$AK55 -> 0.125 | J55: =$AK55 -> 0.125 | K55: =$AK55 -> 0.125 | L55: =$AK55 -> 0.125 | M55: =$AK55 -> 0.125 | N55: =$AK55 -> 0.125 | O55: =$AK55 -> 0.125 | ... AI55: =$AK55 -> 0.125 | AK55: 0.125
A56: =AL15 -> I-IS-DRI_EAF_H201 | B56: =AM15 -> IND Iron and Steel technology: DRI using H2 plus EAF | C56: INDH2G | F56: INPUT | G56: PJ/Mt | H56: =$AK56 -> 7.2 | I56: =$AK56 -> 7.2 | J56: =$AK56 -> 7.2 | K56: =$AK56 -> 7.2 | L56: =$AK56 -> 7.2 | M56: =$AK56 -> 7.2 | N56: =$AK56 -> 7.2 | O56: =$AK56 -> 7.2 | ... AI56: =$AK56 -> 7.2 | AK56: 7.2 | AL56: Check H2 input per tonne of steel
C57: INDELC | F57: INPUT | G57: PJ/Mt | H57: =$AK57 -> 2.1 | I57: =$AK57 -> 2.1 | J57: =$AK57 -> 2.1 | K57: =$AK57 -> 2.1 | L57: =$AK57 -> 2.1 | M57: =$AK57 -> 2.1 | N57: =$AK57 -> 2.1 | O57: =$AK57 -> 2.1 | ... AI57: =$AK57 -> 2.1 | AK57: 2.1
D58: INDCO2p | F58: OUTPUT | G58: kt/Mt | H58: =$AL58*1000 -> 180 | I58: =$AL58*1000 -> 180 | J58: =$AL58*1000 -> 180 | K58: =$AL58*1000 -> 180 | L58: =$AL58*1000 -> 180 | M58: =$AL58*1000 -> 180 | N58: =$AL58*1000 -> 180 | O58: =$AL58*1000 -> 180 | ... AI58: =$AL58*1000 -> 180 | AL58: =0.18 -> 0.18 | AM58: From IPCC, https://www.ipcc-nggip.iges.or.jp/public/2019rf/pdf/3_Volume3/19R_V3_Ch04_Metal_Industry.pdf
C59: IISSCP | F59: INPUT | G59: Mt/Mt | H59: =$AK59 -> 0.15 | I59: =$AK59 -> 0.15 | J59: =$AK59 -> 0.15 | K59: =$AK59 -> 0.15 | L59: =$AK59 -> 0.15 | M59: =$AK59 -> 0.15 | N59: =$AK59 -> 0.15 | O59: =$AK59 -> 0.15 | ... AI59: =$AK59 -> 0.15 | AK59: 0.15
A60: =AL16 -> I-IS-SCP_EAF01 | B60: =AM16 -> IND Iron and Steel technology: EAF using scrap (secondary) | C60: INDELC | F60: INPUT | G60: PJ/Mt | H60: =$AK60 -> 2.1 | I60: =$AK60 -> 2.1 | J60: =$AK60 -> 2.1 | K60: =$AK60 -> 2.1 | L60: =$AK60 -> 2.1 | M60: =$AK60 -> 2.1 | N60: =$AK60 -> 2.1 | O60: =$AK60 -> 2.1 | ... AI60: =$AK60 -> 2.1 | AK60: 2.1
D61: INDCO2p | F61: OUTPUT | G61: kt/Mt | H61: =$AL61*1000 -> 180 | I61: =$AL61*1000 -> 180 | J61: =$AL61*1000 -> 180 | K61: =$AL61*1000 -> 180 | L61: =$AL61*1000 -> 180 | M61: =$AL61*1000 -> 180 | N61: =$AL61*1000 -> 180 | O61: =$AL61*1000 -> 180 | ... AI61: =$AL61*1000 -> 180 | AL61: =0.18 -> 0.18 | AM61: From IPCC, https://www.ipcc-nggip.iges.or.jp/public/2019rf/pdf/3_Volume3/19R_V3_Ch04_Metal_Industry.pdf
C62: IISSCP | F62: INPUT | G62: Mt/Mt | H62: =$AK62 -> 1.05 | I62: =$AK62 -> 1.05 | J62: =$AK62 -> 1.05 | K62: =$AK62 -> 1.05 | L62: =$AK62 -> 1.05 | M62: =$AK62 -> 1.05 | N62: =$AK62 -> 1.05 | O62: =$AK62 -> 1.05 | ... AI62: =$AK62 -> 1.05 | AK62: 1.05
A63: =A17 -> I-IS-BF_BOF01_CCS | B63: =B17 -> IND Iron and Steel technology: BF-BOF w/CCS | C63: =C27 -> INDCOA | F63: INPUT | G63: PJ/Mt | H63: =$AK63 -> 1.65 | I63: =$AK63 -> 1.65 | J63: =$AK63 -> 1.65 | K63: =$AK63 -> 1.65 | L63: =$AK63 -> 1.65 | M63: =$AK63 -> 1.65 | N63: =$AK63 -> 1.65 | O63: =$AK63 -> 1.65 | ... AI63: =$AK63 -> 1.65 | AK63: =AK27*$AL$63 -> 1.65 | AL63: 1.1 | AM63: Efficiency penalty
C64: =C28 -> INDCOG | F64: INPUT | G64: PJ/Mt | H64: =$AK64 -> 1.1 | I64: =$AK64 -> 1.1 | J64: =$AK64 -> 1.1 | K64: =$AK64 -> 1.1 | L64: =$AK64 -> 1.1 | M64: =$AK64 -> 1.1 | N64: =$AK64 -> 1.1 | O64: =$AK64 -> 1.1 | ... AI64: =$AK64 -> 1.1 | AK64: =AK28*$AL$63 -> 1.1
C65: =C29 -> INDCOK | F65: INPUT | G65: PJ/Mt | H65: =$AK65 -> 1.65 | I65: =$AK65 -> 1.65 | J65: =$AK65 -> 1.65 | K65: =$AK65 -> 1.65 | L65: =$AK65 -> 1.65 | M65: =$AK65 -> 1.65 | N65: =$AK65 -> 1.65 | O65: =$AK65 -> 1.65 | ... AI65: =$AK65 -> 1.65 | AK65: =AK29*$AL$63 -> 1.65
C66: =C30 -> INDELC | F66: INPUT | G66: PJ/Mt | H66: =$AK66 -> 1.65 | I66: =$AK66 -> 1.65 | J66: =$AK66 -> 1.65 | K66: =$AK66 -> 1.65 | L66: =$AK66 -> 1.65 | M66: =$AK66 -> 1.65 | N66: =$AK66 -> 1.65 | O66: =$AK66 -> 1.65 | ... AI66: =$AK66 -> 1.65 | AK66: =AK30*$AL$63 -> 1.65
C67: =C31 -> INDGAS | F67: INPUT | G67: PJ/Mt | H67: =$AK67 -> 2.2 | I67: =$AK67 -> 2.2 | J67: =$AK67 -> 2.2 | K67: =$AK67 -> 2.2 | L67: =$AK67 -> 2.2 | M67: =$AK67 -> 2.2 | N67: =$AK67 -> 2.2 | O67: =$AK67 -> 2.2 | ... AI67: =$AK67 -> 2.2 | AK67: =AK31*$AL$63 -> 2.2
C68: =C32 -> UPSCOA | F68: INPUT | G68: PJ/Mt | H68: =$AK68 -> 2.2 | I68: =$AK68 -> 2.2 | J68: =$AK68 -> 2.2 | K68: =$AK68 -> 2.2 | L68: =$AK68 -> 2.2 | M68: =$AK68 -> 2.2 | N68: =$AK68 -> 2.2 | O68: =$AK68 -> 2.2 | ... AI68: =$AK68 -> 2.2 | AK68: =AK32*$AL$63 -> 2.2
C69: =C33 -> UPSCOK | F69: INPUT | G69: PJ/Mt | H69: =$AK69 -> 8.8 | I69: =$AK69 -> 8.8 | J69: =$AK69 -> 8.8 | K69: =$AK69 -> 8.8 | L69: =$AK69 -> 8.8 | M69: =$AK69 -> 8.8 | N69: =$AK69 -> 8.8 | O69: =$AK69 -> 8.8 | ... AI69: =$AK69 -> 8.8 | AK69: =AK33*$AL$63 -> 8.8
D70: INDCO2p | F70: OUTPUT | G70: kt/Mt | H70: =$AL70*(1-$AL72)*1000 -> 79 | I70: =$AL70*(1-$AL72)*1000 -> 79 | J70: =$AL70*(1-$AL72)*1000 -> 79 | K70: =$AL70*(1-$AL72)*1000 -> 79 | L70: =$AL70*(1-$AL72)*1000 -> 79 | M70: =$AL70*(1-$AL72)*1000 -> 79 | N70: =$AL70*(1-$AL72)*1000 -> 79 | O70: =$AL70*(1-$AL72)*1000 -> 79 | ... AI70: =$AL70*(1-$AL72)*1000 -> 79 | AL70: =AL45 -> 1.58 | AM70: Emission factor
D71: GASBFG | F71: OUTPUT | G71: PJ/Mt | H71: =$AL71 -> 1.2624923 | I71: =$AL71 -> 1.2624923 | J71: =$AL71 -> 1.2624923 | K71: =$AL71 -> 1.2624923 | L71: =$AL71 -> 1.2624923 | M71: =$AL71 -> 1.2624923 | N71: =$AL71 -> 1.2624923 | O71: =$AL71 -> 1.2624923 | ... AI71: =$AL71 -> 1.2624923 | AL71: =AL35 -> 1.2624923 | AM71: Uses the value from CHN as the basis for BFG generation (note the wide variation in regional base year values)
D72: CCSCO2 | F72: OUTPUT | G72: kt/Mt | H72: =$AL70*$AL72*1000 -> 1501 | I72: =$AL70*$AL72*1000 -> 1501 | J72: =$AL70*$AL72*1000 -> 1501 | K72: =$AL70*$AL72*1000 -> 1501 | L72: =$AL70*$AL72*1000 -> 1501 | M72: =$AL70*$AL72*1000 -> 1501 | N72: =$AL70*$AL72*1000 -> 1501 | O72: =$AL70*$AL72*1000 -> 1501 | ... AI72: =$AL70*$AL72*1000 -> 1501 | AL72: 0.95 | AM72: Capture rate
C73: =C36 -> IISSCP | F73: INPUT | G73: Mt/Mt | H73: =$AK73 -> 0.125 | I73: =$AK73 -> 0.125 | J73: =$AK73 -> 0.125 | K73: =$AK73 -> 0.125 | L73: =$AK73 -> 0.125 | M73: =$AK73 -> 0.125 | N73: =$AK73 -> 0.125 | O73: =$AK73 -> 0.125 | ... AI73: =$AK73 -> 0.125 | AK73: =AK36 -> 0.125
A74: =A18 -> I-IS-BF_BOF02_CCS | B74: =B18 -> IND Iron and Steel technology: BF-BOF - High bio w/CCS | C74: =C37 -> INDCOA | F74: INPUT | G74: PJ/Mt | H74: =$AK74 -> 1.2728571 | I74: =$AK74 -> 1.2728571 | J74: =$AK74 -> 1.2728571 | K74: =$AK74 -> 1.2728571 | L74: =$AK74 -> 1.2728571 | M74: =$AK74 -> 1.2728571 | N74: =$AK74 -> 1.2728571 | O74: =$AK74 -> 1.2728571 | ... AI74: =$AK74 -> 1.2728571 | AK74: =AK37*$AL$74 -> 1.2728571 | AL74: 1.1 | AM74: Efficiency penalty
C75: =C38 -> INDCOG | F75: INPUT | G75: PJ/Mt | H75: =$AK75 -> 0.84857143 | I75: =$AK75 -> 0.84857143 | J75: =$AK75 -> 0.84857143 | K75: =$AK75 -> 0.84857143 | L75: =$AK75 -> 0.84857143 | M75: =$AK75 -> 0.84857143 | N75: =$AK75 -> 0.84857143 | O75: =$AK75 -> 0.84857143 | ... AI75: =$AK75 -> 0.84857143 | AK75: =AK38*$AL$74 -> 0.84857143
C76: =C39 -> INDCOK | F76: INPUT | G76: PJ/Mt | H76: =$AK76 -> 1.2728571 | I76: =$AK76 -> 1.2728571 | J76: =$AK76 -> 1.2728571 | K76: =$AK76 -> 1.2728571 | L76: =$AK76 -> 1.2728571 | M76: =$AK76 -> 1.2728571 | N76: =$AK76 -> 1.2728571 | O76: =$AK76 -> 1.2728571 | ... AI76: =$AK76 -> 1.2728571 | AK76: =AK39*$AL$74 -> 1.2728571
C77: =C40 -> INDELC | F77: INPUT | G77: PJ/Mt | H77: =$AK77 -> 1.2728571 | I77: =$AK77 -> 1.2728571 | J77: =$AK77 -> 1.2728571 | K77: =$AK77 -> 1.2728571 | L77: =$AK77 -> 1.2728571 | M77: =$AK77 -> 1.2728571 | N77: =$AK77 -> 1.2728571 | O77: =$AK77 -> 1.2728571 | ... AI77: =$AK77 -> 1.2728571 | AK77: =AK40*$AL$74 -> 1.2728571
C78: =C41 -> INDGAS | F78: INPUT | G78: PJ/Mt | H78: =$AK78 -> 1.6971429 | I78: =$AK78 -> 1.6971429 | J78: =$AK78 -> 1.6971429 | K78: =$AK78 -> 1.6971429 | L78: =$AK78 -> 1.6971429 | M78: =$AK78 -> 1.6971429 | N78: =$AK78 -> 1.6971429 | O78: =$AK78 -> 1.6971429 | ... AI78: =$AK78 -> 1.6971429 | AK78: =AK41*$AL$74 -> 1.6971429
C79: =C42 -> INDBIO | F79: INPUT | G79: PJ/Mt | H79: =$AK79 -> 4.4 | I79: =$AK79 -> 4.4 | J79: =$AK79 -> 4.4 | K79: =$AK79 -> 4.4 | L79: =$AK79 -> 4.4 | M79: =$AK79 -> 4.4 | N79: =$AK79 -> 4.4 | O79: =$AK79 -> 4.4 | ... AI79: =$AK79 -> 4.4 | AK79: =AK42*$AL$74 -> 4.4
C80: =C43 -> UPSCOA | F80: INPUT | G80: PJ/Mt | H80: =$AK80 -> 1.6971429 | I80: =$AK80 -> 1.6971429 | J80: =$AK80 -> 1.6971429 | K80: =$AK80 -> 1.6971429 | L80: =$AK80 -> 1.6971429 | M80: =$AK80 -> 1.6971429 | N80: =$AK80 -> 1.6971429 | O80: =$AK80 -> 1.6971429 | ... AI80: =$AK80 -> 1.6971429 | AK80: =AK43*$AL$74 -> 1.6971429
C81: =C44 -> UPSCOK | F81: INPUT | G81: PJ/Mt | H81: =$AK81 -> 6.7885714 | I81: =$AK81 -> 6.7885714 | J81: =$AK81 -> 6.7885714 | K81: =$AK81 -> 6.7885714 | L81: =$AK81 -> 6.7885714 | M81: =$AK81 -> 6.7885714 | N81: =$AK81 -> 6.7885714 | O81: =$AK81 -> 6.7885714 | ... AI81: =$AK81 -> 6.7885714 | AK81: =AK44*$AL$74 -> 6.7885714
D82: INDCO2p | F82: OUTPUT | G82: kt/Mt | H82: =$AL82*(1-$AL84)*1000 -> 79 | I82: =$AL82*(1-$AL84)*1000 -> 79 | J82: =$AL82*(1-$AL84)*1000 -> 79 | K82: =$AL82*(1-$AL84)*1000 -> 79 | L82: =$AL82*(1-$AL84)*1000 -> 79 | M82: =$AL82*(1-$AL84)*1000 -> 79 | N82: =$AL82*(1-$AL84)*1000 -> 79 | O82: =$AL82*(1-$AL84)*1000 -> 79 | ... AI82: =$AL82*(1-$AL84)*1000 -> 79 | AL82: =AL70 -> 1.58 | AM82: Emission factor
D83: GASBFG | F83: OUTPUT | G83: PJ/Mt | H83: =$AL83 -> 1.2624923 | I83: =$AL83 -> 1.2624923 | J83: =$AL83 -> 1.2624923 | K83: =$AL83 -> 1.2624923 | L83: =$AL83 -> 1.2624923 | M83: =$AL83 -> 1.2624923 | N83: =$AL83 -> 1.2624923 | O83: =$AL83 -> 1.2624923 | ... AI83: =$AL83 -> 1.2624923 | AL83: =AL35 -> 1.2624923 | AM83: Uses the value from CHN as the basis for BFG generation (note the wide variation in regional base year values)
D84: CCSCO2 | F84: OUTPUT | G84: kt/Mt | H84: =$AL82*$AL84*1000 -> 1501 | I84: =$AL82*$AL84*1000 -> 1501 | J84: =$AL82*$AL84*1000 -> 1501 | K84: =$AL82*$AL84*1000 -> 1501 | L84: =$AL82*$AL84*1000 -> 1501 | M84: =$AL82*$AL84*1000 -> 1501 | N84: =$AL82*$AL84*1000 -> 1501 | O84: =$AL82*$AL84*1000 -> 1501 | ... AI84: =$AL82*$AL84*1000 -> 1501 | AL84: 0.95 | AM84: Capture rate
C85: =C47 -> IISSCP | F85: INPUT | G85: Mt/Mt | H85: =$AK85 -> 0.125 | I85: =$AK85 -> 0.125 | J85: =$AK85 -> 0.125 | K85: =$AK85 -> 0.125 | L85: =$AK85 -> 0.125 | M85: =$AK85 -> 0.125 | N85: =$AK85 -> 0.125 | O85: =$AK85 -> 0.125 | ... AI85: =$AK85 -> 0.125 | AK85: =AK47 -> 0.125
A86: =A19 -> I-IS-DRI_EAF_COA01_CCS | B86: =B19 -> IND Iron and Steel technology: DRI using coal plus EAF w/CCS | C86: =C48 -> INDCOA | F86: INPUT | G86: PJ/Mt | H86: =$AK86 -> 16.7365 | I86: =$AK86 -> 16.7365 | J86: =$AK86 -> 16.7365 | K86: =$AK86 -> 16.7365 | L86: =$AK86 -> 16.7365 | M86: =$AK86 -> 16.7365 | N86: =$AK86 -> 16.7365 | O86: =$AK86 -> 16.7365 | ... AI86: =$AK86 -> 16.7365 | AK86: =AK48*$AL$86 -> 16.7365 | AL86: 1.1 | AM86: Efficiency penalty
C87: =C49 -> INDELC | F87: INPUT | G87: PJ/Mt | H87: =$AK87 -> 2.31 | I87: =$AK87 -> 2.31 | J87: =$AK87 -> 2.31 | K87: =$AK87 -> 2.31 | L87: =$AK87 -> 2.31 | M87: =$AK87 -> 2.31 | N87: =$AK87 -> 2.31 | O87: =$AK87 -> 2.31 | ... AI87: =$AK87 -> 2.31 | AK87: =AK49*$AL$86 -> 2.31
D88: INDCO2p | F88: OUTPUT | G88: kt/Mt | H88: =$AL88*(1-$AL89)*1000 -> 44 | I88: =$AL88*(1-$AL89)*1000 -> 44 | J88: =$AL88*(1-$AL89)*1000 -> 44 | K88: =$AL88*(1-$AL89)*1000 -> 44 | L88: =$AL88*(1-$AL89)*1000 -> 44 | M88: =$AL88*(1-$AL89)*1000 -> 44 | N88: =$AL88*(1-$AL89)*1000 -> 44 | O88: =$AL88*(1-$AL89)*1000 -> 44 | ... AI88: =$AL88*(1-$AL89)*1000 -> 44 | AL88: ='IIS_BY Techs'!AM49 -> 0.88 | AM88: Emission factor
D89: CCSCO2 | F89: OUTPUT | G89: kt/Mt | H89: =$AL88*$AL89*1000 -> 836 | I89: =$AL88*$AL89*1000 -> 836 | J89: =$AL88*$AL89*1000 -> 836 | K89: =$AL88*$AL89*1000 -> 836 | L89: =$AL88*$AL89*1000 -> 836 | M89: =$AL88*$AL89*1000 -> 836 | N89: =$AL88*$AL89*1000 -> 836 | O89: =$AL88*$AL89*1000 -> 836 | ... AI89: =$AL88*$AL89*1000 -> 836 | AL89: 0.95 | AM89: Capture rate
C90: =C51 -> IISSCP | F90: INPUT | G90: Mt/Mt | H90: =$AK90 -> 0.125 | I90: =$AK90 -> 0.125 | J90: =$AK90 -> 0.125 | K90: =$AK90 -> 0.125 | L90: =$AK90 -> 0.125 | M90: =$AK90 -> 0.125 | N90: =$AK90 -> 0.125 | O90: =$AK90 -> 0.125 | ... AI90: =$AK90 -> 0.125 | AK90: =AK51 -> 0.125
A91: =A20 -> I-IS-DRI_EAF_NGA01_CCS | B91: =B20 -> IND Iron and Steel technology: DRI using gas plus EAF w/CCS | C91: =C52 -> INDGAS | F91: INPUT | G91: PJ/Mt | H91: =$AK91 -> 13.2 | I91: =$AK91 -> 13.2 | J91: =$AK91 -> 13.2 | K91: =$AK91 -> 13.2 | L91: =$AK91 -> 13.2 | M91: =$AK91 -> 13.2 | N91: =$AK91 -> 13.2 | O91: =$AK91 -> 13.2 | ... AI91: =$AK91 -> 13.2 | AK91: =AK52*$AL$86 -> 13.2 | AL91: 1.1 | AM91: Efficiency penalty
C92: =C53 -> INDELC | F92: INPUT | G92: PJ/Mt | H92: =$AK92 -> 2.31 | I92: =$AK92 -> 2.31 | J92: =$AK92 -> 2.31 | K92: =$AK92 -> 2.31 | L92: =$AK92 -> 2.31 | M92: =$AK92 -> 2.31 | N92: =$AK92 -> 2.31 | O92: =$AK92 -> 2.31 | ... AI92: =$AK92 -> 2.31 | AK92: =AK53*$AL$86 -> 2.31
D93: INDCO2p | F93: OUTPUT | G93: kt/Mt | H93: =$AL93*(1-$AL94)*1000 -> 44 | I93: =$AL93*(1-$AL94)*1000 -> 44 | J93: =$AL93*(1-$AL94)*1000 -> 44 | K93: =$AL93*(1-$AL94)*1000 -> 44 | L93: =$AL93*(1-$AL94)*1000 -> 44 | M93: =$AL93*(1-$AL94)*1000 -> 44 | N93: =$AL93*(1-$AL94)*1000 -> 44 | O93: =$AL93*(1-$AL94)*1000 -> 44 | ... AI93: =$AL93*(1-$AL94)*1000 -> 44 | AL93: ='IIS_BY Techs'!AM54 -> 0.88 | AM93: Emission factor
D94: CCSCO2 | F94: OUTPUT | G94: kt/Mt | H94: =$AL93*$AL94 -> 0.836 | I94: =$AL93*$AL94 -> 0.836 | J94: =$AL93*$AL94 -> 0.836 | K94: =$AL93*$AL94 -> 0.836 | L94: =$AL93*$AL94 -> 0.836 | M94: =$AL93*$AL94 -> 0.836 | N94: =$AL93*$AL94 -> 0.836 | O94: =$AL93*$AL94 -> 0.836 | ... AI94: =$AL93*$AL94 -> 0.836 | AL94: 0.95 | AM94: Capture rate
C95: =C55 -> IISSCP | F95: INPUT | G95: Mt/Mt | H95: =$AK95 -> 0.125 | I95: =$AK95 -> 0.125 | J95: =$AK95 -> 0.125 | K95: =$AK95 -> 0.125 | L95: =$AK95 -> 0.125 | M95: =$AK95 -> 0.125 | N95: =$AK95 -> 0.125 | O95: =$AK95 -> 0.125 | ... AI95: =$AK95 -> 0.125 | AK95: =AK55 -> 0.125
A96: =A21 -> I-IS-MOE01 | B96: =B21 -> IND Iron and Steel technology: Molten Oxide Electrolysis | C96: INDELC | F96: INPUT | G96: PJ/Mt | H96: =$AK96 -> 6.93 | I96: =$AK96 -> 6.93 | J96: =$AK96 -> 6.93 | K96: =$AK96 -> 6.93 | L96: =$AK96 -> 6.93 | M96: =$AK96 -> 6.93 | N96: =$AK96 -> 6.93 | O96: =$AK96 -> 6.93 | ... AI96: =$AK96 -> 6.93 | AK96: =AK87*3 -> 6.93 | AL96: Value needs to be sourced
A101: ~FI_T
A102: TechName | B102: *Technology Description | C102: Year | D102: * | E102: LimType | F102: Attribute | G102: *Unit | H102: AFE | I102: AFN | J102: AFW | K102: AFZ | L102: ANZ | M102: ASC | N102: ASE | O102: ASO | P102: BRA | Q102: CAN | R102: CHL | S102: CHN | T102: ENE | U102: ENW | V102: EUE | W102: EUM | X102: EUW | Y102: IDN | Z102: IND | AA102: JPN | AB102: LAM | AC102: MDA | AD102: MEA | AE102: MEX | AF102: NIG | AG102: RUS | AH102: SKT | AI102: USA
A103: *Technology Name | B103: Description | C103: Year | E103: Sign of the equation | F103: TIMES attribute for regionalized variables -> | G103: unit
A104: =AL11 -> I-IS-BF_BOF01 | B104: =AM11 -> IND Iron and Steel technology: BF-BOF | C104: 2020 | F104: INVCOST | G104: $M/Mt | H104: =$AK104 -> 763.65359 | I104: =$AK104 -> 763.65359 | J104: =$AK104 -> 763.65359 | K104: =$AK104 -> 763.65359 | L104: =$AK104 -> 763.65359 | M104: =$AK104 -> 763.65359 | N104: =$AK104 -> 763.65359 | O104: =$AK104 -> 763.65359 | ... AI104: =$AK104 -> 763.65359 | AK104: =IIS_Costs!F9*(Legend!$B$71/Legend!$B$69) -> 763.65359
A105: =AL12 -> I-IS-BF_BOF02 | B105: =AM12 -> IND Iron and Steel technology: BF-BOF - High bio | C105: 2020 | F105: INVCOST | G105: $M/Mt | H105: =$AK105 -> 763.65359 | I105: =$AK105 -> 763.65359 | J105: =$AK105 -> 763.65359 | K105: =$AK105 -> 763.65359 | L105: =$AK105 -> 763.65359 | M105: =$AK105 -> 763.65359 | N105: =$AK105 -> 763.65359 | O105: =$AK105 -> 763.65359 | ... AI105: =$AK105 -> 763.65359 | AK105: =AK104 -> 763.65359
A106: =AL13 -> I-IS-DRI_EAF_COA01 | B106: =AM13 -> IND Iron and Steel technology: DRI using coal plus EAF | C106: 2020 | F106: INVCOST | G106: $M/Mt | H106: =$AK106 -> 645.6344 | I106: =$AK106 -> 645.6344 | J106: =$AK106 -> 645.6344 | K106: =$AK106 -> 645.6344 | L106: =$AK106 -> 645.6344 | M106: =$AK106 -> 645.6344 | N106: =$AK106 -> 645.6344 | O106: =$AK106 -> 645.6344 | ... AI106: =$AK106 -> 645.6344 | AK106: =IIS_Costs!F6*(Legend!$B$71/Legend!$B$69) -> 645.6344
A107: =AL14 -> I-IS-DRI_EAF_NGA01 | B107: =AM14 -> IND Iron and Steel technology: DRI using gas plus EAF | C107: 2020 | F107: INVCOST | G107: $M/Mt | H107: =$AK107 -> 645.6344 | I107: =$AK107 -> 645.6344 | J107: =$AK107 -> 645.6344 | K107: =$AK107 -> 645.6344 | L107: =$AK107 -> 645.6344 | M107: =$AK107 -> 645.6344 | N107: =$AK107 -> 645.6344 | O107: =$AK107 -> 645.6344 | ... AI107: =$AK107 -> 645.6344 | AK107: =AK106 -> 645.6344
A108: =AL15 -> I-IS-DRI_EAF_H201 | B108: =AM15 -> IND Iron and Steel technology: DRI using H2 plus EAF | C108: 2020 | F108: INVCOST | G108: $M/Mt | H108: =$AK108 -> 1034.1093 | I108: =$AK108 -> 1034.1093 | J108: =$AK108 -> 1034.1093 | K108: =$AK108 -> 1034.1093 | L108: =$AK108 -> 1034.1093 | M108: =$AK108 -> 1034.1093 | N108: =$AK108 -> 1034.1093 | O108: =$AK108 -> 1034.1093 | ... AI108: =$AK108 -> 1034.1093 | AK108: =$AK$107*IIS_Costs!J7 -> 1034.1093 | AL108: Review further - as this cost may also include H2 production
C109: 2030 | F109: INVCOST | G109: $M/Mt | H109: =$AK109 -> 935.62273 | I109: =$AK109 -> 935.62273 | J109: =$AK109 -> 935.62273 | K109: =$AK109 -> 935.62273 | L109: =$AK109 -> 935.62273 | M109: =$AK109 -> 935.62273 | N109: =$AK109 -> 935.62273 | O109: =$AK109 -> 935.62273 | ... AI109: =$AK109 -> 935.62273 | AK109: =$AK$107*IIS_Costs!K7 -> 935.62273 | AL109: Review further - as this cost may also include H2 production
...

Sheet IIS_Prod
B2: PIOLab Data pasted in from: | D2: OMNIA_steel_production_2017_and_2019.xlsx
C4: 1 | D4: =C4+1 -> 2 | E4: =D4+1 -> 3 | F4: =E4+1 -> 4 | G4: =F4+1 -> 5 | H4: =G4+1 -> 6 | I4: =H4+1 -> 7 | J4: =I4+1 -> 8 | K4: =J4+1 -> 9 | ... Y4: =X4+1 -> 23
D5: PIOLab data to use | L5: WSA data for reference
D6: Iron_ore_Mt | E6: Pig_iron_Mt | F6: Sponge_iron_Mt | G6: Crude_steel_OBF_Mt | H6: Crude_steel_EAF_Mt | I6: Crude_steel_EAF_form_DRI_Mt | J6: Crude_steel_EAF_form_scrap_Mt | K6: Total_crude_steel_MT | L6: Iron_ore_Mt | M6: Pig_iron_Mt | N6: Sponge_iron_Mt | O6: Crude_steel_OBF_Mt | P6: Crude_steel_EAF_Mt | Q6: Total_crude_steel_MT | S6: Total_crude_steel_MT | W6: % shares by steel pathway
D7: Production of Iron Ore | E7: Production of Pig Iron | F7: Production of DRI | G7: Production of steel in Oxygen-blown converter | H7: Production of Crude Steel in EAF | I7: Production of Crude Steel in EAF | J7: Production of Crude Steel in EAF | L7: Production of Iron Ore | M7: Production of Pig Iron | N7: Production of DRI | O7: Production of steel in Oxygen-blown converter | P7: Production of Crude Steel in EAF | S7: % difference with WSA | T7: Mt difference with WSA | W7: BF-BOF | X7: DRI-EAF | Y7: SCRP-EAF | AA7: Checks
B8: Australia and New Zealand | C8: ANZ | D8: 753.56664 | E8: 3.9611571 | F8: 0 | G8: 4.3225289 | H8: 1.4065405 | I8: 0.13930967 | J8: 1.2672309 | K8: 5.7290694 | L8: 921.9 | M8: 4.336 | N8: 0 | O8: 4.69 | P8: 1.47 | Q8: 6.16 | S8: =(K8/Q8)-1 -> -0.069956258 | T8: =K8-Q8 -> -0.43093055 | W8: =G8/$K8 -> 0.75449058 | X8: =I8/$K8 -> 0.024316282 | Y8: =J8/$K8 -> 0.22119314 | AA8: =SUM(W8:Y8) -> 1
B9: Southeast Asia | C9: ASE | D9: 5.7485503 | E9: 2.3086387 | F9: 5.8270193 | G9: 0 | H9: 5.4087258 | I9: 0.53922147 | J9: 4.8695043 | K9: 5.4087258 | L9: 4.8663616 | M9: 3.872 | N9: 0.595 | O9: 0 | P9: 11.462 | Q9: 11.462 | S9: =(K9/Q9)-1 -> -0.52811675 | T9: =K9-Q9 -> -6.0532742 | W9: =G9/$K9 -> 0 | X9: =I9/$K9 -> 0.099694732 | Y9: =J9/$K9 -> 0.90030527 | AA9: =SUM(W9:Y9) -> 1
B10: China | C10: CHN | D10: 613.3821 | E10: 843.2633 | F10: 0 | G10: 855.34619 | H10: 92.923972 | I10: 9.3828364 | J10: 83.541135 | K10: 948.27016 | L10: 241.3 | M10: 809.365 | N10: 0 | O10: 893.3 | P10: 103.2 | Q10: 996.5 | S10: =(K10/Q10)-1 -> -0.04839924 | T10: =K10-Q10 -> -48.229842 | W10: =G10/$K10 -> 0.90200686 | X10: =I10/$K10 -> 0.009894687 | Y10: =J10/$K10 -> 0.088098454 | AA10: =SUM(W10:Y10) -> 1
B11: Japan | C11: JPN | D11: 0 | E11: 79.242314 | F11: 0 | G11: 78.844141 | H11: 23.604557 | I11: 2.352352 | J11: 21.252205 | K11: 102.4487 | L11: 0 | M11: 74.907 | N11: 0 | O11: 74.983 | P11: 24.301 | Q11: 99.284 | S11: =(K11/Q11)-1 -> 0.03187521 | T11: =K11-Q11 -> 3.1646984 | W11: =G11/$K11 -> 0.76959632 | X11: =I11/$K11 -> 0.022961267 | Y11: =J11/$K11 -> 0.20744241 | AA11: =SUM(W11:Y11) -> 1
B12: South Korea | C12: SKT | D12: 0.17959259 | E12: 46.297002 | F12: 0 | G12: 47.80033 | H12: 21.514178 | I12: 2.1467806 | J12: 19.367397 | K12: 69.314507 | L12: 2.3333028 | M12: 62.281 | N12: 0 | O12: 62.303 | P12: 31.063 | Q12: 93.366 | S12: =(K12/Q12)-1 -> -0.2576044 | T12: =K12-Q12 -> -24.051493 | W12: =G12/$K12 -> 0.68961508 | X12: =I12/$K12 -> 0.030971591 | Y12: =J12/$K12 -> 0.27941333 | AA12: =SUM(W12:Y12) -> 1
B13: Central Asia | C13: ASC | D13: 22.235736 | E13: 2.330698 | F13: 0 | G13: 3.4861665 | H13: 0.46430056 | I13: 0.04628832 | J13: 0.41801224 | K13: 3.9504671 | L13: 18.834079 | M13: 3.167 | N13: 0 | O13: 4.074 | P13: 0.976 | Q13: 5.05 | S13: =(K13/Q13)-1 -> -0.21772929 | T13: =K13-Q13 -> -1.0995329 | W13: =G13/$K13 -> 0.88246945 | X13: =I13/$K13 -> 0.011717176 | Y13: =J13/$K13 -> 0.10581337 | AA13: =SUM(W13:Y13) -> 1
B14: Indonesia, Philippines, Vietnam | C14: IDN | D14: 6.780919 | E14: 6.6827689 | F14: 0.12 | G14: 12.656545 | H14: 6.3404048 | I14: 0.63320346 | J14: 5.7072014 | K14: 18.99695 | L14: 4.1740046 | M14: 9.836 | N14: 0.12 | O14: 15.734 | P14: 11.433 | Q14: 27.167 | S14: =(K14/Q14)-1 -> -0.30073435 | T14: =K14-Q14 -> -8.17005 | W14: =G14/$K14 -> 0.66624091 | X14: =I14/$K14 -> 0.033331849 | Y14: =J14/$K14 -> 0.30042724 | AA14: =SUM(W14:Y14) -> 1
B15: South Asia | C15: ASO | D15: 0 | E15: 0 | F15: 0 | G15: 0 | H15: 3.4063714 | I15: 0.33959729 | J15: 3.0667741 | K15: 3.4063714 | L15: 0 | M15: 0 | N15: 0 | O15: 0 | P15: 8.434 | Q15: 8.434 | S15: =(K15/Q15)-1 -> -0.59611437 | T15: =K15-Q15 -> -5.0276286 | W15: =G15/$K15 -> 0 | X15: =I15/$K15 -> 0.099694732 | Y15: =J15/$K15 -> 0.90030527 | AA15: =SUM(W15:Y15) -> 1
B16: India | C16: IND | D16: 149.56444 | E16: 68.309328 | F16: 38.008513 | G16: 45.276825 | H16: 59.474162 | I16: 29.42185 | J16: 30.052313 | K16: 104.75099 | L16: 232.8 | M16: 74.156 | N16: 36.818 | O16: 48.68 | P16: 62.678 | Q16: 111.358 | S16: =(K16/Q16)-1 -> -0.059331276 | T16: =K16-Q16 -> -6.6070123 | W16: =G16/$K16 -> 0.43223292 | X16: =I16/$K16 -> 0.2808742 | Y16: =J16/$K16 -> 0.28689288 | AA16: =SUM(W16:Y16) -> 1
B17: Canada | C17: CAN | D17: 27.633029 | E17: 6.5642375 | F17: 0.48313471 | G17: 9.6419103 | H17: 4.4693547 | I17: 0.44672632 | J17: 4.0226284 | K17: 14.111265 | L17: 58.5 | M17: 6.42 | N17: 1.44 | O17: 7.82 | P17: 5.08 | Q17: 12.9 | S17: =(K17/Q17)-1 -> 0.09389651 | T17: =K17-Q17 -> 1.211265 | W17: =G17/$K17 -> 0.68327753 | X17: =I17/$K17 -> 0.031657426 | Y17: =J17/$K17 -> 0.28506504 | AA17: =SUM(W17:Y17) -> 1
B18: United States | C18: USA | D18: 27.008599 | E18: 24.108387 | F18: 0.74777109 | G18: 28.60045 | H18: 58.112176 | I18: 5.8077998 | J18: 52.304376 | K18: 86.712626 | L18: 48 | M18: 22.301 | N18: 3.24 | O18: 26.59 | P18: 61.171 | Q18: 87.761 | S18: =(K18/Q18)-1 -> -0.011945788 | T18: =K18-Q18 -> -1.0483743 | W18: =G18/$K18 -> 0.32983029 | X18: =I18/$K18 -> 0.066977557 | Y18: =J18/$K18 -> 0.60319216 | AA18: =SUM(W18:Y18) -> 1
B19: Mexico | C19: MEX | D19: 30.27403 | E19: 4.1720199 | F19: 1.5902945 | G19: 4.6665248 | H19: 13.019956 | I19: 1.2926771 | J19: 11.727279 | K19: 17.686481 | L19: 20.6 | M19: 3.845 | N19: 5.974 | O19: 4.242 | P19: 14.145 | Q19: 18.387 | S19: =(K19/Q19)-1 -> -0.038098615 | T19: =K19-Q19 -> -0.70051924 | W19: =G19/$K19 -> 0.26384699 | X19: =I19/$K19 -> 0.073088432 | Y19: =J19/$K19 -> 0.66306457 | AA19: =SUM(W19:Y19) -> 1
... B35: Eastern Africa | C35: AFE | D35: 0 | E35: 0 | F35: 0 | G35: 0 | H35: 0.055066776 | I35: 0.0055172179 | J35: 0.049549559 | K35: 0.055066776 | L35: 0 | M35: 0 | N35: 0 | O35: 0 | P35: 0.05 | Q35: 0.05 | S35: =(K35/Q35)-1 -> 0.10133553 | T35: =K35-Q35 -> 0.0050667764 | W35: =G35/$K35 -> 0 | X35: =I35/$K35 -> 0.10019141 | Y35: =J35/$K35 -> 0.89980859 | AA35: =SUM(W35:Y35) -> 1
B36: TOTAL | D36: =SUM(D8:D35) -> 2160.15 | E36: 1300.4099 | F36: 43.248213 | G36: =SUM(G8:G35) -> 1332.0853 | H36: =SUM(H8:H35) -> 422.62626 | I36: =SUM(I8:I35) -> 76.503894 | J36: =SUM(J8:J35) -> 346.12237 | K36: =SUM(K8:K35) -> 1754.7116 | L36: =SUM(L8:L35) -> 2332.529 | M36: =SUM(M8:M35) -> 1279.097 | N36: =SUM(N8:N35) -> 109.511 | ... Q36: =SUM(Q8:Q35) -> 1869.079 | S36: =(K36/Q36)-1 -> -0.0611892 | T36: =K36-Q36 -> -114.36745 | W36: =G36/$K36 -> 0.75914773 | X36: =I36/$K36 -> 0.043599128 | Y36: =J36/$K36 -> 0.19725314 | AA36: =SUM(W36:Y36) -> 1
B37: % difference with WSA | D37: =(D36-L36)/L36 -> -0.07390217 | E37: =(E36-O36)/O36 -> -0.036791901 | F37: =(F36-P36)/P36 -> -0.91666963 | G37: =(G36-O36)/O36 -> -0.013330088 | H37: =(H36-P36)/P36 -> -0.1856865 | K37: =(K36-Q36)/Q36 -> -0.0611892
Q42: REMOVE | S42: Total_crude_steel_MT | W42: % shares by steel pathway
Q43: REMOVE | S43: % difference with WSA | T43: Mt difference with WSA | W43: BF-BOF | X43: DRI-EAF | Y43: SCRP-EAF
Q44: REMOVE | S44: 0.66270814 | T44: 4.0822821 | W44: 0.86196356 | X44: 0.0086610639 | Y44: 0.12937537
Q45: REMOVE | S45: 0.03762099 | T45: 0.43121178 | W45: 0 | X45: 0.25433296 | Y45: 0.74566704
Q46: REMOVE | S46: -0.042063888 | T46: -41.916664 | W46: 0.91198201 | X46: 0.0040061413 | Y46: 0.084011844
Q47: REMOVE | S47: 0.030603818 | T47: 3.0384695 | W47: 0.76995773 | X47: 0.013923599 | Y47: 0.21611867
Q48: REMOVE | S48: -0.022607666 | T48: -2.1107873 | W48: 0.67558725 | X48: 0.018232002 | Y48: 0.30618075
Q49: REMOVE | S49: 0.7601427 | T49: 3.8387206 | W49: 0.89627171 | X49: 0 | Y49: 0.10372829
Q50: REMOVE | S50: 0.20828968 | T50: 5.6586057 | W50: 0.65 | X50: 0 | Y50: 0.35
Q51: REMOVE | S51: -0.11189852 | T51: -0.94375211 | W51: 0 | X51: 0 | Y51: 1
Q52: REMOVE | S52: 0.0040195025 | T52: 0.44760376 | W52: 0.43949673 | X52: 0.060142274 | Y52: 0.50036099
Q53: REMOVE | S53: 0.049058909 | T53: 0.63285993 | W53: 0.6251078 | X53: 0.036430449 | Y53: 0.33846175
Q54: REMOVE | S54: -0.021551925 | T54: -1.8914184 | W54: 0.32279682 | X54: 0.069288118 | Y54: 0.60791506
Q55: REMOVE | S55: -0.0058307056 | T55: -0.10720918 | W55: 0.24495892 | X55: 0.095826074 | Y55: 0.65921501
... Q72: REMOVE | S72: -0.036897652 | T72: -68.964626 | W72: 0.76105695 | X72: 0.022221363 | Y72: 0.21672169

Sheet IIS_Capacity
A2: From query qry7_CapacityXTAB, in database GEM_DBASE.accdb
A3: Source: Global Energy Monitor, Global-Steel-Plant-Tracker-April-2024-Standard-Copy-V1.xlsx
A5: Main production process | B5: Cat | C5: AFE | D5: AFN | E5: AFW | F5: AFZ | G5: ANZ | H5: ASC | I5: ASE | J5: ASO | K5: BRA | L5: CAN | M5: CHL | N5: CHN | O5: ENE | P5: ENW | Q5: EUE | R5: EUM | S5: EUW | T5: IDN | U5: IND | V5: JPN | W5: LAM | X5: MDA | Y5: MEA | Z5: MEX | AA5: RUS | AB5: SKT | AC5: USA
A6: electric | B6: BOF | N6: 1726
A7: electric | B7: EAF | C7: 450 | D7: 7420 | E7: 800 | F7: 850 | G7: 1530 | H7: 2800 | I7: 15055 | J7: 3890 | K7: 6956 | L7: 2950 | M7: 520 | N7: 85950 | O7: 8070 | P7: 5060 | Q7: 9501 | R7: 49021 | S7: 19225 | T7: 11600 | U7: 4230 | V7: 28133 | W7: 2400 | X7: 44280 | Y7: 18300 | Z7: 11710 | AA7: 18095 | AB7: 32230 | AC7: 73099
A8: electric | B8: OTH | J8: 170
A9: electric, oxygen | B9: BOF | N9: 2750
A10: electric, oxygen | B10: EAF | N10: 5359
A11: electric, oxygen | B11: OTH | S11: 300
A12: integrated (BF and DRI) | B12: BOF | F12: 4500 | U12: 16700 | Z12: 2400
A13: integrated (BF and DRI) | B13: EAF | T13: 260 | U13: 28697 | W13: 750 | Z13: 4000
A14: integrated (BF and DRI) | B14: OTH | U14: 7341
A15: integrated (BF) | B15: BOF | D15: 350 | G15: 3200 | H15: 6000 | I15: 9500 | K15: 33210 | L15: 2500 | M15: 1450 | N15: 803546 | O15: 15595 | Q15: 10800 | R15: 13800 | S15: 10420 | T15: 27580 | U15: 55326 | V15: 67831 | W15: 3500 | X15: 13100 | Y15: 6280 | AA15: 53799 | AB15: 67400 | AC15: 32021
A16: integrated (BF) | B16: EAF | D16: 1800 | I16: 3150 | K16: 3500 | L16: 1350 | N16: 42717 | O16: 800 | Q16: 200 | T16: 2820 | U16: 2050 | V16: 2070 | X16: 800 | Y16: 1000 | AA16: 13006 | AB16: 4680
A17: integrated (BF) | B17: OHF | I17: 2250
A18: integrated (BF) | B18: OTH | U18: 255
A19: integrated (DRI) | B19: BOF | I19: 1000
A20: integrated (DRI) | B20: EAF | C20: 1000 | D20: 18111 | F20: 600 | I20: 1000 | L20: 2400 | S20: 1113 | T20: 4000 | U20: 1700 | W20: 3790 | Y20: 46475 | Z20: 3730 | AA20: 3500 | AC20: 3000
A21: integrated (DRI) | B21: OTH | U21: 5606 | Y21: 600
A22: integrated (unknown) | B22: EAF | N22: 1350
A23: oxygen | B23: BOF | L23: 600 | N23: 24320 | R23: 4200 | AC23: 1000
A24: steelmaking (other) | B24: OTH | F24: 500 | I24: 1530 | J24: 2962 | Y24: 750
A25: unknown | B25: OTH | J25: 850

Sheet IIS_Costs
B1: Source: Pye et al. 2022
B3: Table A2. Steel production technology costs assumptions. Point estimates for CAPEX used in the model, based on range median. | J3: X-check all of this with https://netzeroindustry.org/wp-content/uploads/pdf/net_zero_steel_report_ii.pdf
B4: Technology name | C4: Technology abbr. | D4: CAPEX1, $2005/t (Range) | E4: CAPEX1, $2005/t (Point estimate) | F4: CAPEX1, $2019/t (Point estimate) | G4: OPEX, % of CAPEX
B5: Electric Arc Furnace | C5: EAF | D5: 187-292 | E5: 240 | F5: =E5*$J$5 -> 314.4 | G5: 0.075 | J5: 1.31 | K5: Factor used in TIAM to convert between 2005 & 2019
B6: Direct Reduction Iron and EAF | C6: DRI-EAF | D6: 459-471 | E6: 465 | F6: =E6*$J$5 -> 609.15 | G6: 0.075 | J6: Today | K6: 2030 | L6: LT
B7: Direct Reduction Iron with hydrogen and EAF | C7: DRI-H2-EAF | D7: 459-471 (excl. H2 production) | E7: 465 | F7: =E7*$J$5 -> 609.15 | G7: 0.075 | J7: =945/590 -> 1.6016949 | K7: =855/590 -> 1.4491525 | L7: =755/590 -> 1.279661 | M7: IEA uplift for H2 DRI compared to NG DRI
B8: Direct Reduction Iron with CCS and EAF | C8: DRI-CCS-EAF | E8: 580 | F8: =E8*$J$5 -> 759.8 | G8: 0.1
B9: Blast furnace and BOF | C9: BF-BOF | D9: 490-597 | E9: 550 | F9: =E9*$J$5 -> 720.5 | G9: 0.075
B10: Blast furnace and BOF with CCS | C10: BF-BOF-CCS | D10: 628-743 | E10: 680 | F10: =E10*$J$5 -> 890.8 | G10: 0.1
B11: 1 Upfront investment, not annualised
B14: Table A3. Steel production technology non-cost assumptions
B15: Technology name | C15: Technology abbr. | D15: Energy input (GJ/t)2 | E15: Capture rate1 | F15: Scrap input (t)3
B16: Electric Arc Furnace | C16: EAF | D16: 2 | F16: 1.1
B17: Direct Reduction Iron and EAF | C17: DRI-EAF | D17: 17 | F17: 0.15
B18: Direct Reduction Iron with hydrogen and EAF | C18: DRI-H2-EAF | D18: 9 | F18: 0.15
B19: Direct Reduction Iron with CCS and EAF | C19: DRI-CCS-EAF | D19: 17 | E19: 0.9 | F19: 0.15
B20: Blast furnace and BOF | C20: BF-BOF | D20: 19 | F20: 0.15
B21: Blast furnace and BOF with CCS | C21: BF-BOF-CCS | D21: 19 | E21: 0.9 | F21: 0.15
B22: 1 90% capture rate assumed (Bataille et al., 2021; IEA, 2020a)
B23: 2 For DRI-H2-EAF, based on (Vogl et al., 2018); 59 kg H2 per tonne steel, based on 15% scrap charge
B24: 3 For primary production, these can vary significantly but are based on typical levels from the World Steel Association
K38: https://iea.blob.core.windows.net/assets/29b027e5-fefc-47df-aed0-456b1bb38844/IEA-The-Future-of-Hydrogen-Assumptions-Annex_CORR.pdf

Sheet Inputs_BY INM
A2: ENERGY BALANCE - Non-metallic minerals
A3: Source: UN energy balances - Omnia_Energy_Balance_NEW_29_4_2024.xlsx
A5: Final Energy Use
A6: Subsector | B6: Primary energy commodity | D6: Unit | E6: AFE | F6: AFN | G6: AFW | H6: AFZ | I6: ANZ | J6: ASC | K6: ASE | L6: ASO | M6: BRA | N6: CAN | O6: CHL | P6: CHN | Q6: ENE | R6: ENW | S6: EUE | T6: EUM | U6: EUW | V6: IDN | W6: IND | X6: JPN | Y6: LAM | Z6: MDA | AA6: MEA | AB6: MEX | AC6: NIG | AD6: RUS | AE6: SKT | AF6: USA
A7: INM | B7: Non metallic minerals | C7: INDBFG | D7: TJ | E7: =EnergyBalance!E54 -> 0 | F7: =EnergyBalance!F54 -> 0 | G7: =EnergyBalance!G54 -> 0 | H7: =EnergyBalance!H54 -> 0 | I7: =EnergyBalance!I54 -> 0 | J7: =EnergyBalance!J54 -> 0 | K7: =EnergyBalance!K54 -> 0 | L7: =EnergyBalance!L54 -> 0 | ... AF7: =EnergyBalance!AF54 -> 0
A8: INM | B8: Non metallic minerals | C8: INDBGS | D8: TJ | E8: =EnergyBalance!E55 -> 0 | F8: =EnergyBalance!F55 -> 0 | G8: =EnergyBalance!G55 -> 0 | H8: =EnergyBalance!H55 -> 0 | I8: =EnergyBalance!I55 -> 83 | J8: =EnergyBalance!J55 -> 0 | K8: =EnergyBalance!K55 -> 0 | L8: =EnergyBalance!L55 -> 0 | ... AF8: =EnergyBalance!AF55 -> 0
A9: INM | B9: Non metallic minerals | C9: INDBIO | D9: TJ | E9: =EnergyBalance!E56 -> 0 | F9: =EnergyBalance!F56 -> 2989 | G9: =EnergyBalance!G56 -> 445 | H9: =EnergyBalance!H56 -> 1284 | I9: =EnergyBalance!I56 -> 3033 | J9: =EnergyBalance!J56 -> 1 | K9: =EnergyBalance!K56 -> 19800 | L9: =EnergyBalance!L56 -> 0 | ... AF9: =EnergyBalance!AF56 -> 21052
A10: INM | B10: Non metallic minerals | C10: INDBLQ | D10: TJ | E10: =EnergyBalance!E57 -> 0 | F10: =EnergyBalance!F57 -> 0 | G10: =EnergyBalance!G57 -> 0 | H10: =EnergyBalance!H57 -> 0 | I10: =EnergyBalance!I57 -> 0 | J10: =EnergyBalance!J57 -> 0 | K10: =EnergyBalance!K57 -> 0 | L10: =EnergyBalance!L57 -> 0 | ... AF10: =EnergyBalance!AF57 -> 273
A11: INM | B11: Non metallic minerals | C11: INDCOA | D11: TJ | E11: =EnergyBalance!E58 -> 27523 | F11: =EnergyBalance!F58 -> 101160 | G11: =EnergyBalance!G58 -> 17390 | H11: =EnergyBalance!H58 -> 41000 | I11: =EnergyBalance!I58 -> 21761 | J11: =EnergyBalance!J58 -> 56808 | K11: =EnergyBalance!K58 -> 365731 | L11: =EnergyBalance!L58 -> 155792 | ... AF11: =EnergyBalance!AF58 -> 193312
A12: INM | B12: Non metallic minerals | C12: INDCOG | D12: TJ | E12: =EnergyBalance!E59 -> 0 | F12: =EnergyBalance!F59 -> 0 | G12: =EnergyBalance!G59 -> 0 | H12: =EnergyBalance!H59 -> 0 | I12: =EnergyBalance!I59 -> 0 | J12: =EnergyBalance!J59 -> 0 | K12: =EnergyBalance!K59 -> 0 | L12: =EnergyBalance!L59 -> 0 | ... AF12: =EnergyBalance!AF59 -> 0
A13: INM | B13: Non metallic minerals | C13: INDCOK | D13: TJ | E13: =EnergyBalance!E60 -> 0 | F13: =EnergyBalance!F60 -> 0 | G13: =EnergyBalance!G60 -> 0 | H13: =EnergyBalance!H60 -> 0 | I13: =EnergyBalance!I60 -> 108 | J13: =EnergyBalance!J60 -> 253 | K13: =EnergyBalance!K60 -> 0 | L13: =EnergyBalance!L60 -> 0 | ... AF13: =EnergyBalance!AF60 -> 0
A14: INM | B14: Non metallic minerals | C14: INDELC | D14: TJ | E14: =EnergyBalance!E61 -> 0 | F14: =EnergyBalance!F61 -> 27048 | G14: =EnergyBalance!G61 -> 5420 | H14: =EnergyBalance!H61 -> 8875 | I14: =EnergyBalance!I61 -> 12579 | J14: =EnergyBalance!J61 -> 14372 | K14: =EnergyBalance!K61 -> 31717 | L14: =EnergyBalance!L61 -> 0 | ... AF14: =EnergyBalance!AF61 -> 119179
A15: INM | B15: Non metallic minerals | C15: INDGAS | D15: TJ | E15: =EnergyBalance!E62 -> 1486 | F15: =EnergyBalance!F62 -> 20264 | G15: =EnergyBalance!G62 -> 0 | H15: =EnergyBalance!H62 -> 15741 | I15: =EnergyBalance!I62 -> 48090 | J15: =EnergyBalance!J62 -> 62807 | K15: =EnergyBalance!K62 -> 36923 | L15: =EnergyBalance!L62 -> 0 | ... AF15: =EnergyBalance!AF62 -> 398884
A16: INM | B16: Non metallic minerals | C16: INDHET | D16: TJ | E16: =EnergyBalance!E63 -> 0 | F16: =EnergyBalance!F63 -> 0 | G16: =EnergyBalance!G63 -> 0 | H16: =EnergyBalance!H63 -> 0 | I16: =EnergyBalance!I63 -> 0 | J16: =EnergyBalance!J63 -> 2193 | K16: =EnergyBalance!K63 -> 0 | L16: =EnergyBalance!L63 -> 0 | ... AF16: =EnergyBalance!AF63 -> 149
A17: INM | B17: Non metallic minerals | C17: INDLPG | D17: TJ | E17: =EnergyBalance!E64 -> 0 | F17: =EnergyBalance!F64 -> 2976 | G17: =EnergyBalance!G64 -> 0 | H17: =EnergyBalance!H64 -> 0 | I17: =EnergyBalance!I64 -> 4180 | J17: =EnergyBalance!J64 -> 586 | K17: =EnergyBalance!K64 -> 3068 | L17: =EnergyBalance!L64 -> 0 | ... AF17: =EnergyBalance!AF64 -> 717
A18: INM | B18: Non metallic minerals | C18: INDOIL | D18: TJ | E18: =EnergyBalance!E65 -> 8943 | F18: =EnergyBalance!F65 -> 70148 | G18: =EnergyBalance!G65 -> 2810 | H18: =EnergyBalance!H65 -> 1902 | I18: =EnergyBalance!I65 -> 2973 | J18: =EnergyBalance!J65 -> 3535 | K18: =EnergyBalance!K65 -> 13500 | L18: =EnergyBalance!L65 -> 21695 | ... AF18: =EnergyBalance!AF65 -> 48551
... A21: INM | B21: Non metallic minerals | C21: INDWAS | D21: TJ | E21: =EnergyBalance!E68 -> 0 | F21: =EnergyBalance!F68 -> 2021 | G21: =EnergyBalance!G68 -> 0 | H21: =EnergyBalance!H68 -> 0 | I21: =EnergyBalance!I68 -> 0 | J21: =EnergyBalance!J68 -> 0 | K21: =EnergyBalance!K68 -> 0 | L21: =EnergyBalance!L68 -> 0 | ... AF21: =EnergyBalance!AF68 -> 7
A24: Production estimates
E25: =INDEX(IIS_Prod!$B$7:$K$35,MATCH('Inputs_BY IIS'!E$78,IIS_Prod!$C$7:$C$35,0),1) -> Eastern Africa | F25: =INDEX(IIS_Prod!$B$7:$K$35,MATCH('Inputs_BY IIS'!F$78,IIS_Prod!$C$7:$C$35,0),1) -> Northern Africa | G25: =INDEX(IIS_Prod!$B$7:$K$35,MATCH('Inputs_BY IIS'!G$78,IIS_Prod!$C$7:$C$35,0),1) -> Western Africa | H25: =INDEX(IIS_Prod!$B$7:$K$35,MATCH('Inputs_BY IIS'!H$78,IIS_Prod!$C$7:$C$35,0),1) -> Southern Africa | I25: =INDEX(IIS_Prod!$B$7:$K$35,MATCH('Inputs_BY IIS'!I$78,IIS_Prod!$C$7:$C$35,0),1) -> Australia and New Zealand | J25: =INDEX(IIS_Prod!$B$7:$K$35,MATCH('Inputs_BY IIS'!J$78,IIS_Prod!$C$7:$C$35,0),1) -> Central Asia | K25: =INDEX(IIS_Prod!$B$7:$K$35,MATCH('Inputs_BY IIS'!K$78,IIS_Prod!$C$7:$C$35,0),1) -> Southeast Asia | L25: =INDEX(IIS_Prod!$B$7:$K$35,MATCH('Inputs_BY IIS'!L$78,IIS_Prod!$C$7:$C$35,0),1) -> South Asia | ... AF25: =INDEX(IIS_Prod!$B$7:$K$35,MATCH('Inputs_BY IIS'!AF$78,IIS_Prod!$C$7:$C$35,0),1) -> United States
A26: GCP production & emission estimates | D26: Unit | E26: AFE | F26: AFN | G26: AFW | H26: AFZ | I26: ANZ | J26: ASC | K26: ASE | L26: ASO | M26: BRA | N26: CAN | O26: CHL | P26: CHN | Q26: ENE | R26: ENW | S26: EUE | T26: EUM | U26: EUW | V26: IDN | W26: IND | X26: JPN | Y26: LAM | Z26: MDA | AA26: MEA | AB26: MEX | AC26: NIG | AD26: RUS | AE26: SKT | AF26: USA | AH26: Global
A27: 21 | B27: Cement production | D27: Kt | E27: =INDEX(Cem_GCP_Prod!$B$10:$Z$37,MATCH(E26,Cem_GCP_Prod!$B$10:$B$37),$A$27) -> 26228.2 | F27: =INDEX(Cem_GCP_Prod!$B$10:$Z$37,MATCH(F26,Cem_GCP_Prod!$B$10:$B$37),$A$27) -> 99456 | G27: =INDEX(Cem_GCP_Prod!$B$10:$Z$37,MATCH(G26,Cem_GCP_Prod!$B$10:$B$37),$A$27) -> 34539 | H27: =INDEX(Cem_GCP_Prod!$B$10:$Z$37,MATCH(H26,Cem_GCP_Prod!$B$10:$B$37),$A$27) -> 22596 | I27: =INDEX(Cem_GCP_Prod!$B$10:$Z$37,MATCH(I26,Cem_GCP_Prod!$B$10:$B$37),$A$27) -> 10900 | J27: =INDEX(Cem_GCP_Prod!$B$10:$Z$37,MATCH(J26,Cem_GCP_Prod!$B$10:$B$37),$A$27) -> 37758.8 | K27: =INDEX(Cem_GCP_Prod!$B$10:$Z$37,MATCH(K26,Cem_GCP_Prod!$B$10:$B$37),$A$27) -> 85081.2 | L27: =INDEX(Cem_GCP_Prod!$B$10:$Z$37,MATCH(L26,Cem_GCP_Prod!$B$10:$B$37),$A$27) -> 88699 | ... AF27: =INDEX(Cem_GCP_Prod!$B$10:$Z$37,MATCH(AF26,Cem_GCP_Prod!$B$10:$B$37),$A$27) -> 88100 | AH27: =SUM(E27:AF27) -> 4201409.3
A28: 21 | B28: Clinker production | D28: Kt | E28: =INDEX(Cem_GCP_Prod!$B$46:$Z$69,MATCH(E26,Cem_GCP_Prod!$B$46:$B$69),$A$28) -> 0 | F28: =INDEX(Cem_GCP_Prod!$B$46:$Z$69,MATCH(F26,Cem_GCP_Prod!$B$46:$B$69),$A$28) -> 7207 | G28: =INDEX(Cem_GCP_Prod!$B$46:$Z$69,MATCH(G26,Cem_GCP_Prod!$B$46:$B$69),$A$28) -> 0 | H28: =INDEX(Cem_GCP_Prod!$B$46:$Z$69,MATCH(H26,Cem_GCP_Prod!$B$46:$B$69),$A$28) -> 0 | I28: =INDEX(Cem_GCP_Prod!$B$46:$Z$69,MATCH(I26,Cem_GCP_Prod!$B$46:$B$69),$A$28) -> 5625.4 | J28: =INDEX(Cem_GCP_Prod!$B$46:$Z$69,MATCH(J26,Cem_GCP_Prod!$B$46:$B$69),$A$28) -> 7221.6 | K28: =INDEX(Cem_GCP_Prod!$B$46:$Z$69,MATCH(K26,Cem_GCP_Prod!$B$46:$B$69),$A$28) -> 42867.8 | L28: =INDEX(Cem_GCP_Prod!$B$46:$Z$69,MATCH(L26,Cem_GCP_Prod!$B$46:$B$69),$A$28) -> 0 | ... AF28: =INDEX(Cem_GCP_Prod!$B$46:$Z$69,MATCH(AF26,Cem_GCP_Prod!$B$46:$B$69),$A$28) -> 78600 | AH28: =SUM(E28:AF28) -> 2322119.7
A29: 21 | B29: Process emissions | D29: MtCO2 | E29: =INDEX(Cem_GCP_Prod!$B$77:$Z$104,MATCH(E26,Cem_GCP_Prod!$B$77:$B$104),$A$29)/1000 -> 11.596 | F29: =INDEX(Cem_GCP_Prod!$B$77:$Z$104,MATCH(F26,Cem_GCP_Prod!$B$77:$B$104),$A$29)/1000 -> 40.338 | G29: =INDEX(Cem_GCP_Prod!$B$77:$Z$104,MATCH(G26,Cem_GCP_Prod!$B$77:$B$104),$A$29)/1000 -> 8.1394 | H29: =INDEX(Cem_GCP_Prod!$B$77:$Z$104,MATCH(H26,Cem_GCP_Prod!$B$77:$B$104),$A$29)/1000 -> 9.4098 | I29: =INDEX(Cem_GCP_Prod!$B$77:$Z$104,MATCH(I26,Cem_GCP_Prod!$B$77:$B$104),$A$29)/1000 -> 3.4509 | J29: =INDEX(Cem_GCP_Prod!$B$77:$Z$104,MATCH(J26,Cem_GCP_Prod!$B$77:$B$104),$A$29)/1000 -> 15.1912 | K29: =INDEX(Cem_GCP_Prod!$B$77:$Z$104,MATCH(K26,Cem_GCP_Prod!$B$77:$B$104),$A$29)/1000 -> 42.5294 | L29: =INDEX(Cem_GCP_Prod!$B$77:$Z$104,MATCH(L26,Cem_GCP_Prod!$B$77:$B$104),$A$29)/1000 -> 22.457 | ... AF29: =INDEX(Cem_GCP_Prod!$B$77:$Z$104,MATCH(AF26,Cem_GCP_Prod!$B$77:$B$104),$A$29)/1000 -> 40.9 | AH29: =SUM(E29:AF29) -> 1617.4484
A31: 520 | B31: Implied clinker production (based on GCP emissions) | D31: Kt | E31: =E29/($A$31/1000000) -> 22300 | F31: =F29/($A$31/1000000) -> 77573.077 | G31: =G29/($A$31/1000000) -> 15652.692 | H31: =H29/($A$31/1000000) -> 18095.769 | I31: =I29/($A$31/1000000) -> 6636.3462 | J31: =J29/($A$31/1000000) -> 29213.846 | K31: =K29/($A$31/1000000) -> 81787.308 | L31: =L29/($A$31/1000000) -> 43186.538 | M31: =M29/($M$32/1000) -> 38623.853 | N31: =N29/($N$32/1000) -> 12622.807 | O31: =O29/(O32/1000) -> 1616.3462 | P31: =P29/(P$32/1000) -> 1528138.9 | Q31: =Q29/($A$31/1000000) -> 17430 | R31: =R29/($A$31/1000000) -> 13234.038 | S31: =S29/($A$31/1000000) -> 38766.731 | T31: =T29/($A$31/1000000) -> 57994.615 | U31: =U29/($A$31/1000000) -> 44699.231 | V31: =V29/(V32/1000) -> 176909.09 | W31: =W29/(W$32/1000) -> 267597.77 | X31: =X29/($A$31/1000000) -> 48711.538 | Y31: =Y29/($A$31/1000000) -> 51123.846 | Z31: =Z29/(Z$32/1000) -> 65334.035 | AA31: =AA29/($A$31/1000000) -> 155216.54 | AB31: =AB29/($A$31/1000000) -> 37326.923 | AC31: =AC29/($A$31/1000000) -> 17138.462 | AD31: =AD29/($A$31/1000000) -> 39057.692 | AE31: =AE29/($A$31/1000000) -> 47569.997 | AF31: =AF29/($A$31/1000000) -> 78653.846 | AH31: =SUM(E31:AF31) -> 3032211.9
B32: Clinker EF | D32: tCO2/t clinker | M32: 0.545 | N32: 0.57 | O32: =A31/1000 -> 0.52 | P32: 0.537 | V32: 0.55 | W32: 0.537 | Z32: 0.57 | AH32: Emission factors based on Andrew
B33: Difference (reported vs estimated) | D33: % | E33: =(E31-E28)/E31 -> 1 | F33: =(F31-F28)/F31 -> 0.90709406 | G33: =(G31-G28)/G31 -> 1 | H33: =(H31-H28)/H31 -> 1 | I33: =(I31-I28)/I31 -> 0.15233475 | J33: =(J31-J28)/J31 -> 0.75280215 | K33: =(K31-K28)/K31 -> 0.47586244 | L33: =(L31-L28)/L31 -> 1 | ... AF33: =(AF31-AF28)/AF31 -> 0.00068459658
B35: Clinker production est. used (prioritising 'reported') | D35: Kt | E35: =_xlfn.IFS(E33>10%,E31,E33<-10%,E31,E33<=10%,E28) -> 22300 | F35: =_xlfn.IFS(F33>10%,F31,F33<-10%,F31,F33<=10%,F28) -> 77573.077 | G35: =_xlfn.IFS(G33>10%,G31,G33<-10%,G31,G33<=10%,G28) -> 15652.692 | H35: =_xlfn.IFS(H33>10%,H31,H33<-10%,H31,H33<=10%,H28) -> 18095.769 | I35: =_xlfn.IFS(I33>10%,I31,I33<-10%,I31,I33<=10%,I28) -> 6636.3462 | J35: =_xlfn.IFS(J33>10%,J31,J33<-10%,J31,J33<=10%,J28) -> 29213.846 | K35: =_xlfn.IFS(K33>10%,K31,K33<-10%,K31,K33<=10%,K28) -> 81787.308 | L35: =_xlfn.IFS(L33>10%,L31,L33<-10%,L31,L33<=10%,L28) -> 43186.538 | ... AF35: =_xlfn.IFS(AF33>10%,AF31,AF33<-10%,AF31,AF33<=10%,AF28) -> 78600 | AH35: =SUM(E35:AF35) -> 3030439.9 | AJ35: Estimate used in base year
B37: Clinker-cement ratio (reported) | E37: =E28/E27 -> 0 | F37: =F28/F27 -> 0.072464205 | G37: =G28/G27 -> 0 | H37: =H28/H27 -> 0 | I37: =I28/I27 -> 0.51609174 | J37: =J28/J27 -> 0.19125608 | K37: =K28/K27 -> 0.50384574 | L37: =L28/L27 -> 0 | ... AF37: =AF28/AF27 -> 0.89216799 | AH37: =AH28/AH27 -> 0.55270019
B38: Clinker-cement ratio (implied by CO2) | D38: Low ration may imply imports e.g. Chile | E38: =IF(E35<>E28,E31/E27,E37) -> 0.85022991 | F38: =IF(F35<>F28,F31/F27,F37) -> 0.77997383 | G38: =IF(G35<>G28,G31/G27,G37) -> 0.45318893 | H38: =IF(H35<>H28,H31/H27,H37) -> 0.8008395 | I38: =IF(I35<>I28,I31/I27,I37) -> 0.6088391 | J38: =IF(J35<>J28,J31/J27,J37) -> 0.77369636 | K38: =IF(K35<>K28,K31/K27,K37) -> 0.96128531 | L38: =IF(L35<>L28,L31/L27,L37) -> 0.48688867 | ... AF38: =IF(AF35<>AF28,AF31/AF27,AF37) -> 0.89216799 | AH38: =AH31/AH27 -> 0.72171303
B41: Process EF (based on reported) | D41: kgCO2/t cement | E41: =E29*1000/E27*1000 -> 442.11955 | F41: =F29*1000/F27*1000 -> 405.58639 | G41: =G29*1000/G27*1000 -> 235.65824 | H41: =H29*1000/H27*1000 -> 416.43654 | I41: =I29*1000/I27*1000 -> 316.59633 | J41: =J29*1000/J27*1000 -> 402.32211 | K41: =K29*1000/K27*1000 -> 499.86836 | L41: =L29*1000/L27*1000 -> 253.18211 | ... AF41: =AF29*1000/AF27*1000 -> 464.24518 | AH41: =AH29*1000/AH27*1000 -> 384.97758
B42: Process EF (based on clinker prod est. used) | D42: kgCO2/t clinker | E42: =E29*1000/E35*1000 -> 520 | F42: =F29*1000/F35*1000 -> 520 | G42: =G29*1000/G35*1000 -> 520 | H42: =H29*1000/H35*1000 -> 520 | I42: =I29*1000/I35*1000 -> 520 | J42: =J29*1000/J35*1000 -> 520 | K42: =K29*1000/K35*1000 -> 520 | L42: =L29*1000/L35*1000 -> 520 | ... AF42: =AF29*1000/AF35*1000 -> 520.35623 | AH42: =AH29*1000/AH35*1000 -> 533.73387
A45: DRYAD capacity estimates [DATA NOT USED] | D45: Unit | E45: AFE | F45: AFN | G45: AFW | H45: AFZ | I45: ANZ | J45: ASC | K45: ASE | L45: ASO | M45: BRA | N45: CAN | O45: CHL | P45: CHN | Q45: ENE | R45: ENW | S45: EUE | T45: EUM | U45: EUW | V45: IDN | W45: IND | X45: JPN | Y45: LAM | Z45: MDA | AA45: MEA | AB45: MEX | AC45: NIG | AD45: RUS | AE45: SKT | AF45: USA
A46: 4 | B46: Integrated | C46: Dry | D46: Mt | E46: =Cem_SFI_Cap!D10 -> 35.291 | F46: =Cem_SFI_Cap!E10 -> 107.087 | G46: =Cem_SFI_Cap!F10 -> 36.01 | H46: =Cem_SFI_Cap!G10 -> 36.35 | I46: =Cem_SFI_Cap!H10 -> 16.8 | J46: =Cem_SFI_Cap!I10 -> 35.87 | K46: =Cem_SFI_Cap!J10 -> 71.755 | L46: =Cem_SFI_Cap!K10 -> 87.3642 | ... AF46: =Cem_SFI_Cap!AE10 -> 58.42 | AH46: =SUM(E46:AF46) -> 4491.2998
A47: 4 | B47: Integrated | C47: Wet | D47: Mt | E47: =Cem_SFI_Cap!D11 -> 4.7 | F47: =Cem_SFI_Cap!E11 -> 16.12 | G47: =Cem_SFI_Cap!F11 -> 4.45 | H47: =Cem_SFI_Cap!G11 -> 10.05 | I47: =Cem_SFI_Cap!H11 -> 0.5 | J47: =Cem_SFI_Cap!I11 -> 8.5 | K47: =Cem_SFI_Cap!J11 -> 31.5 | L47: =Cem_SFI_Cap!K11 -> 26.224 | ... AF47: =Cem_SFI_Cap!AE11 -> 25.26 | AH47: =SUM(E47:AF47) -> 1852.7608
A48: 4 | B48: Grinding | C48: N/A | D48: Mt | E48: =Cem_SFI_Cap!D9 -> 12.39 | F48: =Cem_SFI_Cap!E9 -> 21.255 | G48: =Cem_SFI_Cap!F9 -> 19.79 | H48: =Cem_SFI_Cap!G9 -> 12.5 | I48: =Cem_SFI_Cap!H9 -> 8.3 | J48: =Cem_SFI_Cap!I9 -> 7.837 | K48: =Cem_SFI_Cap!J9 -> 21.3 | L48: =Cem_SFI_Cap!K9 -> 18.916 | ... AF48: =Cem_SFI_Cap!AE9 -> 49.782 | AH48: =SUM(E48:AF48) -> 1130.202
C49: % wet | E49: =E47/SUM(E46:E47) -> 0.11752644 | F49: =F47/SUM(F46:F47) -> 0.13083672 | G49: =G47/SUM(G46:G47) -> 0.10998517 | H49: =H47/SUM(H46:H47) -> 0.21659483 | I49: =I47/SUM(I46:I47) -> 0.028901734 | J49: =J47/SUM(J46:J47) -> 0.19157088 | K49: =K47/SUM(K46:K47) -> 0.30506997 | L49: =L47/SUM(L46:L47) -> 0.23086905 | ... AF49: =AF47/SUM(AF46:AF47) -> 0.30186424 | AH49: =AH47/SUM(AH46:AH47) -> 0.29204652
D50: Capacity above Production | E50: =((SUM(E46:E48))/(E27/1000))-1 -> 0.99712523 | F50: =((SUM(F46:F48))/(F27/1000))-1 -> 0.45252172 | G50: =((SUM(G46:G48))/(G27/1000))-1 -> 0.74440488 | H50: =((SUM(H46:H48))/(H27/1000))-1 -> 1.606656 | I50: =((SUM(I46:I48))/(I27/1000))-1 -> 1.3486239 | J50: =((SUM(J46:J48))/(J27/1000))-1 -> 0.38264458 | K50: =((SUM(K46:K48))/(K27/1000))-1 -> 0.46395443 | L50: =((SUM(L46:L48))/(L27/1000))-1 -> 0.49386352 | ... AF50: =((SUM(AF46:AF48))/(AF27/1000))-1 -> 0.51489217
C52: % wet (assumed) | E52: 0.05 | F52: 0.05 | G52: 0.05 | H52: 0.05 | I52: 0.05 | J52: 0.05 | K52: 0.05 | L52: 0.05 | M52: 0.05 | N52: 0.05 | O52: 0.05 | P52: 0.05 | Q52: 0.05 | R52: 0.05 | S52: 0.05 | T52: 0.05 | U52: 0.05 | V52: 0.05 | W52: 0.05 | X52: 0.05 | Y52: 0.05 | Z52: 0.05 | AA52: 0.05 | AB52: 0.05 | AC52: 0.05 | AD52: 0.05 | AE52: 0.05 | AF52: 0.05 | AH52: Subject to review, not confident to use DRYAD data
A55: Energy consumption (thermal) | AH55: Global
B56: GNR benchmark intensity, dry | C56: Cement | D56: MJ/t clinker | E56: =Cem_GNR_Metrics!$M$35 -> 3406.1724 | F56: =Cem_GNR_Metrics!G35 -> 3455.7702 | G56: =Cem_GNR_Metrics!$M$35 -> 3406.1724 | H56: =Cem_GNR_Metrics!$M$35 -> 3406.1724 | I56: =Cem_GNR_Metrics!$M$35 -> 3406.1724 | J56: =Cem_GNR_Metrics!$M$35 -> 3406.1724 | K56: =Cem_GNR_Metrics!$M$35 -> 3406.1724 | L56: =Cem_GNR_Metrics!$M$35 -> 3406.1724 | M56: =Cem_GNR_Metrics!B35 -> 3549.0064 | N56: =Cem_GNR_Metrics!C35 -> 3421.6003 | O56: =Cem_GNR_Metrics!J35 -> 3530.6445 | P56: =Cem_GNR_Metrics!$M$35 -> 3406.1724 | Q56: =Cem_GNR_Metrics!$E$35 -> 3622.567 | R56: =Cem_GNR_Metrics!$E$35 -> 3622.567 | S56: =Cem_GNR_Metrics!$E$35 -> 3622.567 | T56: =Cem_GNR_Metrics!$E$35 -> 3622.567 | U56: =Cem_GNR_Metrics!$E$35 -> 3622.567 | V56: =Cem_GNR_Metrics!I35 -> 3571.4621 | W56: =Cem_GNR_Metrics!F35 -> 3093.9873 | X56: =Cem_GNR_Metrics!H35 -> 3206.2769 | Y56: =Cem_GNR_Metrics!J35 -> 3530.6445 | Z56: =Cem_GNR_Metrics!$M$35 -> 3406.1724 | AA56: =Cem_GNR_Metrics!$M$35 -> 3406.1724 | AB56: =Cem_GNR_Metrics!$M$35 -> 3406.1724 | AC56: =Cem_GNR_Metrics!$M$35 -> 3406.1724 | AD56: =Cem_GNR_Metrics!$M$35 -> 3406.1724 | AE56: =Cem_GNR_Metrics!H35 -> 3206.2769 | AF56: =Cem_GNR_Metrics!L35 -> 3631.3041 | AH56: =Cem_GNR_Metrics!$M$35 -> 3406.1724
B57: GNR benchmark intensity, wet | C57: Cement | D57: MJ/t clinker | E57: =Cem_GNR_Metrics!$M$36 -> 4660.2657 | F57: =Cem_GNR_Metrics!$M$36 -> 4660.2657 | G57: =Cem_GNR_Metrics!$M$36 -> 4660.2657 | H57: =Cem_GNR_Metrics!$M$36 -> 4660.2657 | I57: =Cem_GNR_Metrics!$M$36 -> 4660.2657 | J57: =Cem_GNR_Metrics!$M$36 -> 4660.2657 | K57: =Cem_GNR_Metrics!$M$36 -> 4660.2657 | L57: =Cem_GNR_Metrics!$M$36 -> 4660.2657 | ... AF57: =Cem_GNR_Metrics!$M$36 -> 4660.2657 | AH57: =Cem_GNR_Metrics!$M$36 -> 4660.2657
B58: Est. thermal consumption (used in model) | C58: Cement, Dry | D58: TJ | E58: =E56*E35/1000*(1-E52) -> 72159.763 | F58: =F56*F35/1000*(1-F52) -> 254670.99 | G58: =G56*G35/1000*(1-G52) -> 50649.98 | H58: =H56*H35/1000*(1-H52) -> 58555.445 | I58: =I56*I35/1000*(1-I52) -> 21474.312 | J58: =J56*J35/1000*(1-J52) -> 94532.027 | K58: =K56*K35/1000*(1-K52) -> 264652.59 | L58: =L56*L35/1000*(1-L52) -> 139745.76 | ... AF58: =AF56*AF35/1000*(1-AF52) -> 271149.48
B59: Est. thermal consumption (used in model) | C59: Cement, Wet | D59: TJ | E59: =E57*E35/1000*(E52) -> 5196.1963 | F59: =F57*F35/1000*(F52) -> 18075.558 | G59: =G57*G35/1000*(G52) -> 3647.2853 | H59: =H57*H35/1000*(H52) -> 4216.5546 | I59: =I57*I35/1000*(I52) -> 1546.3568 | J59: =J57*J35/1000*(J52) -> 6807.2143 | K59: =K57*K35/1000*(K52) -> 19057.529 | L59: =L57*L35/1000*(L52) -> 10063.037 | ... AF59: =AF57*AF35/1000*(AF52) -> 18314.844
B61: Thermal est. in EnBal | C61: NMM | D61: TJ | E61: =SUM(E7:E13,E15:E21) -> 37952 | F61: =SUM(F7:F13,F15:F21) -> 199558 | G61: =SUM(G7:G13,G15:G21) -> 20645 | H61: =SUM(H7:H13,H15:H21) -> 59927 | I61: =SUM(I7:I13,I15:I21) -> 80228 | J61: =SUM(J7:J13,J15:J21) -> 126183 | K61: =SUM(K7:K13,K15:K21) -> 439022 | L61: =SUM(L7:L13,L15:L21) -> 177487 | ... AF61: =SUM(AF7:AF13,AF15:AF21) -> 662945
B64: Thermal energy deficit | C64: NMM | D64: % of what is needed | E64: =E61/(E59+E58) -> 0.49061508 | F64: =F61/(F59+F58) -> 0.73166095 | G64: =G61/(G59+G58) -> 0.38022172 | H64: =H61/(H59+H58) -> 0.95467726 | I64: =I61/(I59+I58) -> 3.4850421 | J64: =J61/(J59+J58) -> 1.2451544 | K64: =K61/(K59+K58) -> 1.5474316 | L64: =L61/(L59+L58) -> 1.1847569 | ... AF64: =AF61/(AF59+AF58) -> 2.2902477
B65: Required final energy | C65: NMM | D65: TJ | E65: =IF(E64<1,E58+E59,E61) -> 77355.959 | F65: =IF(F64<1,F58+F59,F61) -> 272746.55 | G65: =IF(G64<1,G58+G59,G61) -> 54297.266 | H65: =IF(H64<1,H58+H59,H61) -> 62771.999 | I65: =IF(I64<1,I58+I59,I61) -> 80228 | J65: =IF(J64<1,J58+J59,J61) -> 126183 | K65: =IF(K64<1,K58+K59,K61) -> 439022 | L65: =IF(L64<1,L58+L59,L61) -> 177487 | ... AF65: =IF(AF64<1,AF58+AF59,AF61) -> 662945
A67: Energy consumption (electric)
B68: GNR benchmark intensity | C68: Cement | D68: KWh / tCement | E68: =Cem_GNR_Metrics!$M$37 -> 114.30329 | F68: =Cem_GNR_Metrics!G37 -> 106.34943 | G68: =Cem_GNR_Metrics!$M$37 -> 114.30329 | H68: =Cem_GNR_Metrics!$M$37 -> 114.30329 | I68: =Cem_GNR_Metrics!$M$37 -> 114.30329 | J68: =Cem_GNR_Metrics!$M$37 -> 114.30329 | K68: =Cem_GNR_Metrics!$M$37 -> 114.30329 | L68: =Cem_GNR_Metrics!$M$37 -> 114.30329 | M68: =Cem_GNR_Metrics!B37 -> 117.45252 | N68: =Cem_GNR_Metrics!C37 -> 143.41591 | O68: =Cem_GNR_Metrics!J37 -> 113.96786 | P68: =Cem_GNR_Metrics!$M$37 -> 114.30329 | Q68: =Cem_GNR_Metrics!$E$37 -> 125.02727 | R68: =Cem_GNR_Metrics!$E$37 -> 125.02727 | S68: =Cem_GNR_Metrics!$E$37 -> 125.02727 | T68: =Cem_GNR_Metrics!$E$37 -> 125.02727 | U68: =Cem_GNR_Metrics!$E$37 -> 125.02727 | V68: =Cem_GNR_Metrics!I37 -> 98.128485 | W68: =Cem_GNR_Metrics!F37 -> 102.65489 | X68: =Cem_GNR_Metrics!H37 -> 98.763308 | Y68: =Cem_GNR_Metrics!J37 -> 113.96786 | Z68: =Cem_GNR_Metrics!$M$37 -> 114.30329 | AA68: =Cem_GNR_Metrics!$M$37 -> 114.30329 | AB68: =Cem_GNR_Metrics!$M$37 -> 114.30329 | AC68: =Cem_GNR_Metrics!$M$37 -> 114.30329 | AD68: =Cem_GNR_Metrics!$M$37 -> 114.30329 | AE68: =Cem_GNR_Metrics!H37 -> 98.763308 | AF68: =Cem_GNR_Metrics!L37 -> 137.34651 | AJ68: KWh to TJ | AK68: 3.6e-06
B69: Est. electricity consumption (used in model) | C69: Cement | D69: TJ | E69: =E68*$AK$68*E27*1000 -> 10792.69 | F69: =F68*$AK$68*F27*1000 -> 38077.519 | G69: =G68*$AK$68*G27*1000 -> 14212.516 | H69: =H68*$AK$68*H27*1000 -> 9298.0693 | I69: =I68*$AK$68*I27*1000 -> 4485.2609 | J69: =J68*$AK$68*J27*1000 -> 15537.438 | K69: =K68*$AK$68*K27*1000 -> 35010.218 | L69: =L68*$AK$68*L27*1000 -> 36498.914 | ... AF69: =AF68*$AK$68*AF27*1000 -> 43560.82
B71: Electricity est. in EnBal | C71: INM | D71: TJ | E71: =E14 -> 0 | F71: =F14 -> 27048 | G71: =G14 -> 5420 | H71: =H14 -> 8875 | I71: =I14 -> 12579 | J71: =J14 -> 14372 | K71: =K14 -> 31717 | L71: =L14 -> 0 | ... AF71: =AF14 -> 119179
B74: Electrical energy deficit | C74: INM | D74: % of what is needed | E74: =E71/E69 -> 0 | F74: =F71/F69 -> 0.71034039 | G74: =G71/G69 -> 0.38135401 | H74: =H71/H69 -> 0.95449923 | I74: =I71/I69 -> 2.8045191 | J74: =J71/J69 -> 0.92499165 | K74: =K71/K69 -> 0.90593551 | L74: =L71/L69 -> 0 | ... AF74: =AF71/AF69 -> 2.7359218
B75: Required final energy | C75: INM | D75: TJ | E75: =IF(E74<1,E69,E71) -> 10792.69 | F75: =IF(F74<1,F69,F71) -> 38077.519 | G75: =IF(G74<1,G69,G71) -> 14212.516 | H75: =IF(H74<1,H69,H71) -> 9298.0693 | I75: =IF(I74<1,I69,I71) -> 12579 | J75: =IF(J74<1,J69,J71) -> 15537.438 | K75: =IF(K74<1,K69,K71) -> 35010.218 | L75: =IF(L74<1,L69,L71) -> 36498.914 | ... AF75: =IF(AF74<1,AF69,AF71) -> 119179
P77: 0.975
A79: Final energy use for INM - adjusted to make up for deficit in cement sector estimates | E79: Values in dark yellow shade manually adjusted to resolve energy balance issues
A80: Subsector | B80: Primary energy commodity | D80: Unit | E80: AFE | F80: AFN | G80: AFW | H80: AFZ | I80: ANZ | J80: ASC | K80: ASE | L80: ASO | M80: BRA | N80: CAN | O80: CHL | P80: CHN | Q80: ENE | R80: ENW | S80: EUE | T80: EUM | U80: EUW | V80: IDN | W80: IND | X80: JPN | Y80: LAM | Z80: MDA | AA80: MEA | AB80: MEX | AC80: NIG | AD80: RUS | AE80: SKT | AF80: USA | AH80: IND % shares (as absent from EnBal)
A81: INM | B81: Non metallic minerals | C81: INDBFG | D81: TJ | E81: =IF(E$64<1,E7/E$64,E7) -> 0 | F81: =IF(F$64<1,F7/F$64,F7) -> 0 | G81: =IF(G$64<1,G7/G$64,G7) -> 0 | H81: =IF(H$64<1,H7/H$64,H7) -> 0 | I81: =IF(I$64<1,I7/I$64,I7) -> 0 | J81: =IF(J$64<1,J7/J$64,J7) -> 0 | K81: =IF(K$64<1,K7/K$64,K7) -> 0 | L81: =IF(L$64<1,L7/L$64,L7) -> 0 | ... O81: =IF(O$64<1,O7/O$64,O7) -> 0 | P81: =P7 -> 0 | Q81: =IF(Q$64<1,Q7/Q$64,Q7) -> 0 | R81: =IF(R$64<1,R7/R$64,R7) -> 165 | S81: =IF(S$64<1,S7/S$64,S7) -> 0 | T81: =IF(T$64<1,T7/T$64,T7) -> 0 | U81: =IF(U$64<1,U7/U$64,U7) -> 0 | V81: =IF(V$64<1,V7/V$64,V7) -> 0 | W81: =$W$65*AH81 -> 0 | X81: =IF(X$64<1,X7/X$64,X7) -> 235 | Y81: =IF(Y$64<1,Y7/Y$64,Y7) -> 0 | Z81: =IF(Z$64<1,Z7/Z$64,Z7) -> 0 | AA81: =IF(AA$64<1,AA7/AA$64,AA7) -> 0 | AB81: =IF(AB$64<1,AB7/AB$64,AB7) -> 0 | AC81: =IF(AC$64<1,AC7/AC$64,AC7) -> 0 | AD81: =IF(AD$64<1,AD7/AD$64,AD7) -> 0 | AE81: =IF(AE$64<1,AE7/AE$64,AE7) -> 0 | AF81: =IF(AF$64<1,AF7/AF$64,AF7) -> 0 | AH81: 0 | AI81: =SUM(E81:O81,Q81:V81,X81:AF81)/SUM($E$81:$O$87,$Q$81:$V$87,$X$81:$AF$87,$Q$89:$V$95,$X$89:$AF$95,$E$89:$O$95) -> 6.1991208e-05
A82: INM | B82: Non metallic minerals | C82: INDBGS | D82: TJ | E82: =IF(E$64<1,E8/E$64,E8) -> 0 | F82: =IF(F$64<1,F8/F$64,F8) -> 0 | G82: =IF(G$64<1,G8/G$64,G8) -> 0 | H82: =IF(H$64<1,H8/H$64,H8) -> 0 | I82: =IF(I$64<1,I8/I$64,I8) -> 83 | J82: =IF(J$64<1,J8/J$64,J8) -> 0 | K82: =IF(K$64<1,K8/K$64,K8) -> 0 | L82: =IF(L$64<1,L8/L$64,L8) -> 0 | ... O82: =IF(O$64<1,O8/O$64,O8) -> 0 | P82: =P8 -> 0 | Q82: =IF(Q$64<1,Q8/Q$64,Q8) -> 0 | R82: =IF(R$64<1,R8/R$64,R8) -> 13 | S82: =IF(S$64<1,S8/S$64,S8) -> 25 | T82: =IF(T$64<1,T8/T$64,T8) -> 275 | U82: =IF(U$64<1,U8/U$64,U8) -> 108 | V82: =IF(V$64<1,V8/V$64,V8) -> 0 | W82: =$W$65*AH82 -> 0 | X82: =IF(X$64<1,X8/X$64,X8) -> 0 | Y82: =IF(Y$64<1,Y8/Y$64,Y8) -> 0 | Z82: =IF(Z$64<1,Z8/Z$64,Z8) -> 0 | AA82: =IF(AA$64<1,AA8/AA$64,AA8) -> 0 | AB82: =IF(AB$64<1,AB8/AB$64,AB8) -> 0 | AC82: =IF(AC$64<1,AC8/AC$64,AC8) -> 0 | AD82: =IF(AD$64<1,AD8/AD$64,AD8) -> 0 | AE82: =IF(AE$64<1,AE8/AE$64,AE8) -> 0 | AF82: =IF(AF$64<1,AF8/AF$64,AF8) -> 0 | AH82: 0 | AI82: =SUM(E82:O82,Q82:V82,X82:AF82)/SUM($E$81:$O$87,$Q$81:$V$87,$X$81:$AF$87,$Q$89:$V$95,$X$89:$AF$95,$E$89:$O$95) -> 7.8108922e-05
A83: INM | B83: Non metallic minerals | C83: INDBIO | D83: TJ | E83: =IF(E$64<1,E9/E$64,E9) -> 0 | F83: =IF(F$64<1,F9/F$64,F9) -> 4085.2255 | G83: =IF(G$64<1,G9/G$64,G9) -> 1170.3697 | H83: =IF(H$64<1,H9/H$64,H9) -> 1344.9571 | I83: =IF(I$64<1,I9/I$64,I9) -> 3033 | J83: =IF(J$64<1,J9/J$64,J9) -> 1 | K83: =IF(K$64<1,K9/K$64,K9) -> 19800 | L83: =IF(L$64<1,L9/L$64,L9) -> 0 | ... O83: =IF(O$64<1,O9/O$64,O9) -> 0 | P83: =P9 -> 11296 | Q83: =IF(Q$64<1,Q9/Q$64,Q9) -> 324 | R83: =IF(R$64<1,R9/R$64,R9) -> 11924 | S83: =IF(S$64<1,S9/S$64,S9) -> 4261 | T83: =IF(T$64<1,T9/T$64,T9) -> 32992 | U83: =IF(U$64<1,U9/U$64,U9) -> 8514 | V83: =IF(V$64<1,V9/V$64,V9) -> 0 | W83: =$W$65*AH83 -> 42445.036 | X83: =IF(X$64<1,X9/X$64,X9) -> 6059 | Y83: =IF(Y$64<1,Y9/Y$64,Y9) -> 1613.8418 | Z83: =IF(Z$64<1,Z9/Z$64,Z9) -> 0 | AA83: =IF(AA$64<1,AA9/AA$64,AA9) -> 0 | AB83: =IF(AB$64<1,AB9/AB$64,AB9) -> 0 | AC83: =IF(AC$64<1,AC9/AC$64,AC9) -> 0 | AD83: =IF(AD$64<1,AD9/AD$64,AD9) -> 54 | AE83: =IF(AE$64<1,AE9/AE$64,AE9) -> 68 | AF83: =IF(AF$64<1,AF9/AF$64,AF9) -> 21052 | AH83: 0.05 | AI83: =SUM(E83:O83,Q83:V83,X83:AF83)/SUM($E$81:$O$87,$Q$81:$V$87,$X$81:$AF$87,$Q$89:$V$95,$X$89:$AF$95,$E$89:$O$95) -> 0.019227099
A84: INM | B84: Non metallic minerals | C84: INDBLQ | D84: TJ | E84: =IF(E$64<1,E10/E$64,E10) -> 0 | F84: =IF(F$64<1,F10/F$64,F10) -> 0 | G84: =IF(G$64<1,G10/G$64,G10) -> 0 | H84: =IF(H$64<1,H10/H$64,H10) -> 0 | I84: =IF(I$64<1,I10/I$64,I10) -> 0 | J84: =IF(J$64<1,J10/J$64,J10) -> 0 | K84: =IF(K$64<1,K10/K$64,K10) -> 0 | L84: =IF(L$64<1,L10/L$64,L10) -> 0 | ... O84: =IF(O$64<1,O10/O$64,O10) -> 0 | P84: =P10 -> 0 | Q84: =IF(Q$64<1,Q10/Q$64,Q10) -> 0 | R84: =IF(R$64<1,R10/R$64,R10) -> 0 | S84: =IF(S$64<1,S10/S$64,S10) -> 2 | T84: =IF(T$64<1,T10/T$64,T10) -> 80 | U84: =IF(U$64<1,U10/U$64,U10) -> 440 | V84: =IF(V$64<1,V10/V$64,V10) -> 348.04942 | W84: =$W$65*AH84 -> 0 | X84: =IF(X$64<1,X10/X$64,X10) -> 0 | Y84: =IF(Y$64<1,Y10/Y$64,Y10) -> 0 | Z84: =IF(Z$64<1,Z10/Z$64,Z10) -> 0 | AA84: =IF(AA$64<1,AA10/AA$64,AA10) -> 0 | AB84: =IF(AB$64<1,AB10/AB$64,AB10) -> 0 | AC84: =IF(AC$64<1,AC10/AC$64,AC10) -> 0 | AD84: =IF(AD$64<1,AD10/AD$64,AD10) -> 0 | AE84: =IF(AE$64<1,AE10/AE$64,AE10) -> 0 | AF84: =IF(AF$64<1,AF10/AF$64,AF10) -> 273 | AH84: 0 | AI84: =SUM(E84:O84,Q84:V84,X84:AF84)/SUM($E$81:$O$87,$Q$81:$V$87,$X$81:$AF$87,$Q$89:$V$95,$X$89:$AF$95,$E$89:$O$95) -> 0.00021248252
A85: INM | B85: Non metallic minerals | C85: INDCOA | D85: TJ | E85: =IF(E$64<1,E11/E$64,E11)+EnergyBalance!E434 -> 46937 | F85: =IF(F$64<1,F11/F$64,F11)+EnergyBalance!F434 -> 101160 | G85: =IF(G$64<1,G11/G$64,G11)+EnergyBalance!G434 -> 17559.339 | H85: =IF(H$64<1,H11/H$64,H11) -> 42946.451 | I85: =IF(I$64<1,I11/I$64,I11) -> 21761 | J85: =IF(J$64<1,J11/J$64,J11) -> 56808 | K85: =IF(K$64<1,K11/K$64,K11) -> 365731 | L85: =IF(L$64<1,L11/L$64,L11) -> 155792 | M85: =IF(M$64<1,M11/M$64,M11) -> 3098 | N85: =IF(N$64<1,N11/N$64,N11) -> 9657 | O85: =IF(O$64<1,O11/O$64,O11) -> 99 | P85: =P65-(SUM(P7:P21)) -> 4942826 | Q85: =IF(Q$64<1,Q11/Q$64,Q11) -> 59635 | R85: =IF(R$64<1,R11/R$64,R11) -> 21555 | S85: =IF(S$64<1,S11/S$64,S11) -> 39909 | T85: =IF(T$64<1,T11/T$64,T11) -> 20254 | U85: =IF(U$64<1,U11/U$64,U11) -> 55015 | V85: =IF(V$64<1,V11/V$64,V11) -> 505144.01 | W85: =$W$65*AH85 -> 721565.61 | X85: =IF(X$64<1,X11/X$64,X11) -> 126700 | Y85: =IF(Y$64<1,Y11/Y$64,Y11)+EnergyBalance!Y434 -> 63880.224 | Z85: =IF(Z$64<1,Z11/Z$64,Z11) -> 71791 | AA85: =IF(AA$64<1,AA11/AA$64,AA11)+EnergyBalance!AA434 -> 77318 | AB85: =IF(AB$64<1,AB11/AB$64,AB11) -> 4267 | AC85: =IF(AC$64<1,AC11/AC$64,AC11)+EnergyBalance!AC434 -> 1409 | AD85: =IF(AD$64<1,AD11/AD$64,AD11) -> 29891 | AE85: =IF(AE$64<1,AE11/AE$64,AE11) -> 94013 | AF85: =IF(AF$64<1,AF11/AF$64,AF11) -> 193312 | AH85: 0.85 | AI85: =SUM(E85:O85,Q85:V85,X85:AF85)/SUM($E$81:$O$87,$Q$81:$V$87,$X$81:$AF$87,$Q$89:$V$95,$X$89:$AF$95,$E$89:$O$95) -> 0.33872647
A86: INM | B86: Non metallic minerals | C86: INDCOG | D86: TJ | E86: =IF(E$64<1,E12/E$64,E12) -> 0 | F86: =IF(F$64<1,F12/F$64,F12) -> 0 | G86: =IF(G$64<1,G12/G$64,G12) -> 0 | H86: =IF(H$64<1,H12/H$64,H12) -> 0 | I86: =IF(I$64<1,I12/I$64,I12) -> 0 | J86: =IF(J$64<1,J12/J$64,J12) -> 0 | K86: =IF(K$64<1,K12/K$64,K12) -> 0 | L86: =IF(L$64<1,L12/L$64,L12) -> 0 | ... O86: =IF(O$64<1,O12/O$64,O12) -> 0 | P86: =P12 -> 0 | Q86: =IF(Q$64<1,Q12/Q$64,Q12) -> 0 | R86: =IF(R$64<1,R12/R$64,R12) -> 0 | S86: =IF(S$64<1,S12/S$64,S12) -> 2630 | T86: =IF(T$64<1,T12/T$64,T12) -> 0 | U86: =IF(U$64<1,U12/U$64,U12) -> 3595 | V86: =IF(V$64<1,V12/V$64,V12) -> 0 | W86: =$W$65*AH86 -> 0 | X86: =IF(X$64<1,X12/X$64,X12) -> 6389 | Y86: =IF(Y$64<1,Y12/Y$64,Y12) -> 0 | Z86: =IF(Z$64<1,Z12/Z$64,Z12) -> 0 | AA86: =IF(AA$64<1,AA12/AA$64,AA12) -> 0 | AB86: =IF(AB$64<1,AB12/AB$64,AB12) -> 0 | AC86: =IF(AC$64<1,AC12/AC$64,AC12) -> 0 | AD86: =IF(AD$64<1,AD12/AD$64,AD12) -> 961 | AE86: =IF(AE$64<1,AE12/AE$64,AE12) -> 0 | AF86: =IF(AF$64<1,AF12/AF$64,AF12) -> 0 | AH86: 0 | AI86: =SUM(E86:O86,Q86:V86,X86:AF86)/SUM($E$81:$O$87,$Q$81:$V$87,$X$81:$AF$87,$Q$89:$V$95,$X$89:$AF$95,$E$89:$O$95) -> 0.0021038266
A87: INM | B87: Non metallic minerals | C87: INDCOK | D87: TJ | E87: =IF(E$64<1,E13/E$64,E13) -> 0 | F87: =IF(F$64<1,F13/F$64,F13) -> 0 | G87: =IF(G$64<1,G13/G$64,G13) -> 0 | H87: =IF(H$64<1,H13/H$64,H13) -> 0 | I87: =IF(I$64<1,I13/I$64,I13) -> 108 | J87: =IF(J$64<1,J13/J$64,J13) -> 253 | K87: =IF(K$64<1,K13/K$64,K13) -> 0 | L87: =IF(L$64<1,L13/L$64,L13) -> 0 | ... O87: =IF(O$64<1,O13/O$64,O13) -> 0 | P87: =P13 -> 0 | Q87: =IF(Q$64<1,Q13/Q$64,Q13) -> 649 | R87: =IF(R$64<1,R13/R$64,R13) -> 674 | S87: =IF(S$64<1,S13/S$64,S13) -> 7412 | T87: =IF(T$64<1,T13/T$64,T13) -> 1844 | U87: =IF(U$64<1,U13/U$64,U13) -> 30143 | V87: =IF(V$64<1,V13/V$64,V13) -> 0 | W87: =$W$65*AH87 -> 0 | X87: =IF(X$64<1,X13/X$64,X13) -> 5513 | Y87: =IF(Y$64<1,Y13/Y$64,Y13)+EnergyBalance!Y436 -> 181 | Z87: =IF(Z$64<1,Z13/Z$64,Z13) -> 2259 | AA87: =IF(AA$64<1,AA13/AA$64,AA13) -> 0 | AB87: =IF(AB$64<1,AB13/AB$64,AB13) -> 0 | AC87: =IF(AC$64<1,AC13/AC$64,AC13) -> 0 | AD87: =IF(AD$64<1,AD13/AD$64,AD13) -> 2422 | AE87: =IF(AE$64<1,AE13/AE$64,AE13) -> 0 | AF87: =IF(AF$64<1,AF13/AF$64,AF13) -> 0 | AH87: 0 | AI87: =SUM(E87:O87,Q87:V87,X87:AF87)/SUM($E$81:$O$87,$Q$81:$V$87,$X$81:$AF$87,$Q$89:$V$95,$X$89:$AF$95,$E$89:$O$95) -> 0.0083731524
A88: INM | B88: Non metallic minerals | C88: INDELC | D88: TJ | E88: =E75 -> 10792.69 | F88: =F75 -> 38077.519 | G88: =G75 -> 14212.516 | H88: =H75 -> 9298.0693 | I88: =I75 -> 12579 | J88: =J75 -> 15537.438 | K88: =K75 -> 35010.218 | L88: =L75 -> 36498.914 | ... AF88: =AF75 -> 119179 | AI88: =SUM(E88:O88,Q88:V88,X88:AF88)/SUM($E$81:$O$87,$Q$81:$V$87,$X$81:$AF$87,$Q$89:$V$95,$X$89:$AF$95,$E$89:$O$95) -> 0.16012572
A89: INM | B89: Non metallic minerals | C89: INDGAS | D89: TJ | E89: =IF(E$64<1,E15/E$64,E15) -> 3028.8511 | F89: =IF(F$64<1,F15/F$64,F15)-+EnergyBalance!F434 -> 64796.65 | G89: =IF(G$64<1,G15/G$64,G15) -> 0 | H89: =IF(H$64<1,H15/H$64,H15) -> 16488.295 | I89: =IF(I$64<1,I15/I$64,I15) -> 48090 | J89: =IF(J$64<1,J15/J$64,J15) -> 62807 | K89: =IF(K$64<1,K15/K$64,K15) -> 36923 | L89: =IF(L$64<1,L15/L$64,L15) -> 0 | M89: =IF(M$64<1,M15/M$64,M15) -> 49676 | N89: =IF(N$64<1,N15/N$64,N15) -> 36610 | O89: =IF(O$64<1,O15/O$64,O15) -> 366 | P89: =P15 -> 0 | Q89: =IF(Q$64<1,Q15/Q$64,Q15) -> 35224 | R89: =IF(R$64<1,R15/R$64,R15) -> 51785 | S89: =IF(S$64<1,S15/S$64,S15) -> 113986 | T89: =IF(T$64<1,T15/T$64,T15) -> 250235 | U89: =IF(U$64<1,U15/U$64,U15) -> 170235 | V89: =IF(V$64<1,V15/V$64,V15) -> 59334.139 | W89: =$W$65*AH89 -> 0 | X89: =IF(X$64<1,X15/X$64,X15) -> 32095 | Y89: =IF(Y$64<1,Y15/Y$64,Y15)-EnergyBalance!Y434 -> 56146.452 | Z89: =IF(Z$64<1,Z15/Z$64,Z15) -> 63356 | AA89: =IF(AA$64<1,AA15/AA$64,AA15)-EnergyBalance!AA434 -> 461109.09 | AB89: =IF(AB$64<1,AB15/AB$64,AB15) -> 48877 | AC89: =-(EnergyBalance!AC434*0.7) -> 40629.552 | AD89: =IF(AD$64<1,AD15/AD$64,AD15) -> 339508 | AE89: =IF(AE$64<1,AE15/AE$64,AE15) -> 24901 | AF89: =IF(AF$64<1,AF15/AF$64,AF15) -> 398884 | AH89: 0 | AI89: =SUM(E89:O89,Q89:V89,X89:AF89)/SUM($E$81:$O$87,$Q$81:$V$87,$X$81:$AF$87,$Q$89:$V$95,$X$89:$AF$95,$E$89:$O$95) -> 0.38203493
A90: INM | B90: Non metallic minerals | C90: INDHET | D90: TJ | E90: =IF(E$64<1,E16/E$64,E16) -> 0 | F90: =IF(F$64<1,F16/F$64,F16) -> 0 | G90: =IF(G$64<1,G16/G$64,G16) -> 0 | H90: =IF(H$64<1,H16/H$64,H16) -> 0 | I90: =IF(I$64<1,I16/I$64,I16) -> 0 | J90: =IF(J$64<1,J16/J$64,J16) -> 2193 | K90: =IF(K$64<1,K16/K$64,K16) -> 0 | L90: =IF(L$64<1,L16/L$64,L16) -> 0 | ... O90: =IF(O$64<1,O16/O$64,O16) -> 0 | P90: =P16 -> 0 | Q90: =IF(Q$64<1,Q16/Q$64,Q16) -> 5445 | R90: =IF(R$64<1,R16/R$64,R16) -> 36 | S90: =IF(S$64<1,S16/S$64,S16) -> 2192 | T90: =IF(T$64<1,T16/T$64,T16) -> 7389 | U90: =IF(U$64<1,U16/U$64,U16) -> 2120 | V90: =IF(V$64<1,V16/V$64,V16) -> 0 | W90: =$W$65*AH90 -> 0 | X90: =IF(X$64<1,X16/X$64,X16) -> 0 | Y90: =IF(Y$64<1,Y16/Y$64,Y16) -> 0 | Z90: =IF(Z$64<1,Z16/Z$64,Z16) -> 0 | AA90: =IF(AA$64<1,AA16/AA$64,AA16) -> 0 | AB90: =IF(AB$64<1,AB16/AB$64,AB16) -> 0 | AC90: =IF(AC$64<1,AC16/AC$64,AC16) -> 0 | AD90: =IF(AD$64<1,AD16/AD$64,AD16) -> 88621 | AE90: =IF(AE$64<1,AE16/AE$64,AE16) -> 119 | AF90: =IF(AF$64<1,AF16/AF$64,AF16) -> 149 | AH90: 0 | AI90: =SUM(E90:O90,Q90:V90,X90:AF90)/SUM($E$81:$O$87,$Q$81:$V$87,$X$81:$AF$87,$Q$89:$V$95,$X$89:$AF$95,$E$89:$O$95) -> 0.01677854
A91: INM | B91: Non metallic minerals | C91: INDLPG | D91: TJ | E91: =IF(E$64<1,E17/E$64,E17) -> 0 | F91: =IF(F$64<1,F17/F$64,F17) -> 4067.4577 | G91: =IF(G$64<1,G17/G$64,G17) -> 0 | H91: =IF(H$64<1,H17/H$64,H17) -> 0 | I91: =IF(I$64<1,I17/I$64,I17) -> 4180 | J91: =IF(J$64<1,J17/J$64,J17) -> 586 | K91: =IF(K$64<1,K17/K$64,K17) -> 3068 | L91: =IF(L$64<1,L17/L$64,L17) -> 0 | ... O91: =IF(O$64<1,O17/O$64,O17) -> 56 | P91: =P17 -> 29186 | Q91: =IF(Q$64<1,Q17/Q$64,Q17) -> 1003 | R91: =IF(R$64<1,R17/R$64,R17) -> 1542 | S91: =IF(S$64<1,S17/S$64,S17) -> 1014 | T91: =IF(T$64<1,T17/T$64,T17) -> 5649 | U91: =IF(U$64<1,U17/U$64,U17) -> 2633 | V91: =IF(V$64<1,V17/V$64,V17) -> 24330.312 | W91: =$W$65*AH91 -> 0 | X91: =IF(X$64<1,X17/X$64,X17) -> 3979 | Y91: =IF(Y$64<1,Y17/Y$64,Y17) -> 1449.8685 | Z91: =IF(Z$64<1,Z17/Z$64,Z17) -> 197 | AA91: =IF(AA$64<1,AA17/AA$64,AA17) -> 0 | AB91: =IF(AB$64<1,AB17/AB$64,AB17) -> 92 | AC91: =IF(AC$64<1,AC17/AC$64,AC17) -> 0 | AD91: =IF(AD$64<1,AD17/AD$64,AD17) -> 750 | AE91: =IF(AE$64<1,AE17/AE$64,AE17) -> 646 | AF91: =IF(AF$64<1,AF17/AF$64,AF17) -> 717 | AH91: 0 | AI91: =SUM(E91:O91,Q91:V91,X91:AF91)/SUM($E$81:$O$87,$Q$81:$V$87,$X$81:$AF$87,$Q$89:$V$95,$X$89:$AF$95,$E$89:$O$95) -> 0.0097740977
A92: INM | B92: Non metallic minerals | C92: INDOIL | D92: TJ | E92: =IF(E$64<1,E18/E$64,E18)-EnergyBalance!E434 -> 27390.108 | F92: =IF(F$64<1,F18/F$64,F18) -> 95875.009 | G92: =IF(G$64<1,G18/G$64,G18)-EnergyBalance!G434 -> 35567.557 | H92: =IF(H$64<1,H18/H$64,H18) -> 1992.2963 | I92: =IF(I$64<1,I18/I$64,I18) -> 2973 | J92: =IF(J$64<1,J18/J$64,J18) -> 3535 | K92: =IF(K$64<1,K18/K$64,K18) -> 13500 | L92: =IF(L$64<1,L18/L$64,L18) -> 21695 | M92: =IF(M$64<1,M18/M$64,M18) -> 119534 | N92: =IF(N$64<1,N18/N$64,N18) -> 21063 | O92: =IF(O$64<1,O18/O$64,O18) -> 9099 | P92: =P18 -> 337384 | Q92: =IF(Q$64<1,Q18/Q$64,Q18) -> 17309 | R92: =IF(R$64<1,R18/R$64,R18) -> 8882 | S92: =IF(S$64<1,S18/S$64,S18) -> 33565 | T92: =IF(T$64<1,T18/T$64,T18) -> 146259 | U92: =IF(U$64<1,U18/U$64,U18) -> 43306 | V92: =IF(V$64<1,V18/V$64,V18) -> 52298.569 | W92: =$W$65*AH92 -> 84890.072 | X92: =IF(X$64<1,X18/X$64,X18) -> 74298 | Y92: =IF(Y$64<1,Y18/Y$64,Y18) -> 59919.269 | Z92: =IF(Z$64<1,Z18/Z$64,Z18) -> 132992 | AA92: =IF(AA$64<1,AA18/AA$64,AA18) -> 0 | AB92: =IF(AB$64<1,AB18/AB$64,AB18) -> 133915 | AC92: =IF(AC$64<1,AC18/AC$64,AC18)-(EnergyBalance!AC434*0.3) -> 17412.665 | AD92: =IF(AD$64<1,AD18/AD$64,AD18) -> 22846 | AE92: =IF(AE$64<1,AE18/AE$64,AE18) -> 23025 | AF92: =IF(AF$64<1,AF18/AF$64,AF18) -> 48551 | AH92: 0.1 | AI92: =SUM(E92:O92,Q92:V92,X92:AF92)/SUM($E$81:$O$87,$Q$81:$V$87,$X$81:$AF$87,$Q$89:$V$95,$X$89:$AF$95,$E$89:$O$95) -> 0.18082874
A93: INM | B93: Non metallic minerals | C93: INDGEO | D93: TJ | E93: =IF(E$64<1,E19/E$64,E19) -> 0 | F93: =IF(F$64<1,F19/F$64,F19) -> 0 | G93: =IF(G$64<1,G19/G$64,G19) -> 0 | H93: =IF(H$64<1,H19/H$64,H19) -> 0 | I93: =IF(I$64<1,I19/I$64,I19) -> 0 | J93: =IF(J$64<1,J19/J$64,J19) -> 0 | K93: =IF(K$64<1,K19/K$64,K19) -> 0 | L93: =IF(L$64<1,L19/L$64,L19) -> 0 | ... O93: =IF(O$64<1,O19/O$64,O19) -> 0 | P93: =P19 -> 0 | Q93: =IF(Q$64<1,Q19/Q$64,Q19) -> 0 | R93: =IF(R$64<1,R19/R$64,R19) -> 0 | S93: 0 | T93: =IF(T$64<1,T19/T$64,T19) -> 0 | U93: =IF(U$64<1,U19/U$64,U19) -> 0 | V93: =IF(V$64<1,V19/V$64,V19) -> 0 | W93: =$W$65*AH93 -> 0 | X93: =IF(X$64<1,X19/X$64,X19) -> 0 | Y93: =IF(Y$64<1,Y19/Y$64,Y19) -> 0 | Z93: =IF(Z$64<1,Z19/Z$64,Z19) -> 0 | AA93: =IF(AA$64<1,AA19/AA$64,AA19) -> 0 | AB93: =IF(AB$64<1,AB19/AB$64,AB19) -> 0 | AC93: =IF(AC$64<1,AC19/AC$64,AC19) -> 0 | AD93: =IF(AD$64<1,AD19/AD$64,AD19) -> 0 | AE93: =IF(AE$64<1,AE19/AE$64,AE19) -> 0 | AF93: =IF(AF$64<1,AF19/AF$64,AF19) -> 0 | AH93: 0 | AI93: =SUM(E93:O93,Q93:V93,X93:AF93)/SUM($E$81:$O$87,$Q$81:$V$87,$X$81:$AF$87,$Q$89:$V$95,$X$89:$AF$95,$E$89:$O$95) -> 0
A94: INM | B94: Non metallic minerals | C94: INDCSP | D94: TJ | E94: =IF(E$64<1,E20/E$64,E20) -> 0 | F94: =IF(F$64<1,F20/F$64,F20) -> 0 | G94: =IF(G$64<1,G20/G$64,G20) -> 0 | H94: =IF(H$64<1,H20/H$64,H20) -> 0 | I94: =IF(I$64<1,I20/I$64,I20) -> 0 | J94: =IF(J$64<1,J20/J$64,J20) -> 0 | K94: =IF(K$64<1,K20/K$64,K20) -> 0 | L94: =IF(L$64<1,L20/L$64,L20) -> 0 | ... O94: =IF(O$64<1,O20/O$64,O20) -> 0 | P94: =P20 -> 0 | Q94: =IF(Q$64<1,Q20/Q$64,Q20) -> 0 | R94: =IF(R$64<1,R20/R$64,R20) -> 0 | S94: =IF(S$64<1,S20/S$64,S20) -> 0 | T94: =IF(T$64<1,T20/T$64,T20) -> 0 | U94: =IF(U$64<1,U20/U$64,U20) -> 0 | V94: =IF(V$64<1,V20/V$64,V20) -> 0 | W94: =$W$65*AH94 -> 0 | X94: =IF(X$64<1,X20/X$64,X20) -> 0 | Y94: =IF(Y$64<1,Y20/Y$64,Y20) -> 0 | Z94: =IF(Z$64<1,Z20/Z$64,Z20) -> 0 | AA94: =IF(AA$64<1,AA20/AA$64,AA20) -> 0 | AB94: =IF(AB$64<1,AB20/AB$64,AB20) -> 0 | AC94: =IF(AC$64<1,AC20/AC$64,AC20) -> 0 | AD94: =IF(AD$64<1,AD20/AD$64,AD20) -> 0 | AE94: =IF(AE$64<1,AE20/AE$64,AE20) -> 0 | AF94: =IF(AF$64<1,AF20/AF$64,AF20) -> 0 | AH94: 0 | AI94: =SUM(E94:O94,Q94:V94,X94:AF94)/SUM($E$81:$O$87,$Q$81:$V$87,$X$81:$AF$87,$Q$89:$V$95,$X$89:$AF$95,$E$89:$O$95) -> 0
A95: INM | B95: Non metallic minerals | C95: INDWAS | D95: TJ | E95: =IF(E$64<1,E21/E$64,E21) -> 0 | F95: =IF(F$64<1,F21/F$64,F21)+EnergyBalance!F444 -> 2021 | G95: =IF(G$64<1,G21/G$64,G21) -> 0 | H95: =IF(H$64<1,H21/H$64,H21) -> 0 | I95: =IF(I$64<1,I21/I$64,I21) -> 0 | J95: =IF(J$64<1,J21/J$64,J21) -> 0 | K95: =IF(K$64<1,K21/K$64,K21) -> 0 | L95: =IF(L$64<1,L21/L$64,L21) -> 0 | M95: =IF(M$64<1,M21/M$64,M21) -> 0 | N95: =IF(N$64<1,N21/N$64,N21) -> 5567 | O95: =IF(O$64<1,O21/O$64,O21) -> 0 | P95: =P21 -> 0 | Q95: =IF(Q$64<1,Q21/Q$64,Q21) -> 17 | R95: =IF(R$64<1,R21/R$64,R21) -> 8213 | S95: =IF(S$64<1,S21/S$64,S21) -> 72182 | T95: =IF(T$64<1,T21/T$64,T21) -> 28918 | U95: =IF(U$64<1,U21/U$64,U21) -> 74907 | V95: =IF(V$64<1,V21/V$64,V21) -> 0 | W95: =$W$65*AH95 -> 0 | X95: =IF(X$64<1,X21/X$64,X21) -> 23831 | Y95: =IF(Y$64<1,Y21/Y$64,Y21) -> 67.315325 | Z95: =IF(Z$64<1,Z21/Z$64,Z21) -> 21143 | AA95: =IF(AA$64<1,AA21/AA$64,AA21) -> 0 | AB95: =IF(AB$64<1,AB21/AB$64,AB21) -> 0 | AC95: =IF(AC$64<1,AC21/AC$64,AC21) -> 0 | AD95: =IF(AD$64<1,AD21/AD$64,AD21) -> 3043 | AE95: =IF(AE$64<1,AE21/AE$64,AE21) -> 29803 | AF95: =IF(AF$64<1,AF21/AF$64,AF21) -> 7 | AH95: 0 | AI95: =SUM(E95:O95,Q95:V95,X95:AF95)/SUM($E$81:$O$87,$Q$81:$V$87,$X$81:$AF$87,$Q$89:$V$95,$X$89:$AF$95,$E$89:$O$95) -> 0.041800565
D97: Check (must equal 1, unless adjusted) | E97: =SUM(E81:E95)/(E75+E65) -> 1 | F97: =SUM(F81:F95)/(F75+F65) -> 0.99761534 | G97: =SUM(G81:G95)/(G75+G65) -> 1 | H97: =SUM(H81:H95)/(H75+H65) -> 1 | I97: =SUM(I81:I95)/(I75+I65) -> 1 | J97: =SUM(J81:J95)/(J75+J65) -> 1 | K97: =SUM(K81:K95)/(K75+K65) -> 1 | L97: =SUM(L81:L95)/(L75+L65) -> 1 | ... AF97: =SUM(AF81:AF95)/(AF75+AF65) -> 1
A99: Energy consumption
A101: CEMENT - FUEL CONSUMPTION & INTENSITY (adjustment down in some case due to insufficient energy from NES) | D101: Deficit = <1 in sector energy for cement | E101: =E64 -> 0.49061508 | F101: =F64 -> 0.73166095 | G101: =G64 -> 0.38022172 | H101: =H64 -> 0.95467726 | I101: =I64 -> 3.4850421 | J101: =J64 -> 1.2451544 | K101: =K64 -> 1.5474316 | L101: =L64 -> 1.1847569 | ... AF101: =AF64 -> 2.2902477
A102: Subsector | B102: Primary energy commodity | D102: Unit | E102: AFE | F102: AFN | G102: AFW | H102: AFZ | I102: ANZ | J102: ASC | K102: ASE | L102: ASO | M102: BRA | N102: CAN | O102: CHL | P102: CHN | Q102: ENE | R102: ENW | S102: EUE | T102: EUM | U102: EUW | V102: IDN | W102: IND | X102: JPN | Y102: LAM | Z102: MDA | AA102: MEA | AB102: MEX | AC102: NIG | AD102: RUS | AE102: SKT | AF102: USA
A103: ICM | B103: Cement | C103: =C81 -> INDBFG | D103: TJ | E103: =E81 -> 0 | F103: =F81 -> 0 | G103: =G81 -> 0 | H103: =H81 -> 0 | I103: =SUM(I$58:I$59)*(I81/SUM(I$81:I$87,I$89:I$95)) -> 0 | J103: =SUM(J$58:J$59)*(J81/SUM(J$81:J$87,J$89:J$95)) -> 0 | K103: =SUM(K$58:K$59)*(K81/SUM(K$81:K$87,K$89:K$95)) -> 0 | L103: =SUM(L$58:L$59)*(L81/SUM(L$81:L$87,L$89:L$95)) -> 0 | M103: =SUM(M$58:M$59)*(M81/SUM(M$81:M$87,M$89:M$95)) -> 0 | N103: =SUM(N$58:N$59)*(N81/SUM(N$81:N$87,N$89:N$95)) -> 0 | O103: =SUM(O$58:O$59)*(O81/SUM(O$81:O$87,O$89:O$95)) -> 0 | P103: =P81 -> 0 | Q103: =SUM(Q$58:Q$59)*(Q81/SUM(Q$81:Q$87,Q$89:Q$95)) -> 0 | R103: =SUM(R$58:R$59)*(R81/SUM(R$81:R$87,R$89:R$95)) -> 76.569041 | S103: =SUM(S$58:S$59)*(S81/SUM(S$81:S$87,S$89:S$95)) -> 0 | T103: =SUM(T$58:T$59)*(T81/SUM(T$81:T$87,T$89:T$95)) -> 0 | U103: =SUM(U$58:U$59)*(U81/SUM(U$81:U$87,U$89:U$95)) -> 0 | V103: =V81 -> 0 | W103: =W81 -> 0 | X103: =SUM(X$58:X$59)*(X81/SUM(X$81:X$87,X$89:X$95)) -> 136.09216 | Y103: =Y81 -> 0 | Z103: =SUM(Z$58:Z$59)*(Z81/SUM(Z$81:Z$87,Z$89:Z$95)) -> 0 | AA103: =AA81 -> 0 | AB103: =SUM(AB$58:AB$59)*(AB81/SUM(AB$81:AB$87,AB$89:AB$95)) -> 0 | AC103: =AC81 -> 0 | AD103: =SUM(AD$58:AD$59)*(AD81/SUM(AD$81:AD$87,AD$89:AD$95)) -> 0 | AE103: =AE81 -> 0 | AF103: =SUM(AF$58:AF$59)*(AF81/SUM(AF$81:AF$87,AF$89:AF$95)) -> 0
A104: ICM | B104: Cement | C104: =C82 -> INDBGS | D104: TJ | E104: =E82 -> 0 | F104: =F82 -> 0 | G104: =G82 -> 0 | H104: =H82 -> 0 | I104: =SUM(I$58:I$59)*(I82/SUM(I$81:I$87,I$89:I$95)) -> 23.816068 | J104: =SUM(J$58:J$59)*(J82/SUM(J$81:J$87,J$89:J$95)) -> 0 | K104: =SUM(K$58:K$59)*(K82/SUM(K$81:K$87,K$89:K$95)) -> 0 | L104: =SUM(L$58:L$59)*(L82/SUM(L$81:L$87,L$89:L$95)) -> 0 | M104: =SUM(M$58:M$59)*(M82/SUM(M$81:M$87,M$89:M$95)) -> 0 | N104: =SUM(N$58:N$59)*(N82/SUM(N$81:N$87,N$89:N$95)) -> 0 | O104: =SUM(O$58:O$59)*(O82/SUM(O$81:O$87,O$89:O$95)) -> 0 | P104: =P82 -> 0 | Q104: =SUM(Q$58:Q$59)*(Q82/SUM(Q$81:Q$87,Q$89:Q$95)) -> 0 | R104: =SUM(R$58:R$59)*(R82/SUM(R$81:R$87,R$89:R$95)) -> 6.0327123 | S104: =SUM(S$58:S$59)*(S82/SUM(S$81:S$87,S$89:S$95)) -> 12.607008 | T104: =SUM(T$58:T$59)*(T82/SUM(T$81:T$87,T$89:T$95)) -> 118.20623 | U104: =SUM(U$58:U$59)*(U82/SUM(U$81:U$87,U$89:U$95)) -> 44.285013 | V104: =V82 -> 0 | W104: =W82 -> 0 | X104: =SUM(X$58:X$59)*(X82/SUM(X$81:X$87,X$89:X$95)) -> 0 | Y104: =Y82 -> 0 | Z104: =SUM(Z$58:Z$59)*(Z82/SUM(Z$81:Z$87,Z$89:Z$95)) -> 0 | AA104: =AA82 -> 0 | AB104: =SUM(AB$58:AB$59)*(AB82/SUM(AB$81:AB$87,AB$89:AB$95)) -> 0 | AC104: =AC82 -> 0 | AD104: =SUM(AD$58:AD$59)*(AD82/SUM(AD$81:AD$87,AD$89:AD$95)) -> 0 | AE104: =AE82 -> 0 | AF104: =SUM(AF$58:AF$59)*(AF82/SUM(AF$81:AF$87,AF$89:AF$95)) -> 0
